Workbook

Sheet Auswertung
B1: Satz / Modell | C1: Inhalt | D1: Punkte [0-10] | E1: Punkte kumuliert | G1: Satz | H1: d32_el2_dl2_ff128-ep500 | I1: d64_el1_dl1_ff64-ep1000 | J1: d64_el2_dl2_ff64-ep500 | K1: d64_el2_dl2_ff64-ep1000 | L1: d64_el2_dl2_ff128-ep1000 | M1: d64_el3_dl3_ff128-ep1000 | O1: d32_el2_dl2_ff128-ep500 | P1: d64_el1_dl1_ff64-ep1000 | Q1: d64_el2_dl2_ff64-ep500 | R1: d64_el2_dl2_ff64-ep1000 | S1: d64_el2_dl2_ff128-ep1000 | T1: d64_el3_dl3_ff128-ep1000 | V1: d32_el2_dl2_ff128-ep500 | W1: d64_el1_dl1_ff64-ep1000 | X1: d64_el2_dl2_ff64-ep500 | Y1: d64_el2_dl2_ff64-ep1000 | Z1: d64_el2_dl2_ff128-ep1000 | AA1: d64_el3_dl3_ff128-ep1000
A2: 0 | B2: 1 | C2: Guten Morgen! | E2: =D2 -> 0 | G2: 1 | H2: {=INDEX($D$2:$D$701, (ROW()-ROW($G$2))*7 + (COLUMN()-COLUMN($G$2)) + 1)} -> 5 | I2: {=INDEX($D$2:$D$701, (ROW()-ROW($G$2))*7 + (COLUMN()-COLUMN($G$2)) + 1)} -> 1 | J2: {=INDEX($D$2:$D$701, (ROW()-ROW($G$2))*7 + (COLUMN()-COLUMN($G$2)) + 1)} -> 0 | K2: {=INDEX($D$2:$D$701, (ROW()-ROW($G$2))*7 + (COLUMN()-COLUMN($G$2)) + 1)} -> 0 | L2: {=INDEX($D$2:$D$701, (ROW()-ROW($G$2))*7 + (COLUMN()-COLUMN($G$2)) + 1)} -> 1 | M2: {=INDEX($D$2:$D$701, (ROW()-ROW($G$2))*7 + (COLUMN()-COLUMN($G$2)) + 1)} -> 0 | O2: =IF(H2=MAX(Tabelle4[[#This Row],[d32_el2_dl2_ff128-ep500]:[d64_el3_dl3_ff128-ep1000]]),1,0) -> 1 | P2: =IF(I2=MAX(Tabelle4[[#This Row],[d32_el2_dl2_ff128-ep500]:[d64_el3_dl3_ff128-ep1000]]),1,0) -> 0 | Q2: =IF(J2=MAX(Tabelle4[[#This Row],[d32_el2_dl2_ff128-ep500]:[d64_el3_dl3_ff128-ep1000]]),1,0) -> 0 | R2: =IF(K2=MAX(Tabelle4[[#This Row],[d32_el2_dl2_ff128-ep500]:[d64_el3_dl3_ff128-ep1000]]),1,0) -> 0 | S2: =IF(L2=MAX(Tabelle4[[#This Row],[d32_el2_dl2_ff128-ep500]:[d64_el3_dl3_ff128-ep1000]]),1,0) -> 0 | T2: =IF(M2=MAX(Tabelle4[[#This Row],[d32_el2_dl2_ff128-ep500]:[d64_el3_dl3_ff128-ep1000]]),1,0) -> 0 | V2: =IF(H2=MIN(Tabelle4[[#This Row],[d32_el2_dl2_ff128-ep500]:[d64_el3_dl3_ff128-ep1000]]),1,0) -> 0 | W2: =IF(I2=MIN(Tabelle4[[#This Row],[d32_el2_dl2_ff128-ep500]:[d64_el3_dl3_ff128-ep1000]]),1,0) -> 0 | X2: =IF(J2=MIN(Tabelle4[[#This Row],[d32_el2_dl2_ff128-ep500]:[d64_el3_dl3_ff128-ep1000]]),1,0) -> 1 | Y2: =IF(K2=MIN(Tabelle4[[#This Row],[d32_el2_dl2_ff128-ep500]:[d64_el3_dl3_ff128-ep1000]]),1,0) -> 1 | Z2: =IF(L2=MIN(Tabelle4[[#This Row],[d32_el2_dl2_ff128-ep500]:[d64_el3_dl3_ff128-ep1000]]),1,0) -> 0 | AA2: =IF(M2=MIN(Tabelle4[[#This Row],[d32_el2_dl2_ff128-ep500]:[d64_el3_dl3_ff128-ep1000]]),1,0) -> 1
A3: 1 | B3: d32_el2_dl2_ff128-ep500 | C3: ['morgen', 'material'] | D3: 5 | E3: =D3 -> 5 | G3: 2 | H3: {=INDEX($D$2:$D$701, (ROW()-ROW($G$2))*7 + (COLUMN()-COLUMN($G$2)) + 1)} -> 7 | I3: {=INDEX($D$2:$D$701, (ROW()-ROW($G$2))*7 + (COLUMN()-COLUMN($G$2)) + 1)} -> 7 | J3: {=INDEX($D$2:$D$701, (ROW()-ROW($G$2))*7 + (COLUMN()-COLUMN($G$2)) + 1)} -> 7 | K3: {=INDEX($D$2:$D$701, (ROW()-ROW($G$2))*7 + (COLUMN()-COLUMN($G$2)) + 1)} -> 7 | L3: {=INDEX($D$2:$D$701, (ROW()-ROW($G$2))*7 + (COLUMN()-COLUMN($G$2)) + 1)} -> 7 | M3: {=INDEX($D$2:$D$701, (ROW()-ROW($G$2))*7 + (COLUMN()-COLUMN($G$2)) + 1)} -> 7 | O3: =IF(H3=MAX(Tabelle4[[#This Row],[d32_el2_dl2_ff128-ep500]:[d64_el3_dl3_ff128-ep1000]]),1,0) -> 1 | P3: =IF(I3=MAX(Tabelle4[[#This Row],[d32_el2_dl2_ff128-ep500]:[d64_el3_dl3_ff128-ep1000]]),1,0) -> 1 | Q3: =IF(J3=MAX(Tabelle4[[#This Row],[d32_el2_dl2_ff128-ep500]:[d64_el3_dl3_ff128-ep1000]]),1,0) -> 1 | R3: =IF(K3=MAX(Tabelle4[[#This Row],[d32_el2_dl2_ff128-ep500]:[d64_el3_dl3_ff128-ep1000]]),1,0) -> 1 | S3: =IF(L3=MAX(Tabelle4[[#This Row],[d32_el2_dl2_ff128-ep500]:[d64_el3_dl3_ff128-ep1000]]),1,0) -> 1 | T3: =IF(M3=MAX(Tabelle4[[#This Row],[d32_el2_dl2_ff128-ep500]:[d64_el3_dl3_ff128-ep1000]]),1,0) -> 1 | V3: =IF(H3=MIN(Tabelle4[[#This Row],[d32_el2_dl2_ff128-ep500]:[d64_el3_dl3_ff128-ep1000]]),1,0) -> 1 | W3: =IF(I3=MIN(Tabelle4[[#This Row],[d32_el2_dl2_ff128-ep500]:[d64_el3_dl3_ff128-ep1000]]),1,0) -> 1 | X3: =IF(J3=MIN(Tabelle4[[#This Row],[d32_el2_dl2_ff128-ep500]:[d64_el3_dl3_ff128-ep1000]]),1,0) -> 1 | Y3: =IF(K3=MIN(Tabelle4[[#This Row],[d32_el2_dl2_ff128-ep500]:[d64_el3_dl3_ff128-ep1000]]),1,0) -> 1 | Z3: =IF(L3=MIN(Tabelle4[[#This Row],[d32_el2_dl2_ff128-ep500]:[d64_el3_dl3_ff128-ep1000]]),1,0) -> 1 | AA3: =IF(M3=MIN(Tabelle4[[#This Row],[d32_el2_dl2_ff128-ep500]:[d64_el3_dl3_ff128-ep1000]]),1,0) -> 1
A4: 2 | B4: d64_el1_dl1_ff64-ep1000 | C4: ['morgen', 'sonne wandern', 'sonne wandern', 'sonne wandern', 'sonne wandern', 'sonne wandern', 'sonne wandern', 'sonne wandern', 'sonne wandern', 'sonne wandern', 'sonne wandern', 'sonne wandern', 'sonne wandern', 'sonne wandern', 'sonne wandern', 'sonne wandern', 'sonne wandern', 'sonne wandern', 'sonne wandern', 'sonne wandern'] | D4: 1 | E4: =D4 -> 1 | G4: 3 | H4: {=INDEX($D$2:$D$701, (ROW()-ROW($G$2))*7 + (COLUMN()-COLUMN($G$2)) + 1)} -> 2 | I4: {=INDEX($D$2:$D$701, (ROW()-ROW($G$2))*7 + (COLUMN()-COLUMN($G$2)) + 1)} -> 4 | J4: {=INDEX($D$2:$D$701, (ROW()-ROW($G$2))*7 + (COLUMN()-COLUMN($G$2)) + 1)} -> 10 | K4: {=INDEX($D$2:$D$701, (ROW()-ROW($G$2))*7 + (COLUMN()-COLUMN($G$2)) + 1)} -> 10 | L4: {=INDEX($D$2:$D$701, (ROW()-ROW($G$2))*7 + (COLUMN()-COLUMN($G$2)) + 1)} -> 9 | M4: {=INDEX($D$2:$D$701, (ROW()-ROW($G$2))*7 + (COLUMN()-COLUMN($G$2)) + 1)} -> 8 | O4: =IF(H4=MAX(Tabelle4[[#This Row],[d32_el2_dl2_ff128-ep500]:[d64_el3_dl3_ff128-ep1000]]),1,0) -> 0 | P4: =IF(I4=MAX(Tabelle4[[#This Row],[d32_el2_dl2_ff128-ep500]:[d64_el3_dl3_ff128-ep1000]]),1,0) -> 0 | Q4: =IF(J4=MAX(Tabelle4[[#This Row],[d32_el2_dl2_ff128-ep500]:[d64_el3_dl3_ff128-ep1000]]),1,0) -> 1 | R4: =IF(K4=MAX(Tabelle4[[#This Row],[d32_el2_dl2_ff128-ep500]:[d64_el3_dl3_ff128-ep1000]]),1,0) -> 1 | S4: =IF(L4=MAX(Tabelle4[[#This Row],[d32_el2_dl2_ff128-ep500]:[d64_el3_dl3_ff128-ep1000]]),1,0) -> 0 | T4: =IF(M4=MAX(Tabelle4[[#This Row],[d32_el2_dl2_ff128-ep500]:[d64_el3_dl3_ff128-ep1000]]),1,0) -> 0 | V4: =IF(H4=MIN(Tabelle4[[#This Row],[d32_el2_dl2_ff128-ep500]:[d64_el3_dl3_ff128-ep1000]]),1,0) -> 1 | W4: =IF(I4=MIN(Tabelle4[[#This Row],[d32_el2_dl2_ff128-ep500]:[d64_el3_dl3_ff128-ep1000]]),1,0) -> 0 | X4: =IF(J4=MIN(Tabelle4[[#This Row],[d32_el2_dl2_ff128-ep500]:[d64_el3_dl3_ff128-ep1000]]),1,0) -> 0 | Y4: =IF(K4=MIN(Tabelle4[[#This Row],[d32_el2_dl2_ff128-ep500]:[d64_el3_dl3_ff128-ep1000]]),1,0) -> 0 | Z4: =IF(L4=MIN(Tabelle4[[#This Row],[d32_el2_dl2_ff128-ep500]:[d64_el3_dl3_ff128-ep1000]]),1,0) -> 0 | AA4: =IF(M4=MIN(Tabelle4[[#This Row],[d32_el2_dl2_ff128-ep500]:[d64_el3_dl3_ff128-ep1000]]),1,0) -> 0
A5: 3 | B5: d64_el2_dl2_ff64-ep500 | C5: ['ich', 'selbst', 'sorgfältig', 'verschwommen'] | D5: 0 | E5: =D5 -> 0 | G5: 4 | H5: {=INDEX($D$2:$D$701, (ROW()-ROW($G$2))*7 + (COLUMN()-COLUMN($G$2)) + 1)} -> 10 | I5: {=INDEX($D$2:$D$701, (ROW()-ROW($G$2))*7 + (COLUMN()-COLUMN($G$2)) + 1)} -> 6 | J5: {=INDEX($D$2:$D$701, (ROW()-ROW($G$2))*7 + (COLUMN()-COLUMN($G$2)) + 1)} -> 7 | K5: {=INDEX($D$2:$D$701, (ROW()-ROW($G$2))*7 + (COLUMN()-COLUMN($G$2)) + 1)} -> 7 | L5: {=INDEX($D$2:$D$701, (ROW()-ROW($G$2))*7 + (COLUMN()-COLUMN($G$2)) + 1)} -> 5 | M5: {=INDEX($D$2:$D$701, (ROW()-ROW($G$2))*7 + (COLUMN()-COLUMN($G$2)) + 1)} -> 10 | O5: =IF(H5=MAX(Tabelle4[[#This Row],[d32_el2_dl2_ff128-ep500]:[d64_el3_dl3_ff128-ep1000]]),1,0) -> 1 | P5: =IF(I5=MAX(Tabelle4[[#This Row],[d32_el2_dl2_ff128-ep500]:[d64_el3_dl3_ff128-ep1000]]),1,0) -> 0 | Q5: =IF(J5=MAX(Tabelle4[[#This Row],[d32_el2_dl2_ff128-ep500]:[d64_el3_dl3_ff128-ep1000]]),1,0) -> 0 | R5: =IF(K5=MAX(Tabelle4[[#This Row],[d32_el2_dl2_ff128-ep500]:[d64_el3_dl3_ff128-ep1000]]),1,0) -> 0 | S5: =IF(L5=MAX(Tabelle4[[#This Row],[d32_el2_dl2_ff128-ep500]:[d64_el3_dl3_ff128-ep1000]]),1,0) -> 0 | T5: =IF(M5=MAX(Tabelle4[[#This Row],[d32_el2_dl2_ff128-ep500]:[d64_el3_dl3_ff128-ep1000]]),1,0) -> 1 | V5: =IF(H5=MIN(Tabelle4[[#This Row],[d32_el2_dl2_ff128-ep500]:[d64_el3_dl3_ff128-ep1000]]),1,0) -> 0 | W5: =IF(I5=MIN(Tabelle4[[#This Row],[d32_el2_dl2_ff128-ep500]:[d64_el3_dl3_ff128-ep1000]]),1,0) -> 0 | X5: =IF(J5=MIN(Tabelle4[[#This Row],[d32_el2_dl2_ff128-ep500]:[d64_el3_dl3_ff128-ep1000]]),1,0) -> 0 | Y5: =IF(K5=MIN(Tabelle4[[#This Row],[d32_el2_dl2_ff128-ep500]:[d64_el3_dl3_ff128-ep1000]]),1,0) -> 0 | Z5: =IF(L5=MIN(Tabelle4[[#This Row],[d32_el2_dl2_ff128-ep500]:[d64_el3_dl3_ff128-ep1000]]),1,0) -> 1 | AA5: =IF(M5=MIN(Tabelle4[[#This Row],[d32_el2_dl2_ff128-ep500]:[d64_el3_dl3_ff128-ep1000]]),1,0) -> 0
A6: 4 | B6: d64_el2_dl2_ff64-ep1000 | C6: ['ich', 'für', 'ich', 'selbst', 'sorgfältig', 'verschwommen'] | D6: 0 | E6: =D6 -> 0 | G6: 5 | H6: {=INDEX($D$2:$D$701, (ROW()-ROW($G$2))*7 + (COLUMN()-COLUMN($G$2)) + 1)} -> 9 | I6: {=INDEX($D$2:$D$701, (ROW()-ROW($G$2))*7 + (COLUMN()-COLUMN($G$2)) + 1)} -> 8 | J6: {=INDEX($D$2:$D$701, (ROW()-ROW($G$2))*7 + (COLUMN()-COLUMN($G$2)) + 1)} -> 9 | K6: {=INDEX($D$2:$D$701, (ROW()-ROW($G$2))*7 + (COLUMN()-COLUMN($G$2)) + 1)} -> 9 | L6: {=INDEX($D$2:$D$701, (ROW()-ROW($G$2))*7 + (COLUMN()-COLUMN($G$2)) + 1)} -> 8 | M6: {=INDEX($D$2:$D$701, (ROW()-ROW($G$2))*7 + (COLUMN()-COLUMN($G$2)) + 1)} -> 9 | O6: =IF(H6=MAX(Tabelle4[[#This Row],[d32_el2_dl2_ff128-ep500]:[d64_el3_dl3_ff128-ep1000]]),1,0) -> 1 | P6: =IF(I6=MAX(Tabelle4[[#This Row],[d32_el2_dl2_ff128-ep500]:[d64_el3_dl3_ff128-ep1000]]),1,0) -> 0 | Q6: =IF(J6=MAX(Tabelle4[[#This Row],[d32_el2_dl2_ff128-ep500]:[d64_el3_dl3_ff128-ep1000]]),1,0) -> 1 | R6: =IF(K6=MAX(Tabelle4[[#This Row],[d32_el2_dl2_ff128-ep500]:[d64_el3_dl3_ff128-ep1000]]),1,0) -> 1 | S6: =IF(L6=MAX(Tabelle4[[#This Row],[d32_el2_dl2_ff128-ep500]:[d64_el3_dl3_ff128-ep1000]]),1,0) -> 0 | T6: =IF(M6=MAX(Tabelle4[[#This Row],[d32_el2_dl2_ff128-ep500]:[d64_el3_dl3_ff128-ep1000]]),1,0) -> 1 | V6: =IF(H6=MIN(Tabelle4[[#This Row],[d32_el2_dl2_ff128-ep500]:[d64_el3_dl3_ff128-ep1000]]),1,0) -> 0 | W6: =IF(I6=MIN(Tabelle4[[#This Row],[d32_el2_dl2_ff128-ep500]:[d64_el3_dl3_ff128-ep1000]]),1,0) -> 1 | X6: =IF(J6=MIN(Tabelle4[[#This Row],[d32_el2_dl2_ff128-ep500]:[d64_el3_dl3_ff128-ep1000]]),1,0) -> 0 | Y6: =IF(K6=MIN(Tabelle4[[#This Row],[d32_el2_dl2_ff128-ep500]:[d64_el3_dl3_ff128-ep1000]]),1,0) -> 0 | Z6: =IF(L6=MIN(Tabelle4[[#This Row],[d32_el2_dl2_ff128-ep500]:[d64_el3_dl3_ff128-ep1000]]),1,0) -> 1 | AA6: =IF(M6=MIN(Tabelle4[[#This Row],[d32_el2_dl2_ff128-ep500]:[d64_el3_dl3_ff128-ep1000]]),1,0) -> 0
A7: 5 | B7: d64_el2_dl2_ff128-ep1000 | C7: ['früh', 'entlassen'] | D7: 1 | E7: =D7 -> 1 | G7: 6 | H7: {=INDEX($D$2:$D$701, (ROW()-ROW($G$2))*7 + (COLUMN()-COLUMN($G$2)) + 1)} -> 5 | I7: {=INDEX($D$2:$D$701, (ROW()-ROW($G$2))*7 + (COLUMN()-COLUMN($G$2)) + 1)} -> 2 | J7: {=INDEX($D$2:$D$701, (ROW()-ROW($G$2))*7 + (COLUMN()-COLUMN($G$2)) + 1)} -> 1 | K7: {=INDEX($D$2:$D$701, (ROW()-ROW($G$2))*7 + (COLUMN()-COLUMN($G$2)) + 1)} -> 1 | L7: {=INDEX($D$2:$D$701, (ROW()-ROW($G$2))*7 + (COLUMN()-COLUMN($G$2)) + 1)} -> 5 | M7: {=INDEX($D$2:$D$701, (ROW()-ROW($G$2))*7 + (COLUMN()-COLUMN($G$2)) + 1)} -> 5 | O7: =IF(H7=MAX(Tabelle4[[#This Row],[d32_el2_dl2_ff128-ep500]:[d64_el3_dl3_ff128-ep1000]]),1,0) -> 1 | P7: =IF(I7=MAX(Tabelle4[[#This Row],[d32_el2_dl2_ff128-ep500]:[d64_el3_dl3_ff128-ep1000]]),1,0) -> 0 | Q7: =IF(J7=MAX(Tabelle4[[#This Row],[d32_el2_dl2_ff128-ep500]:[d64_el3_dl3_ff128-ep1000]]),1,0) -> 0 | R7: =IF(K7=MAX(Tabelle4[[#This Row],[d32_el2_dl2_ff128-ep500]:[d64_el3_dl3_ff128-ep1000]]),1,0) -> 0 | S7: =IF(L7=MAX(Tabelle4[[#This Row],[d32_el2_dl2_ff128-ep500]:[d64_el3_dl3_ff128-ep1000]]),1,0) -> 1 | T7: =IF(M7=MAX(Tabelle4[[#This Row],[d32_el2_dl2_ff128-ep500]:[d64_el3_dl3_ff128-ep1000]]),1,0) -> 1 | V7: =IF(H7=MIN(Tabelle4[[#This Row],[d32_el2_dl2_ff128-ep500]:[d64_el3_dl3_ff128-ep1000]]),1,0) -> 0 | W7: =IF(I7=MIN(Tabelle4[[#This Row],[d32_el2_dl2_ff128-ep500]:[d64_el3_dl3_ff128-ep1000]]),1,0) -> 0 | X7: =IF(J7=MIN(Tabelle4[[#This Row],[d32_el2_dl2_ff128-ep500]:[d64_el3_dl3_ff128-ep1000]]),1,0) -> 1 | Y7: =IF(K7=MIN(Tabelle4[[#This Row],[d32_el2_dl2_ff128-ep500]:[d64_el3_dl3_ff128-ep1000]]),1,0) -> 1 | Z7: =IF(L7=MIN(Tabelle4[[#This Row],[d32_el2_dl2_ff128-ep500]:[d64_el3_dl3_ff128-ep1000]]),1,0) -> 0 | AA7: =IF(M7=MIN(Tabelle4[[#This Row],[d32_el2_dl2_ff128-ep500]:[d64_el3_dl3_ff128-ep1000]]),1,0) -> 0
A8: 6 | B8: d64_el3_dl3_ff128-ep1000 | C8: ['ich', 'selbst', 'ich', 'sehen'] | D8: 0 | E8: =D8 -> 0 | G8: 7 | H8: {=INDEX($D$2:$D$701, (ROW()-ROW($G$2))*7 + (COLUMN()-COLUMN($G$2)) + 1)} -> 0 | I8: {=INDEX($D$2:$D$701, (ROW()-ROW($G$2))*7 + (COLUMN()-COLUMN($G$2)) + 1)} -> 1 | J8: {=INDEX($D$2:$D$701, (ROW()-ROW($G$2))*7 + (COLUMN()-COLUMN($G$2)) + 1)} -> 1 | K8: {=INDEX($D$2:$D$701, (ROW()-ROW($G$2))*7 + (COLUMN()-COLUMN($G$2)) + 1)} -> 1 | L8: {=INDEX($D$2:$D$701, (ROW()-ROW($G$2))*7 + (COLUMN()-COLUMN($G$2)) + 1)} -> 0 | M8: {=INDEX($D$2:$D$701, (ROW()-ROW($G$2))*7 + (COLUMN()-COLUMN($G$2)) + 1)} -> 0 | O8: =IF(H8=MAX(Tabelle4[[#This Row],[d32_el2_dl2_ff128-ep500]:[d64_el3_dl3_ff128-ep1000]]),1,0) -> 0 | P8: =IF(I8=MAX(Tabelle4[[#This Row],[d32_el2_dl2_ff128-ep500]:[d64_el3_dl3_ff128-ep1000]]),1,0) -> 1 | Q8: =IF(J8=MAX(Tabelle4[[#This Row],[d32_el2_dl2_ff128-ep500]:[d64_el3_dl3_ff128-ep1000]]),1,0) -> 1 | R8: =IF(K8=MAX(Tabelle4[[#This Row],[d32_el2_dl2_ff128-ep500]:[d64_el3_dl3_ff128-ep1000]]),1,0) -> 1 | S8: =IF(L8=MAX(Tabelle4[[#This Row],[d32_el2_dl2_ff128-ep500]:[d64_el3_dl3_ff128-ep1000]]),1,0) -> 0 | T8: =IF(M8=MAX(Tabelle4[[#This Row],[d32_el2_dl2_ff128-ep500]:[d64_el3_dl3_ff128-ep1000]]),1,0) -> 0 | V8: =IF(H8=MIN(Tabelle4[[#This Row],[d32_el2_dl2_ff128-ep500]:[d64_el3_dl3_ff128-ep1000]]),1,0) -> 1 | W8: =IF(I8=MIN(Tabelle4[[#This Row],[d32_el2_dl2_ff128-ep500]:[d64_el3_dl3_ff128-ep1000]]),1,0) -> 0 | X8: =IF(J8=MIN(Tabelle4[[#This Row],[d32_el2_dl2_ff128-ep500]:[d64_el3_dl3_ff128-ep1000]]),1,0) -> 0 | Y8: =IF(K8=MIN(Tabelle4[[#This Row],[d32_el2_dl2_ff128-ep500]:[d64_el3_dl3_ff128-ep1000]]),1,0) -> 0 | Z8: =IF(L8=MIN(Tabelle4[[#This Row],[d32_el2_dl2_ff128-ep500]:[d64_el3_dl3_ff128-ep1000]]),1,0) -> 1 | AA8: =IF(M8=MIN(Tabelle4[[#This Row],[d32_el2_dl2_ff128-ep500]:[d64_el3_dl3_ff128-ep1000]]),1,0) -> 1
A9: 0 | B9: 2 | C9: Wie geht es dir? | E9: =D9+E2 -> 0 | G9: 8 | H9: {=INDEX($D$2:$D$701, (ROW()-ROW($G$2))*7 + (COLUMN()-COLUMN($G$2)) + 1)} -> 6 | I9: {=INDEX($D$2:$D$701, (ROW()-ROW($G$2))*7 + (COLUMN()-COLUMN($G$2)) + 1)} -> 4 | J9: {=INDEX($D$2:$D$701, (ROW()-ROW($G$2))*7 + (COLUMN()-COLUMN($G$2)) + 1)} -> 5 | K9: {=INDEX($D$2:$D$701, (ROW()-ROW($G$2))*7 + (COLUMN()-COLUMN($G$2)) + 1)} -> 6 | L9: {=INDEX($D$2:$D$701, (ROW()-ROW($G$2))*7 + (COLUMN()-COLUMN($G$2)) + 1)} -> 6 | M9: {=INDEX($D$2:$D$701, (ROW()-ROW($G$2))*7 + (COLUMN()-COLUMN($G$2)) + 1)} -> 6 | O9: =IF(H9=MAX(Tabelle4[[#This Row],[d32_el2_dl2_ff128-ep500]:[d64_el3_dl3_ff128-ep1000]]),1,0) -> 1 | P9: =IF(I9=MAX(Tabelle4[[#This Row],[d32_el2_dl2_ff128-ep500]:[d64_el3_dl3_ff128-ep1000]]),1,0) -> 0 | Q9: =IF(J9=MAX(Tabelle4[[#This Row],[d32_el2_dl2_ff128-ep500]:[d64_el3_dl3_ff128-ep1000]]),1,0) -> 0 | R9: =IF(K9=MAX(Tabelle4[[#This Row],[d32_el2_dl2_ff128-ep500]:[d64_el3_dl3_ff128-ep1000]]),1,0) -> 1 | S9: =IF(L9=MAX(Tabelle4[[#This Row],[d32_el2_dl2_ff128-ep500]:[d64_el3_dl3_ff128-ep1000]]),1,0) -> 1 | T9: =IF(M9=MAX(Tabelle4[[#This Row],[d32_el2_dl2_ff128-ep500]:[d64_el3_dl3_ff128-ep1000]]),1,0) -> 1 | V9: =IF(H9=MIN(Tabelle4[[#This Row],[d32_el2_dl2_ff128-ep500]:[d64_el3_dl3_ff128-ep1000]]),1,0) -> 0 | W9: =IF(I9=MIN(Tabelle4[[#This Row],[d32_el2_dl2_ff128-ep500]:[d64_el3_dl3_ff128-ep1000]]),1,0) -> 1 | X9: =IF(J9=MIN(Tabelle4[[#This Row],[d32_el2_dl2_ff128-ep500]:[d64_el3_dl3_ff128-ep1000]]),1,0) -> 0 | Y9: =IF(K9=MIN(Tabelle4[[#This Row],[d32_el2_dl2_ff128-ep500]:[d64_el3_dl3_ff128-ep1000]]),1,0) -> 0 | Z9: =IF(L9=MIN(Tabelle4[[#This Row],[d32_el2_dl2_ff128-ep500]:[d64_el3_dl3_ff128-ep1000]]),1,0) -> 0 | AA9: =IF(M9=MIN(Tabelle4[[#This Row],[d32_el2_dl2_ff128-ep500]:[d64_el3_dl3_ff128-ep1000]]),1,0) -> 0
A10: 1 | B10: d32_el2_dl2_ff128-ep500 | C10: ['wie frage vergleich'] | D10: 7 | E10: =D10+E3 -> 12 | G10: 9 | H10: {=INDEX($D$2:$D$701, (ROW()-ROW($G$2))*7 + (COLUMN()-COLUMN($G$2)) + 1)} -> 4 | I10: {=INDEX($D$2:$D$701, (ROW()-ROW($G$2))*7 + (COLUMN()-COLUMN($G$2)) + 1)} -> 6 | J10: {=INDEX($D$2:$D$701, (ROW()-ROW($G$2))*7 + (COLUMN()-COLUMN($G$2)) + 1)} -> 0 | K10: {=INDEX($D$2:$D$701, (ROW()-ROW($G$2))*7 + (COLUMN()-COLUMN($G$2)) + 1)} -> 0 | L10: {=INDEX($D$2:$D$701, (ROW()-ROW($G$2))*7 + (COLUMN()-COLUMN($G$2)) + 1)} -> 6 | M10: {=INDEX($D$2:$D$701, (ROW()-ROW($G$2))*7 + (COLUMN()-COLUMN($G$2)) + 1)} -> 6 | O10: =IF(H10=MAX(Tabelle4[[#This Row],[d32_el2_dl2_ff128-ep500]:[d64_el3_dl3_ff128-ep1000]]),1,0) -> 0 | P10: =IF(I10=MAX(Tabelle4[[#This Row],[d32_el2_dl2_ff128-ep500]:[d64_el3_dl3_ff128-ep1000]]),1,0) -> 1 | Q10: =IF(J10=MAX(Tabelle4[[#This Row],[d32_el2_dl2_ff128-ep500]:[d64_el3_dl3_ff128-ep1000]]),1,0) -> 0 | R10: =IF(K10=MAX(Tabelle4[[#This Row],[d32_el2_dl2_ff128-ep500]:[d64_el3_dl3_ff128-ep1000]]),1,0) -> 0 | S10: =IF(L10=MAX(Tabelle4[[#This Row],[d32_el2_dl2_ff128-ep500]:[d64_el3_dl3_ff128-ep1000]]),1,0) -> 1 | T10: =IF(M10=MAX(Tabelle4[[#This Row],[d32_el2_dl2_ff128-ep500]:[d64_el3_dl3_ff128-ep1000]]),1,0) -> 1 | V10: =IF(H10=MIN(Tabelle4[[#This Row],[d32_el2_dl2_ff128-ep500]:[d64_el3_dl3_ff128-ep1000]]),1,0) -> 0 | W10: =IF(I10=MIN(Tabelle4[[#This Row],[d32_el2_dl2_ff128-ep500]:[d64_el3_dl3_ff128-ep1000]]),1,0) -> 0 | X10: =IF(J10=MIN(Tabelle4[[#This Row],[d32_el2_dl2_ff128-ep500]:[d64_el3_dl3_ff128-ep1000]]),1,0) -> 1 | Y10: =IF(K10=MIN(Tabelle4[[#This Row],[d32_el2_dl2_ff128-ep500]:[d64_el3_dl3_ff128-ep1000]]),1,0) -> 1 | Z10: =IF(L10=MIN(Tabelle4[[#This Row],[d32_el2_dl2_ff128-ep500]:[d64_el3_dl3_ff128-ep1000]]),1,0) -> 0 | AA10: =IF(M10=MIN(Tabelle4[[#This Row],[d32_el2_dl2_ff128-ep500]:[d64_el3_dl3_ff128-ep1000]]),1,0) -> 0
A11: 2 | B11: d64_el1_dl1_ff64-ep1000 | C11: ['wie frage vergleich'] | D11: 7 | E11: =D11+E4 -> 8 | G11: 10 | H11: {=INDEX($D$2:$D$701, (ROW()-ROW($G$2))*7 + (COLUMN()-COLUMN($G$2)) + 1)} -> 10 | I11: {=INDEX($D$2:$D$701, (ROW()-ROW($G$2))*7 + (COLUMN()-COLUMN($G$2)) + 1)} -> 10 | J11: {=INDEX($D$2:$D$701, (ROW()-ROW($G$2))*7 + (COLUMN()-COLUMN($G$2)) + 1)} -> 10 | K11: {=INDEX($D$2:$D$701, (ROW()-ROW($G$2))*7 + (COLUMN()-COLUMN($G$2)) + 1)} -> 10 | L11: {=INDEX($D$2:$D$701, (ROW()-ROW($G$2))*7 + (COLUMN()-COLUMN($G$2)) + 1)} -> 10 | M11: {=INDEX($D$2:$D$701, (ROW()-ROW($G$2))*7 + (COLUMN()-COLUMN($G$2)) + 1)} -> 10 | O11: =IF(H11=MAX(Tabelle4[[#This Row],[d32_el2_dl2_ff128-ep500]:[d64_el3_dl3_ff128-ep1000]]),1,0) -> 1 | P11: =IF(I11=MAX(Tabelle4[[#This Row],[d32_el2_dl2_ff128-ep500]:[d64_el3_dl3_ff128-ep1000]]),1,0) -> 1 | Q11: =IF(J11=MAX(Tabelle4[[#This Row],[d32_el2_dl2_ff128-ep500]:[d64_el3_dl3_ff128-ep1000]]),1,0) -> 1 | R11: =IF(K11=MAX(Tabelle4[[#This Row],[d32_el2_dl2_ff128-ep500]:[d64_el3_dl3_ff128-ep1000]]),1,0) -> 1 | S11: =IF(L11=MAX(Tabelle4[[#This Row],[d32_el2_dl2_ff128-ep500]:[d64_el3_dl3_ff128-ep1000]]),1,0) -> 1 | T11: =IF(M11=MAX(Tabelle4[[#This Row],[d32_el2_dl2_ff128-ep500]:[d64_el3_dl3_ff128-ep1000]]),1,0) -> 1 | V11: =IF(H11=MIN(Tabelle4[[#This Row],[d32_el2_dl2_ff128-ep500]:[d64_el3_dl3_ff128-ep1000]]),1,0) -> 1 | W11: =IF(I11=MIN(Tabelle4[[#This Row],[d32_el2_dl2_ff128-ep500]:[d64_el3_dl3_ff128-ep1000]]),1,0) -> 1 | X11: =IF(J11=MIN(Tabelle4[[#This Row],[d32_el2_dl2_ff128-ep500]:[d64_el3_dl3_ff128-ep1000]]),1,0) -> 1 | Y11: =IF(K11=MIN(Tabelle4[[#This Row],[d32_el2_dl2_ff128-ep500]:[d64_el3_dl3_ff128-ep1000]]),1,0) -> 1 | Z11: =IF(L11=MIN(Tabelle4[[#This Row],[d32_el2_dl2_ff128-ep500]:[d64_el3_dl3_ff128-ep1000]]),1,0) -> 1 | AA11: =IF(M11=MIN(Tabelle4[[#This Row],[d32_el2_dl2_ff128-ep500]:[d64_el3_dl3_ff128-ep1000]]),1,0) -> 1
A12: 3 | B12: d64_el2_dl2_ff64-ep500 | C12: ['wie frage vergleich'] | D12: 7 | E12: =D12+E5 -> 7 | G12: 11 | H12: {=INDEX($D$2:$D$701, (ROW()-ROW($G$2))*7 + (COLUMN()-COLUMN($G$2)) + 1)} -> 6 | I12: {=INDEX($D$2:$D$701, (ROW()-ROW($G$2))*7 + (COLUMN()-COLUMN($G$2)) + 1)} -> 6 | J12: {=INDEX($D$2:$D$701, (ROW()-ROW($G$2))*7 + (COLUMN()-COLUMN($G$2)) + 1)} -> 6 | K12: {=INDEX($D$2:$D$701, (ROW()-ROW($G$2))*7 + (COLUMN()-COLUMN($G$2)) + 1)} -> 6 | L12: {=INDEX($D$2:$D$701, (ROW()-ROW($G$2))*7 + (COLUMN()-COLUMN($G$2)) + 1)} -> 6 | M12: {=INDEX($D$2:$D$701, (ROW()-ROW($G$2))*7 + (COLUMN()-COLUMN($G$2)) + 1)} -> 4 | O12: =IF(H12=MAX(Tabelle4[[#This Row],[d32_el2_dl2_ff128-ep500]:[d64_el3_dl3_ff128-ep1000]]),1,0) -> 1 | P12: =IF(I12=MAX(Tabelle4[[#This Row],[d32_el2_dl2_ff128-ep500]:[d64_el3_dl3_ff128-ep1000]]),1,0) -> 1 | Q12: =IF(J12=MAX(Tabelle4[[#This Row],[d32_el2_dl2_ff128-ep500]:[d64_el3_dl3_ff128-ep1000]]),1,0) -> 1 | R12: =IF(K12=MAX(Tabelle4[[#This Row],[d32_el2_dl2_ff128-ep500]:[d64_el3_dl3_ff128-ep1000]]),1,0) -> 1 | S12: =IF(L12=MAX(Tabelle4[[#This Row],[d32_el2_dl2_ff128-ep500]:[d64_el3_dl3_ff128-ep1000]]),1,0) -> 1 | T12: =IF(M12=MAX(Tabelle4[[#This Row],[d32_el2_dl2_ff128-ep500]:[d64_el3_dl3_ff128-ep1000]]),1,0) -> 0 | V12: =IF(H12=MIN(Tabelle4[[#This Row],[d32_el2_dl2_ff128-ep500]:[d64_el3_dl3_ff128-ep1000]]),1,0) -> 0 | W12: =IF(I12=MIN(Tabelle4[[#This Row],[d32_el2_dl2_ff128-ep500]:[d64_el3_dl3_ff128-ep1000]]),1,0) -> 0 | X12: =IF(J12=MIN(Tabelle4[[#This Row],[d32_el2_dl2_ff128-ep500]:[d64_el3_dl3_ff128-ep1000]]),1,0) -> 0 | Y12: =IF(K12=MIN(Tabelle4[[#This Row],[d32_el2_dl2_ff128-ep500]:[d64_el3_dl3_ff128-ep1000]]),1,0) -> 0 | Z12: =IF(L12=MIN(Tabelle4[[#This Row],[d32_el2_dl2_ff128-ep500]:[d64_el3_dl3_ff128-ep1000]]),1,0) -> 0 | AA12: =IF(M12=MIN(Tabelle4[[#This Row],[d32_el2_dl2_ff128-ep500]:[d64_el3_dl3_ff128-ep1000]]),1,0) -> 1
A13: 4 | B13: d64_el2_dl2_ff64-ep1000 | C13: ['wie frage vergleich'] | D13: 7 | E13: =D13+E6 -> 7 | G13: 12 | H13: {=INDEX($D$2:$D$701, (ROW()-ROW($G$2))*7 + (COLUMN()-COLUMN($G$2)) + 1)} -> 0 | I13: {=INDEX($D$2:$D$701, (ROW()-ROW($G$2))*7 + (COLUMN()-COLUMN($G$2)) + 1)} -> 3 | J13: {=INDEX($D$2:$D$701, (ROW()-ROW($G$2))*7 + (COLUMN()-COLUMN($G$2)) + 1)} -> 0 | K13: {=INDEX($D$2:$D$701, (ROW()-ROW($G$2))*7 + (COLUMN()-COLUMN($G$2)) + 1)} -> 0 | L13: {=INDEX($D$2:$D$701, (ROW()-ROW($G$2))*7 + (COLUMN()-COLUMN($G$2)) + 1)} -> 0 | M13: {=INDEX($D$2:$D$701, (ROW()-ROW($G$2))*7 + (COLUMN()-COLUMN($G$2)) + 1)} -> 0 | O13: =IF(H13=MAX(Tabelle4[[#This Row],[d32_el2_dl2_ff128-ep500]:[d64_el3_dl3_ff128-ep1000]]),1,0) -> 0 | P13: =IF(I13=MAX(Tabelle4[[#This Row],[d32_el2_dl2_ff128-ep500]:[d64_el3_dl3_ff128-ep1000]]),1,0) -> 1 | Q13: =IF(J13=MAX(Tabelle4[[#This Row],[d32_el2_dl2_ff128-ep500]:[d64_el3_dl3_ff128-ep1000]]),1,0) -> 0 | R13: =IF(K13=MAX(Tabelle4[[#This Row],[d32_el2_dl2_ff128-ep500]:[d64_el3_dl3_ff128-ep1000]]),1,0) -> 0 | S13: =IF(L13=MAX(Tabelle4[[#This Row],[d32_el2_dl2_ff128-ep500]:[d64_el3_dl3_ff128-ep1000]]),1,0) -> 0 | T13: =IF(M13=MAX(Tabelle4[[#This Row],[d32_el2_dl2_ff128-ep500]:[d64_el3_dl3_ff128-ep1000]]),1,0) -> 0 | V13: =IF(H13=MIN(Tabelle4[[#This Row],[d32_el2_dl2_ff128-ep500]:[d64_el3_dl3_ff128-ep1000]]),1,0) -> 1 | W13: =IF(I13=MIN(Tabelle4[[#This Row],[d32_el2_dl2_ff128-ep500]:[d64_el3_dl3_ff128-ep1000]]),1,0) -> 0 | X13: =IF(J13=MIN(Tabelle4[[#This Row],[d32_el2_dl2_ff128-ep500]:[d64_el3_dl3_ff128-ep1000]]),1,0) -> 1 | Y13: =IF(K13=MIN(Tabelle4[[#This Row],[d32_el2_dl2_ff128-ep500]:[d64_el3_dl3_ff128-ep1000]]),1,0) -> 1 | Z13: =IF(L13=MIN(Tabelle4[[#This Row],[d32_el2_dl2_ff128-ep500]:[d64_el3_dl3_ff128-ep1000]]),1,0) -> 1 | AA13: =IF(M13=MIN(Tabelle4[[#This Row],[d32_el2_dl2_ff128-ep500]:[d64_el3_dl3_ff128-ep1000]]),1,0) -> 1
A14: 5 | B14: d64_el2_dl2_ff128-ep1000 | C14: ['wie frage vergleich'] | D14: 7 | E14: =D14+E7 -> 8 | G14: 13 | H14: {=INDEX($D$2:$D$701, (ROW()-ROW($G$2))*7 + (COLUMN()-COLUMN($G$2)) + 1)} -> 10 | I14: {=INDEX($D$2:$D$701, (ROW()-ROW($G$2))*7 + (COLUMN()-COLUMN($G$2)) + 1)} -> 10 | J14: {=INDEX($D$2:$D$701, (ROW()-ROW($G$2))*7 + (COLUMN()-COLUMN($G$2)) + 1)} -> 9 | K14: {=INDEX($D$2:$D$701, (ROW()-ROW($G$2))*7 + (COLUMN()-COLUMN($G$2)) + 1)} -> 3 | L14: {=INDEX($D$2:$D$701, (ROW()-ROW($G$2))*7 + (COLUMN()-COLUMN($G$2)) + 1)} -> 9 | M14: {=INDEX($D$2:$D$701, (ROW()-ROW($G$2))*7 + (COLUMN()-COLUMN($G$2)) + 1)} -> 9 | O14: =IF(H14=MAX(Tabelle4[[#This Row],[d32_el2_dl2_ff128-ep500]:[d64_el3_dl3_ff128-ep1000]]),1,0) -> 1 | P14: =IF(I14=MAX(Tabelle4[[#This Row],[d32_el2_dl2_ff128-ep500]:[d64_el3_dl3_ff128-ep1000]]),1,0) -> 1 | Q14: =IF(J14=MAX(Tabelle4[[#This Row],[d32_el2_dl2_ff128-ep500]:[d64_el3_dl3_ff128-ep1000]]),1,0) -> 0 | R14: =IF(K14=MAX(Tabelle4[[#This Row],[d32_el2_dl2_ff128-ep500]:[d64_el3_dl3_ff128-ep1000]]),1,0) -> 0 | S14: =IF(L14=MAX(Tabelle4[[#This Row],[d32_el2_dl2_ff128-ep500]:[d64_el3_dl3_ff128-ep1000]]),1,0) -> 0 | T14: =IF(M14=MAX(Tabelle4[[#This Row],[d32_el2_dl2_ff128-ep500]:[d64_el3_dl3_ff128-ep1000]]),1,0) -> 0 | V14: =IF(H14=MIN(Tabelle4[[#This Row],[d32_el2_dl2_ff128-ep500]:[d64_el3_dl3_ff128-ep1000]]),1,0) -> 0 | W14: =IF(I14=MIN(Tabelle4[[#This Row],[d32_el2_dl2_ff128-ep500]:[d64_el3_dl3_ff128-ep1000]]),1,0) -> 0 | X14: =IF(J14=MIN(Tabelle4[[#This Row],[d32_el2_dl2_ff128-ep500]:[d64_el3_dl3_ff128-ep1000]]),1,0) -> 0 | Y14: =IF(K14=MIN(Tabelle4[[#This Row],[d32_el2_dl2_ff128-ep500]:[d64_el3_dl3_ff128-ep1000]]),1,0) -> 1 | Z14: =IF(L14=MIN(Tabelle4[[#This Row],[d32_el2_dl2_ff128-ep500]:[d64_el3_dl3_ff128-ep1000]]),1,0) -> 0 | AA14: =IF(M14=MIN(Tabelle4[[#This Row],[d32_el2_dl2_ff128-ep500]:[d64_el3_dl3_ff128-ep1000]]),1,0) -> 0
A15: 6 | B15: d64_el3_dl3_ff128-ep1000 | C15: ['wie frage vergleich'] | D15: 7 | E15: =D15+E8 -> 7 | G15: 14 | H15: {=INDEX($D$2:$D$701, (ROW()-ROW($G$2))*7 + (COLUMN()-COLUMN($G$2)) + 1)} -> 8 | I15: {=INDEX($D$2:$D$701, (ROW()-ROW($G$2))*7 + (COLUMN()-COLUMN($G$2)) + 1)} -> 10 | J15: {=INDEX($D$2:$D$701, (ROW()-ROW($G$2))*7 + (COLUMN()-COLUMN($G$2)) + 1)} -> 5 | K15: {=INDEX($D$2:$D$701, (ROW()-ROW($G$2))*7 + (COLUMN()-COLUMN($G$2)) + 1)} -> 6 | L15: {=INDEX($D$2:$D$701, (ROW()-ROW($G$2))*7 + (COLUMN()-COLUMN($G$2)) + 1)} -> 0 | M15: {=INDEX($D$2:$D$701, (ROW()-ROW($G$2))*7 + (COLUMN()-COLUMN($G$2)) + 1)} -> 2 | O15: =IF(H15=MAX(Tabelle4[[#This Row],[d32_el2_dl2_ff128-ep500]:[d64_el3_dl3_ff128-ep1000]]),1,0) -> 0 | P15: =IF(I15=MAX(Tabelle4[[#This Row],[d32_el2_dl2_ff128-ep500]:[d64_el3_dl3_ff128-ep1000]]),1,0) -> 1 | Q15: =IF(J15=MAX(Tabelle4[[#This Row],[d32_el2_dl2_ff128-ep500]:[d64_el3_dl3_ff128-ep1000]]),1,0) -> 0 | R15: =IF(K15=MAX(Tabelle4[[#This Row],[d32_el2_dl2_ff128-ep500]:[d64_el3_dl3_ff128-ep1000]]),1,0) -> 0 | S15: =IF(L15=MAX(Tabelle4[[#This Row],[d32_el2_dl2_ff128-ep500]:[d64_el3_dl3_ff128-ep1000]]),1,0) -> 0 | T15: =IF(M15=MAX(Tabelle4[[#This Row],[d32_el2_dl2_ff128-ep500]:[d64_el3_dl3_ff128-ep1000]]),1,0) -> 0 | V15: =IF(H15=MIN(Tabelle4[[#This Row],[d32_el2_dl2_ff128-ep500]:[d64_el3_dl3_ff128-ep1000]]),1,0) -> 0 | W15: =IF(I15=MIN(Tabelle4[[#This Row],[d32_el2_dl2_ff128-ep500]:[d64_el3_dl3_ff128-ep1000]]),1,0) -> 0 | X15: =IF(J15=MIN(Tabelle4[[#This Row],[d32_el2_dl2_ff128-ep500]:[d64_el3_dl3_ff128-ep1000]]),1,0) -> 0 | Y15: =IF(K15=MIN(Tabelle4[[#This Row],[d32_el2_dl2_ff128-ep500]:[d64_el3_dl3_ff128-ep1000]]),1,0) -> 0 | Z15: =IF(L15=MIN(Tabelle4[[#This Row],[d32_el2_dl2_ff128-ep500]:[d64_el3_dl3_ff128-ep1000]]),1,0) -> 1 | AA15: =IF(M15=MIN(Tabelle4[[#This Row],[d32_el2_dl2_ff128-ep500]:[d64_el3_dl3_ff128-ep1000]]),1,0) -> 0
A16: 0 | B16: 3 | C16: Hast du gut geschlafen? | E16: =D16+E9 -> 0 | G16: 15 | H16: {=INDEX($D$2:$D$701, (ROW()-ROW($G$2))*7 + (COLUMN()-COLUMN($G$2)) + 1)} -> 1 | I16: {=INDEX($D$2:$D$701, (ROW()-ROW($G$2))*7 + (COLUMN()-COLUMN($G$2)) + 1)} -> 2 | J16: {=INDEX($D$2:$D$701, (ROW()-ROW($G$2))*7 + (COLUMN()-COLUMN($G$2)) + 1)} -> 4 | K16: {=INDEX($D$2:$D$701, (ROW()-ROW($G$2))*7 + (COLUMN()-COLUMN($G$2)) + 1)} -> 4 | L16: {=INDEX($D$2:$D$701, (ROW()-ROW($G$2))*7 + (COLUMN()-COLUMN($G$2)) + 1)} -> 2 | M16: {=INDEX($D$2:$D$701, (ROW()-ROW($G$2))*7 + (COLUMN()-COLUMN($G$2)) + 1)} -> 4 | O16: =IF(H16=MAX(Tabelle4[[#This Row],[d32_el2_dl2_ff128-ep500]:[d64_el3_dl3_ff128-ep1000]]),1,0) -> 0 | P16: =IF(I16=MAX(Tabelle4[[#This Row],[d32_el2_dl2_ff128-ep500]:[d64_el3_dl3_ff128-ep1000]]),1,0) -> 0 | Q16: =IF(J16=MAX(Tabelle4[[#This Row],[d32_el2_dl2_ff128-ep500]:[d64_el3_dl3_ff128-ep1000]]),1,0) -> 1 | R16: =IF(K16=MAX(Tabelle4[[#This Row],[d32_el2_dl2_ff128-ep500]:[d64_el3_dl3_ff128-ep1000]]),1,0) -> 1 | S16: =IF(L16=MAX(Tabelle4[[#This Row],[d32_el2_dl2_ff128-ep500]:[d64_el3_dl3_ff128-ep1000]]),1,0) -> 0 | T16: =IF(M16=MAX(Tabelle4[[#This Row],[d32_el2_dl2_ff128-ep500]:[d64_el3_dl3_ff128-ep1000]]),1,0) -> 1 | V16: =IF(H16=MIN(Tabelle4[[#This Row],[d32_el2_dl2_ff128-ep500]:[d64_el3_dl3_ff128-ep1000]]),1,0) -> 1 | W16: =IF(I16=MIN(Tabelle4[[#This Row],[d32_el2_dl2_ff128-ep500]:[d64_el3_dl3_ff128-ep1000]]),1,0) -> 0 | X16: =IF(J16=MIN(Tabelle4[[#This Row],[d32_el2_dl2_ff128-ep500]:[d64_el3_dl3_ff128-ep1000]]),1,0) -> 0 | Y16: =IF(K16=MIN(Tabelle4[[#This Row],[d32_el2_dl2_ff128-ep500]:[d64_el3_dl3_ff128-ep1000]]),1,0) -> 0 | Z16: =IF(L16=MIN(Tabelle4[[#This Row],[d32_el2_dl2_ff128-ep500]:[d64_el3_dl3_ff128-ep1000]]),1,0) -> 0 | AA16: =IF(M16=MIN(Tabelle4[[#This Row],[d32_el2_dl2_ff128-ep500]:[d64_el3_dl3_ff128-ep1000]]),1,0) -> 0
A17: 1 | B17: d32_el2_dl2_ff128-ep500 | C17: ['schlafen', 'schlafen', 'schlafen', 'schlafen'] | D17: 2 | E17: =D17+E10 -> 14 | G17: 16 | H17: {=INDEX($D$2:$D$701, (ROW()-ROW($G$2))*7 + (COLUMN()-COLUMN($G$2)) + 1)} -> 1 | I17: {=INDEX($D$2:$D$701, (ROW()-ROW($G$2))*7 + (COLUMN()-COLUMN($G$2)) + 1)} -> 4 | J17: {=INDEX($D$2:$D$701, (ROW()-ROW($G$2))*7 + (COLUMN()-COLUMN($G$2)) + 1)} -> 0 | K17: {=INDEX($D$2:$D$701, (ROW()-ROW($G$2))*7 + (COLUMN()-COLUMN($G$2)) + 1)} -> 0 | L17: {=INDEX($D$2:$D$701, (ROW()-ROW($G$2))*7 + (COLUMN()-COLUMN($G$2)) + 1)} -> 0 | M17: {=INDEX($D$2:$D$701, (ROW()-ROW($G$2))*7 + (COLUMN()-COLUMN($G$2)) + 1)} -> 1 | O17: =IF(H17=MAX(Tabelle4[[#This Row],[d32_el2_dl2_ff128-ep500]:[d64_el3_dl3_ff128-ep1000]]),1,0) -> 0 | P17: =IF(I17=MAX(Tabelle4[[#This Row],[d32_el2_dl2_ff128-ep500]:[d64_el3_dl3_ff128-ep1000]]),1,0) -> 1 | Q17: =IF(J17=MAX(Tabelle4[[#This Row],[d32_el2_dl2_ff128-ep500]:[d64_el3_dl3_ff128-ep1000]]),1,0) -> 0 | R17: =IF(K17=MAX(Tabelle4[[#This Row],[d32_el2_dl2_ff128-ep500]:[d64_el3_dl3_ff128-ep1000]]),1,0) -> 0 | S17: =IF(L17=MAX(Tabelle4[[#This Row],[d32_el2_dl2_ff128-ep500]:[d64_el3_dl3_ff128-ep1000]]),1,0) -> 0 | T17: =IF(M17=MAX(Tabelle4[[#This Row],[d32_el2_dl2_ff128-ep500]:[d64_el3_dl3_ff128-ep1000]]),1,0) -> 0 | V17: =IF(H17=MIN(Tabelle4[[#This Row],[d32_el2_dl2_ff128-ep500]:[d64_el3_dl3_ff128-ep1000]]),1,0) -> 0 | W17: =IF(I17=MIN(Tabelle4[[#This Row],[d32_el2_dl2_ff128-ep500]:[d64_el3_dl3_ff128-ep1000]]),1,0) -> 0 | X17: =IF(J17=MIN(Tabelle4[[#This Row],[d32_el2_dl2_ff128-ep500]:[d64_el3_dl3_ff128-ep1000]]),1,0) -> 1 | Y17: =IF(K17=MIN(Tabelle4[[#This Row],[d32_el2_dl2_ff128-ep500]:[d64_el3_dl3_ff128-ep1000]]),1,0) -> 1 | Z17: =IF(L17=MIN(Tabelle4[[#This Row],[d32_el2_dl2_ff128-ep500]:[d64_el3_dl3_ff128-ep1000]]),1,0) -> 1 | AA17: =IF(M17=MIN(Tabelle4[[#This Row],[d32_el2_dl2_ff128-ep500]:[d64_el3_dl3_ff128-ep1000]]),1,0) -> 0
A18: 2 | B18: d64_el1_dl1_ff64-ep1000 | C18: ['schlafen', 'du', 'schlafen', 'du', 'schlafen', 'du', 'schlafen', 'du'] | D18: 4 | E18: =D18+E11 -> 12 | G18: 17 | H18: {=INDEX($D$2:$D$701, (ROW()-ROW($G$2))*7 + (COLUMN()-COLUMN($G$2)) + 1)} -> 0 | I18: {=INDEX($D$2:$D$701, (ROW()-ROW($G$2))*7 + (COLUMN()-COLUMN($G$2)) + 1)} -> 9 | J18: {=INDEX($D$2:$D$701, (ROW()-ROW($G$2))*7 + (COLUMN()-COLUMN($G$2)) + 1)} -> 0 | K18: {=INDEX($D$2:$D$701, (ROW()-ROW($G$2))*7 + (COLUMN()-COLUMN($G$2)) + 1)} -> 0 | L18: {=INDEX($D$2:$D$701, (ROW()-ROW($G$2))*7 + (COLUMN()-COLUMN($G$2)) + 1)} -> 5 | M18: {=INDEX($D$2:$D$701, (ROW()-ROW($G$2))*7 + (COLUMN()-COLUMN($G$2)) + 1)} -> 0 | O18: =IF(H18=MAX(Tabelle4[[#This Row],[d32_el2_dl2_ff128-ep500]:[d64_el3_dl3_ff128-ep1000]]),1,0) -> 0 | P18: =IF(I18=MAX(Tabelle4[[#This Row],[d32_el2_dl2_ff128-ep500]:[d64_el3_dl3_ff128-ep1000]]),1,0) -> 1 | Q18: =IF(J18=MAX(Tabelle4[[#This Row],[d32_el2_dl2_ff128-ep500]:[d64_el3_dl3_ff128-ep1000]]),1,0) -> 0 | R18: =IF(K18=MAX(Tabelle4[[#This Row],[d32_el2_dl2_ff128-ep500]:[d64_el3_dl3_ff128-ep1000]]),1,0) -> 0 | S18: =IF(L18=MAX(Tabelle4[[#This Row],[d32_el2_dl2_ff128-ep500]:[d64_el3_dl3_ff128-ep1000]]),1,0) -> 0 | T18: =IF(M18=MAX(Tabelle4[[#This Row],[d32_el2_dl2_ff128-ep500]:[d64_el3_dl3_ff128-ep1000]]),1,0) -> 0 | V18: =IF(H18=MIN(Tabelle4[[#This Row],[d32_el2_dl2_ff128-ep500]:[d64_el3_dl3_ff128-ep1000]]),1,0) -> 1 | W18: =IF(I18=MIN(Tabelle4[[#This Row],[d32_el2_dl2_ff128-ep500]:[d64_el3_dl3_ff128-ep1000]]),1,0) -> 0 | X18: =IF(J18=MIN(Tabelle4[[#This Row],[d32_el2_dl2_ff128-ep500]:[d64_el3_dl3_ff128-ep1000]]),1,0) -> 1 | Y18: =IF(K18=MIN(Tabelle4[[#This Row],[d32_el2_dl2_ff128-ep500]:[d64_el3_dl3_ff128-ep1000]]),1,0) -> 1 | Z18: =IF(L18=MIN(Tabelle4[[#This Row],[d32_el2_dl2_ff128-ep500]:[d64_el3_dl3_ff128-ep1000]]),1,0) -> 0 | AA18: =IF(M18=MIN(Tabelle4[[#This Row],[d32_el2_dl2_ff128-ep500]:[d64_el3_dl3_ff128-ep1000]]),1,0) -> 1
A19: 3 | B19: d64_el2_dl2_ff64-ep500 | C19: ['schlafen', 'gut'] | D19: 10 | E19: =D19+E12 -> 17 | G19: 18 | H19: {=INDEX($D$2:$D$701, (ROW()-ROW($G$2))*7 + (COLUMN()-COLUMN($G$2)) + 1)} -> 8 | I19: {=INDEX($D$2:$D$701, (ROW()-ROW($G$2))*7 + (COLUMN()-COLUMN($G$2)) + 1)} -> 10 | J19: {=INDEX($D$2:$D$701, (ROW()-ROW($G$2))*7 + (COLUMN()-COLUMN($G$2)) + 1)} -> 10 | K19: {=INDEX($D$2:$D$701, (ROW()-ROW($G$2))*7 + (COLUMN()-COLUMN($G$2)) + 1)} -> 8 | L19: {=INDEX($D$2:$D$701, (ROW()-ROW($G$2))*7 + (COLUMN()-COLUMN($G$2)) + 1)} -> 10 | M19: {=INDEX($D$2:$D$701, (ROW()-ROW($G$2))*7 + (COLUMN()-COLUMN($G$2)) + 1)} -> 10 | O19: =IF(H19=MAX(Tabelle4[[#This Row],[d32_el2_dl2_ff128-ep500]:[d64_el3_dl3_ff128-ep1000]]),1,0) -> 0 | P19: =IF(I19=MAX(Tabelle4[[#This Row],[d32_el2_dl2_ff128-ep500]:[d64_el3_dl3_ff128-ep1000]]),1,0) -> 1 | Q19: =IF(J19=MAX(Tabelle4[[#This Row],[d32_el2_dl2_ff128-ep500]:[d64_el3_dl3_ff128-ep1000]]),1,0) -> 1 | R19: =IF(K19=MAX(Tabelle4[[#This Row],[d32_el2_dl2_ff128-ep500]:[d64_el3_dl3_ff128-ep1000]]),1,0) -> 0 | S19: =IF(L19=MAX(Tabelle4[[#This Row],[d32_el2_dl2_ff128-ep500]:[d64_el3_dl3_ff128-ep1000]]),1,0) -> 1 | T19: =IF(M19=MAX(Tabelle4[[#This Row],[d32_el2_dl2_ff128-ep500]:[d64_el3_dl3_ff128-ep1000]]),1,0) -> 1 | V19: =IF(H19=MIN(Tabelle4[[#This Row],[d32_el2_dl2_ff128-ep500]:[d64_el3_dl3_ff128-ep1000]]),1,0) -> 1 | W19: =IF(I19=MIN(Tabelle4[[#This Row],[d32_el2_dl2_ff128-ep500]:[d64_el3_dl3_ff128-ep1000]]),1,0) -> 0 | X19: =IF(J19=MIN(Tabelle4[[#This Row],[d32_el2_dl2_ff128-ep500]:[d64_el3_dl3_ff128-ep1000]]),1,0) -> 0 | Y19: =IF(K19=MIN(Tabelle4[[#This Row],[d32_el2_dl2_ff128-ep500]:[d64_el3_dl3_ff128-ep1000]]),1,0) -> 1 | Z19: =IF(L19=MIN(Tabelle4[[#This Row],[d32_el2_dl2_ff128-ep500]:[d64_el3_dl3_ff128-ep1000]]),1,0) -> 0 | AA19: =IF(M19=MIN(Tabelle4[[#This Row],[d32_el2_dl2_ff128-ep500]:[d64_el3_dl3_ff128-ep1000]]),1,0) -> 0
A20: 4 | B20: d64_el2_dl2_ff64-ep1000 | C20: ['schlafen', 'gut'] | D20: 10 | E20: =D20+E13 -> 17 | G20: 19 | H20: {=INDEX($D$2:$D$701, (ROW()-ROW($G$2))*7 + (COLUMN()-COLUMN($G$2)) + 1)} -> 2 | I20: {=INDEX($D$2:$D$701, (ROW()-ROW($G$2))*7 + (COLUMN()-COLUMN($G$2)) + 1)} -> 0 | J20: {=INDEX($D$2:$D$701, (ROW()-ROW($G$2))*7 + (COLUMN()-COLUMN($G$2)) + 1)} -> 3 | K20: {=INDEX($D$2:$D$701, (ROW()-ROW($G$2))*7 + (COLUMN()-COLUMN($G$2)) + 1)} -> 1 | L20: {=INDEX($D$2:$D$701, (ROW()-ROW($G$2))*7 + (COLUMN()-COLUMN($G$2)) + 1)} -> 0 | M20: {=INDEX($D$2:$D$701, (ROW()-ROW($G$2))*7 + (COLUMN()-COLUMN($G$2)) + 1)} -> 0 | O20: =IF(H20=MAX(Tabelle4[[#This Row],[d32_el2_dl2_ff128-ep500]:[d64_el3_dl3_ff128-ep1000]]),1,0) -> 0 | P20: =IF(I20=MAX(Tabelle4[[#This Row],[d32_el2_dl2_ff128-ep500]:[d64_el3_dl3_ff128-ep1000]]),1,0) -> 0 | Q20: =IF(J20=MAX(Tabelle4[[#This Row],[d32_el2_dl2_ff128-ep500]:[d64_el3_dl3_ff128-ep1000]]),1,0) -> 1 | R20: =IF(K20=MAX(Tabelle4[[#This Row],[d32_el2_dl2_ff128-ep500]:[d64_el3_dl3_ff128-ep1000]]),1,0) -> 0 | S20: =IF(L20=MAX(Tabelle4[[#This Row],[d32_el2_dl2_ff128-ep500]:[d64_el3_dl3_ff128-ep1000]]),1,0) -> 0 | T20: =IF(M20=MAX(Tabelle4[[#This Row],[d32_el2_dl2_ff128-ep500]:[d64_el3_dl3_ff128-ep1000]]),1,0) -> 0 | V20: =IF(H20=MIN(Tabelle4[[#This Row],[d32_el2_dl2_ff128-ep500]:[d64_el3_dl3_ff128-ep1000]]),1,0) -> 0 | W20: =IF(I20=MIN(Tabelle4[[#This Row],[d32_el2_dl2_ff128-ep500]:[d64_el3_dl3_ff128-ep1000]]),1,0) -> 1 | X20: =IF(J20=MIN(Tabelle4[[#This Row],[d32_el2_dl2_ff128-ep500]:[d64_el3_dl3_ff128-ep1000]]),1,0) -> 0 | Y20: =IF(K20=MIN(Tabelle4[[#This Row],[d32_el2_dl2_ff128-ep500]:[d64_el3_dl3_ff128-ep1000]]),1,0) -> 0 | Z20: =IF(L20=MIN(Tabelle4[[#This Row],[d32_el2_dl2_ff128-ep500]:[d64_el3_dl3_ff128-ep1000]]),1,0) -> 1 | AA20: =IF(M20=MIN(Tabelle4[[#This Row],[d32_el2_dl2_ff128-ep500]:[d64_el3_dl3_ff128-ep1000]]),1,0) -> 1
A21: 5 | B21: d64_el2_dl2_ff128-ep1000 | C21: ['schlafen', 'gut', 'schlafen'] | D21: 9 | E21: =D21+E14 -> 17 | G21: 20 | H21: {=INDEX($D$2:$D$701, (ROW()-ROW($G$2))*7 + (COLUMN()-COLUMN($G$2)) + 1)} -> 8 | I21: {=INDEX($D$2:$D$701, (ROW()-ROW($G$2))*7 + (COLUMN()-COLUMN($G$2)) + 1)} -> 5 | J21: {=INDEX($D$2:$D$701, (ROW()-ROW($G$2))*7 + (COLUMN()-COLUMN($G$2)) + 1)} -> 6 | K21: {=INDEX($D$2:$D$701, (ROW()-ROW($G$2))*7 + (COLUMN()-COLUMN($G$2)) + 1)} -> 10 | L21: {=INDEX($D$2:$D$701, (ROW()-ROW($G$2))*7 + (COLUMN()-COLUMN($G$2)) + 1)} -> 5 | M21: {=INDEX($D$2:$D$701, (ROW()-ROW($G$2))*7 + (COLUMN()-COLUMN($G$2)) + 1)} -> 5 | O21: =IF(H21=MAX(Tabelle4[[#This Row],[d32_el2_dl2_ff128-ep500]:[d64_el3_dl3_ff128-ep1000]]),1,0) -> 0 | P21: =IF(I21=MAX(Tabelle4[[#This Row],[d32_el2_dl2_ff128-ep500]:[d64_el3_dl3_ff128-ep1000]]),1,0) -> 0 | Q21: =IF(J21=MAX(Tabelle4[[#This Row],[d32_el2_dl2_ff128-ep500]:[d64_el3_dl3_ff128-ep1000]]),1,0) -> 0 | R21: =IF(K21=MAX(Tabelle4[[#This Row],[d32_el2_dl2_ff128-ep500]:[d64_el3_dl3_ff128-ep1000]]),1,0) -> 1 | S21: =IF(L21=MAX(Tabelle4[[#This Row],[d32_el2_dl2_ff128-ep500]:[d64_el3_dl3_ff128-ep1000]]),1,0) -> 0 | T21: =IF(M21=MAX(Tabelle4[[#This Row],[d32_el2_dl2_ff128-ep500]:[d64_el3_dl3_ff128-ep1000]]),1,0) -> 0 | V21: =IF(H21=MIN(Tabelle4[[#This Row],[d32_el2_dl2_ff128-ep500]:[d64_el3_dl3_ff128-ep1000]]),1,0) -> 0 | W21: =IF(I21=MIN(Tabelle4[[#This Row],[d32_el2_dl2_ff128-ep500]:[d64_el3_dl3_ff128-ep1000]]),1,0) -> 1 | X21: =IF(J21=MIN(Tabelle4[[#This Row],[d32_el2_dl2_ff128-ep500]:[d64_el3_dl3_ff128-ep1000]]),1,0) -> 0 | Y21: =IF(K21=MIN(Tabelle4[[#This Row],[d32_el2_dl2_ff128-ep500]:[d64_el3_dl3_ff128-ep1000]]),1,0) -> 0 | Z21: =IF(L21=MIN(Tabelle4[[#This Row],[d32_el2_dl2_ff128-ep500]:[d64_el3_dl3_ff128-ep1000]]),1,0) -> 1 | AA21: =IF(M21=MIN(Tabelle4[[#This Row],[d32_el2_dl2_ff128-ep500]:[d64_el3_dl3_ff128-ep1000]]),1,0) -> 1
A22: 6 | B22: d64_el3_dl3_ff128-ep1000 | C22: ['du', 'schlafen', 'index'] | D22: 8 | E22: =D22+E15 -> 15 | G22: 21 | H22: {=INDEX($D$2:$D$701, (ROW()-ROW($G$2))*7 + (COLUMN()-COLUMN($G$2)) + 1)} -> 9 | I22: {=INDEX($D$2:$D$701, (ROW()-ROW($G$2))*7 + (COLUMN()-COLUMN($G$2)) + 1)} -> 9 | J22: {=INDEX($D$2:$D$701, (ROW()-ROW($G$2))*7 + (COLUMN()-COLUMN($G$2)) + 1)} -> 9 | K22: {=INDEX($D$2:$D$701, (ROW()-ROW($G$2))*7 + (COLUMN()-COLUMN($G$2)) + 1)} -> 9 | L22: {=INDEX($D$2:$D$701, (ROW()-ROW($G$2))*7 + (COLUMN()-COLUMN($G$2)) + 1)} -> 9 | M22: {=INDEX($D$2:$D$701, (ROW()-ROW($G$2))*7 + (COLUMN()-COLUMN($G$2)) + 1)} -> 9 | O22: =IF(H22=MAX(Tabelle4[[#This Row],[d32_el2_dl2_ff128-ep500]:[d64_el3_dl3_ff128-ep1000]]),1,0) -> 1 | P22: =IF(I22=MAX(Tabelle4[[#This Row],[d32_el2_dl2_ff128-ep500]:[d64_el3_dl3_ff128-ep1000]]),1,0) -> 1 | Q22: =IF(J22=MAX(Tabelle4[[#This Row],[d32_el2_dl2_ff128-ep500]:[d64_el3_dl3_ff128-ep1000]]),1,0) -> 1 | R22: =IF(K22=MAX(Tabelle4[[#This Row],[d32_el2_dl2_ff128-ep500]:[d64_el3_dl3_ff128-ep1000]]),1,0) -> 1 | S22: =IF(L22=MAX(Tabelle4[[#This Row],[d32_el2_dl2_ff128-ep500]:[d64_el3_dl3_ff128-ep1000]]),1,0) -> 1 | T22: =IF(M22=MAX(Tabelle4[[#This Row],[d32_el2_dl2_ff128-ep500]:[d64_el3_dl3_ff128-ep1000]]),1,0) -> 1 | V22: =IF(H22=MIN(Tabelle4[[#This Row],[d32_el2_dl2_ff128-ep500]:[d64_el3_dl3_ff128-ep1000]]),1,0) -> 1 | W22: =IF(I22=MIN(Tabelle4[[#This Row],[d32_el2_dl2_ff128-ep500]:[d64_el3_dl3_ff128-ep1000]]),1,0) -> 1 | X22: =IF(J22=MIN(Tabelle4[[#This Row],[d32_el2_dl2_ff128-ep500]:[d64_el3_dl3_ff128-ep1000]]),1,0) -> 1 | Y22: =IF(K22=MIN(Tabelle4[[#This Row],[d32_el2_dl2_ff128-ep500]:[d64_el3_dl3_ff128-ep1000]]),1,0) -> 1 | Z22: =IF(L22=MIN(Tabelle4[[#This Row],[d32_el2_dl2_ff128-ep500]:[d64_el3_dl3_ff128-ep1000]]),1,0) -> 1 | AA22: =IF(M22=MIN(Tabelle4[[#This Row],[d32_el2_dl2_ff128-ep500]:[d64_el3_dl3_ff128-ep1000]]),1,0) -> 1
A23: 0 | B23: 4 | C23: Kannst du mir bitte helfen? | E23: =D23+E16 -> 0 | G23: 22 | H23: {=INDEX($D$2:$D$701, (ROW()-ROW($G$2))*7 + (COLUMN()-COLUMN($G$2)) + 1)} -> 10 | I23: {=INDEX($D$2:$D$701, (ROW()-ROW($G$2))*7 + (COLUMN()-COLUMN($G$2)) + 1)} -> 10 | J23: {=INDEX($D$2:$D$701, (ROW()-ROW($G$2))*7 + (COLUMN()-COLUMN($G$2)) + 1)} -> 10 | K23: {=INDEX($D$2:$D$701, (ROW()-ROW($G$2))*7 + (COLUMN()-COLUMN($G$2)) + 1)} -> 5 | L23: {=INDEX($D$2:$D$701, (ROW()-ROW($G$2))*7 + (COLUMN()-COLUMN($G$2)) + 1)} -> 9 | M23: {=INDEX($D$2:$D$701, (ROW()-ROW($G$2))*7 + (COLUMN()-COLUMN($G$2)) + 1)} -> 4 | O23: =IF(H23=MAX(Tabelle4[[#This Row],[d32_el2_dl2_ff128-ep500]:[d64_el3_dl3_ff128-ep1000]]),1,0) -> 1 | P23: =IF(I23=MAX(Tabelle4[[#This Row],[d32_el2_dl2_ff128-ep500]:[d64_el3_dl3_ff128-ep1000]]),1,0) -> 1 | Q23: =IF(J23=MAX(Tabelle4[[#This Row],[d32_el2_dl2_ff128-ep500]:[d64_el3_dl3_ff128-ep1000]]),1,0) -> 1 | R23: =IF(K23=MAX(Tabelle4[[#This Row],[d32_el2_dl2_ff128-ep500]:[d64_el3_dl3_ff128-ep1000]]),1,0) -> 0 | S23: =IF(L23=MAX(Tabelle4[[#This Row],[d32_el2_dl2_ff128-ep500]:[d64_el3_dl3_ff128-ep1000]]),1,0) -> 0 | T23: =IF(M23=MAX(Tabelle4[[#This Row],[d32_el2_dl2_ff128-ep500]:[d64_el3_dl3_ff128-ep1000]]),1,0) -> 0 | V23: =IF(H23=MIN(Tabelle4[[#This Row],[d32_el2_dl2_ff128-ep500]:[d64_el3_dl3_ff128-ep1000]]),1,0) -> 0 | W23: =IF(I23=MIN(Tabelle4[[#This Row],[d32_el2_dl2_ff128-ep500]:[d64_el3_dl3_ff128-ep1000]]),1,0) -> 0 | X23: =IF(J23=MIN(Tabelle4[[#This Row],[d32_el2_dl2_ff128-ep500]:[d64_el3_dl3_ff128-ep1000]]),1,0) -> 0 | Y23: =IF(K23=MIN(Tabelle4[[#This Row],[d32_el2_dl2_ff128-ep500]:[d64_el3_dl3_ff128-ep1000]]),1,0) -> 0 | Z23: =IF(L23=MIN(Tabelle4[[#This Row],[d32_el2_dl2_ff128-ep500]:[d64_el3_dl3_ff128-ep1000]]),1,0) -> 0 | AA23: =IF(M23=MIN(Tabelle4[[#This Row],[d32_el2_dl2_ff128-ep500]:[d64_el3_dl3_ff128-ep1000]]),1,0) -> 1
A24: 1 | B24: d32_el2_dl2_ff128-ep500 | C24: ['bitte', 'helfen'] | D24: 10 | E24: =D24+E17 -> 24 | G24: 23 | H24: {=INDEX($D$2:$D$701, (ROW()-ROW($G$2))*7 + (COLUMN()-COLUMN($G$2)) + 1)} -> 4 | I24: {=INDEX($D$2:$D$701, (ROW()-ROW($G$2))*7 + (COLUMN()-COLUMN($G$2)) + 1)} -> 0 | J24: {=INDEX($D$2:$D$701, (ROW()-ROW($G$2))*7 + (COLUMN()-COLUMN($G$2)) + 1)} -> 0 | K24: {=INDEX($D$2:$D$701, (ROW()-ROW($G$2))*7 + (COLUMN()-COLUMN($G$2)) + 1)} -> 0 | L24: {=INDEX($D$2:$D$701, (ROW()-ROW($G$2))*7 + (COLUMN()-COLUMN($G$2)) + 1)} -> 0 | M24: {=INDEX($D$2:$D$701, (ROW()-ROW($G$2))*7 + (COLUMN()-COLUMN($G$2)) + 1)} -> 0 | O24: =IF(H24=MAX(Tabelle4[[#This Row],[d32_el2_dl2_ff128-ep500]:[d64_el3_dl3_ff128-ep1000]]),1,0) -> 1 | P24: =IF(I24=MAX(Tabelle4[[#This Row],[d32_el2_dl2_ff128-ep500]:[d64_el3_dl3_ff128-ep1000]]),1,0) -> 0 | Q24: =IF(J24=MAX(Tabelle4[[#This Row],[d32_el2_dl2_ff128-ep500]:[d64_el3_dl3_ff128-ep1000]]),1,0) -> 0 | R24: =IF(K24=MAX(Tabelle4[[#This Row],[d32_el2_dl2_ff128-ep500]:[d64_el3_dl3_ff128-ep1000]]),1,0) -> 0 | S24: =IF(L24=MAX(Tabelle4[[#This Row],[d32_el2_dl2_ff128-ep500]:[d64_el3_dl3_ff128-ep1000]]),1,0) -> 0 | T24: =IF(M24=MAX(Tabelle4[[#This Row],[d32_el2_dl2_ff128-ep500]:[d64_el3_dl3_ff128-ep1000]]),1,0) -> 0 | V24: =IF(H24=MIN(Tabelle4[[#This Row],[d32_el2_dl2_ff128-ep500]:[d64_el3_dl3_ff128-ep1000]]),1,0) -> 0 | W24: =IF(I24=MIN(Tabelle4[[#This Row],[d32_el2_dl2_ff128-ep500]:[d64_el3_dl3_ff128-ep1000]]),1,0) -> 1 | X24: =IF(J24=MIN(Tabelle4[[#This Row],[d32_el2_dl2_ff128-ep500]:[d64_el3_dl3_ff128-ep1000]]),1,0) -> 1 | Y24: =IF(K24=MIN(Tabelle4[[#This Row],[d32_el2_dl2_ff128-ep500]:[d64_el3_dl3_ff128-ep1000]]),1,0) -> 1 | Z24: =IF(L24=MIN(Tabelle4[[#This Row],[d32_el2_dl2_ff128-ep500]:[d64_el3_dl3_ff128-ep1000]]),1,0) -> 1 | AA24: =IF(M24=MIN(Tabelle4[[#This Row],[d32_el2_dl2_ff128-ep500]:[d64_el3_dl3_ff128-ep1000]]),1,0) -> 1
A25: 2 | B25: d64_el1_dl1_ff64-ep1000 | C25: ['helfen', 'du', 'helfen', 'weg verlieren'] | D25: 6 | E25: =D25+E18 -> 18 | G25: 24 | H25: {=INDEX($D$2:$D$701, (ROW()-ROW($G$2))*7 + (COLUMN()-COLUMN($G$2)) + 1)} -> 0 | I25: {=INDEX($D$2:$D$701, (ROW()-ROW($G$2))*7 + (COLUMN()-COLUMN($G$2)) + 1)} -> 5 | J25: {=INDEX($D$2:$D$701, (ROW()-ROW($G$2))*7 + (COLUMN()-COLUMN($G$2)) + 1)} -> 1 | K25: {=INDEX($D$2:$D$701, (ROW()-ROW($G$2))*7 + (COLUMN()-COLUMN($G$2)) + 1)} -> 1 | L25: {=INDEX($D$2:$D$701, (ROW()-ROW($G$2))*7 + (COLUMN()-COLUMN($G$2)) + 1)} -> 2 | M25: {=INDEX($D$2:$D$701, (ROW()-ROW($G$2))*7 + (COLUMN()-COLUMN($G$2)) + 1)} -> 0 | O25: =IF(H25=MAX(Tabelle4[[#This Row],[d32_el2_dl2_ff128-ep500]:[d64_el3_dl3_ff128-ep1000]]),1,0) -> 0 | P25: =IF(I25=MAX(Tabelle4[[#This Row],[d32_el2_dl2_ff128-ep500]:[d64_el3_dl3_ff128-ep1000]]),1,0) -> 1 | Q25: =IF(J25=MAX(Tabelle4[[#This Row],[d32_el2_dl2_ff128-ep500]:[d64_el3_dl3_ff128-ep1000]]),1,0) -> 0 | R25: =IF(K25=MAX(Tabelle4[[#This Row],[d32_el2_dl2_ff128-ep500]:[d64_el3_dl3_ff128-ep1000]]),1,0) -> 0 | S25: =IF(L25=MAX(Tabelle4[[#This Row],[d32_el2_dl2_ff128-ep500]:[d64_el3_dl3_ff128-ep1000]]),1,0) -> 0 | T25: =IF(M25=MAX(Tabelle4[[#This Row],[d32_el2_dl2_ff128-ep500]:[d64_el3_dl3_ff128-ep1000]]),1,0) -> 0 | V25: =IF(H25=MIN(Tabelle4[[#This Row],[d32_el2_dl2_ff128-ep500]:[d64_el3_dl3_ff128-ep1000]]),1,0) -> 1 | W25: =IF(I25=MIN(Tabelle4[[#This Row],[d32_el2_dl2_ff128-ep500]:[d64_el3_dl3_ff128-ep1000]]),1,0) -> 0 | X25: =IF(J25=MIN(Tabelle4[[#This Row],[d32_el2_dl2_ff128-ep500]:[d64_el3_dl3_ff128-ep1000]]),1,0) -> 0 | Y25: =IF(K25=MIN(Tabelle4[[#This Row],[d32_el2_dl2_ff128-ep500]:[d64_el3_dl3_ff128-ep1000]]),1,0) -> 0 | Z25: =IF(L25=MIN(Tabelle4[[#This Row],[d32_el2_dl2_ff128-ep500]:[d64_el3_dl3_ff128-ep1000]]),1,0) -> 0 | AA25: =IF(M25=MIN(Tabelle4[[#This Row],[d32_el2_dl2_ff128-ep500]:[d64_el3_dl3_ff128-ep1000]]),1,0) -> 1
A26: 3 | B26: d64_el2_dl2_ff64-ep500 | C26: ['kann', 'helfen'] | D26: 7 | E26: =D26+E19 -> 24 | G26: 25 | H26: {=INDEX($D$2:$D$701, (ROW()-ROW($G$2))*7 + (COLUMN()-COLUMN($G$2)) + 1)} -> 10 | I26: {=INDEX($D$2:$D$701, (ROW()-ROW($G$2))*7 + (COLUMN()-COLUMN($G$2)) + 1)} -> 10 | J26: {=INDEX($D$2:$D$701, (ROW()-ROW($G$2))*7 + (COLUMN()-COLUMN($G$2)) + 1)} -> 10 | K26: {=INDEX($D$2:$D$701, (ROW()-ROW($G$2))*7 + (COLUMN()-COLUMN($G$2)) + 1)} -> 10 | L26: {=INDEX($D$2:$D$701, (ROW()-ROW($G$2))*7 + (COLUMN()-COLUMN($G$2)) + 1)} -> 10 | M26: {=INDEX($D$2:$D$701, (ROW()-ROW($G$2))*7 + (COLUMN()-COLUMN($G$2)) + 1)} -> 10 | O26: =IF(H26=MAX(Tabelle4[[#This Row],[d32_el2_dl2_ff128-ep500]:[d64_el3_dl3_ff128-ep1000]]),1,0) -> 1 | P26: =IF(I26=MAX(Tabelle4[[#This Row],[d32_el2_dl2_ff128-ep500]:[d64_el3_dl3_ff128-ep1000]]),1,0) -> 1 | Q26: =IF(J26=MAX(Tabelle4[[#This Row],[d32_el2_dl2_ff128-ep500]:[d64_el3_dl3_ff128-ep1000]]),1,0) -> 1 | R26: =IF(K26=MAX(Tabelle4[[#This Row],[d32_el2_dl2_ff128-ep500]:[d64_el3_dl3_ff128-ep1000]]),1,0) -> 1 | S26: =IF(L26=MAX(Tabelle4[[#This Row],[d32_el2_dl2_ff128-ep500]:[d64_el3_dl3_ff128-ep1000]]),1,0) -> 1 | T26: =IF(M26=MAX(Tabelle4[[#This Row],[d32_el2_dl2_ff128-ep500]:[d64_el3_dl3_ff128-ep1000]]),1,0) -> 1 | V26: =IF(H26=MIN(Tabelle4[[#This Row],[d32_el2_dl2_ff128-ep500]:[d64_el3_dl3_ff128-ep1000]]),1,0) -> 1 | W26: =IF(I26=MIN(Tabelle4[[#This Row],[d32_el2_dl2_ff128-ep500]:[d64_el3_dl3_ff128-ep1000]]),1,0) -> 1 | X26: =IF(J26=MIN(Tabelle4[[#This Row],[d32_el2_dl2_ff128-ep500]:[d64_el3_dl3_ff128-ep1000]]),1,0) -> 1 | Y26: =IF(K26=MIN(Tabelle4[[#This Row],[d32_el2_dl2_ff128-ep500]:[d64_el3_dl3_ff128-ep1000]]),1,0) -> 1 | Z26: =IF(L26=MIN(Tabelle4[[#This Row],[d32_el2_dl2_ff128-ep500]:[d64_el3_dl3_ff128-ep1000]]),1,0) -> 1 | AA26: =IF(M26=MIN(Tabelle4[[#This Row],[d32_el2_dl2_ff128-ep500]:[d64_el3_dl3_ff128-ep1000]]),1,0) -> 1
A27: 4 | B27: d64_el2_dl2_ff64-ep1000 | C27: ['kann', 'helfen'] | D27: 7 | E27: =D27+E20 -> 24 | G27: 26 | H27: {=INDEX($D$2:$D$701, (ROW()-ROW($G$2))*7 + (COLUMN()-COLUMN($G$2)) + 1)} -> 10 | I27: {=INDEX($D$2:$D$701, (ROW()-ROW($G$2))*7 + (COLUMN()-COLUMN($G$2)) + 1)} -> 6 | J27: {=INDEX($D$2:$D$701, (ROW()-ROW($G$2))*7 + (COLUMN()-COLUMN($G$2)) + 1)} -> 10 | K27: {=INDEX($D$2:$D$701, (ROW()-ROW($G$2))*7 + (COLUMN()-COLUMN($G$2)) + 1)} -> 10 | L27: {=INDEX($D$2:$D$701, (ROW()-ROW($G$2))*7 + (COLUMN()-COLUMN($G$2)) + 1)} -> 10 | M27: {=INDEX($D$2:$D$701, (ROW()-ROW($G$2))*7 + (COLUMN()-COLUMN($G$2)) + 1)} -> 10 | O27: =IF(H27=MAX(Tabelle4[[#This Row],[d32_el2_dl2_ff128-ep500]:[d64_el3_dl3_ff128-ep1000]]),1,0) -> 1 | P27: =IF(I27=MAX(Tabelle4[[#This Row],[d32_el2_dl2_ff128-ep500]:[d64_el3_dl3_ff128-ep1000]]),1,0) -> 0 | Q27: =IF(J27=MAX(Tabelle4[[#This Row],[d32_el2_dl2_ff128-ep500]:[d64_el3_dl3_ff128-ep1000]]),1,0) -> 1 | R27: =IF(K27=MAX(Tabelle4[[#This Row],[d32_el2_dl2_ff128-ep500]:[d64_el3_dl3_ff128-ep1000]]),1,0) -> 1 | S27: =IF(L27=MAX(Tabelle4[[#This Row],[d32_el2_dl2_ff128-ep500]:[d64_el3_dl3_ff128-ep1000]]),1,0) -> 1 | T27: =IF(M27=MAX(Tabelle4[[#This Row],[d32_el2_dl2_ff128-ep500]:[d64_el3_dl3_ff128-ep1000]]),1,0) -> 1 | V27: =IF(H27=MIN(Tabelle4[[#This Row],[d32_el2_dl2_ff128-ep500]:[d64_el3_dl3_ff128-ep1000]]),1,0) -> 0 | W27: =IF(I27=MIN(Tabelle4[[#This Row],[d32_el2_dl2_ff128-ep500]:[d64_el3_dl3_ff128-ep1000]]),1,0) -> 1 | X27: =IF(J27=MIN(Tabelle4[[#This Row],[d32_el2_dl2_ff128-ep500]:[d64_el3_dl3_ff128-ep1000]]),1,0) -> 0 | Y27: =IF(K27=MIN(Tabelle4[[#This Row],[d32_el2_dl2_ff128-ep500]:[d64_el3_dl3_ff128-ep1000]]),1,0) -> 0 | Z27: =IF(L27=MIN(Tabelle4[[#This Row],[d32_el2_dl2_ff128-ep500]:[d64_el3_dl3_ff128-ep1000]]),1,0) -> 0 | AA27: =IF(M27=MIN(Tabelle4[[#This Row],[d32_el2_dl2_ff128-ep500]:[d64_el3_dl3_ff128-ep1000]]),1,0) -> 0
A28: 5 | B28: d64_el2_dl2_ff128-ep1000 | C28: ['helfen'] | D28: 5 | E28: =D28+E21 -> 22 | G28: 27 | H28: {=INDEX($D$2:$D$701, (ROW()-ROW($G$2))*7 + (COLUMN()-COLUMN($G$2)) + 1)} -> 8 | I28: {=INDEX($D$2:$D$701, (ROW()-ROW($G$2))*7 + (COLUMN()-COLUMN($G$2)) + 1)} -> 9 | J28: {=INDEX($D$2:$D$701, (ROW()-ROW($G$2))*7 + (COLUMN()-COLUMN($G$2)) + 1)} -> 10 | K28: {=INDEX($D$2:$D$701, (ROW()-ROW($G$2))*7 + (COLUMN()-COLUMN($G$2)) + 1)} -> 9 | L28: {=INDEX($D$2:$D$701, (ROW()-ROW($G$2))*7 + (COLUMN()-COLUMN($G$2)) + 1)} -> 3 | M28: {=INDEX($D$2:$D$701, (ROW()-ROW($G$2))*7 + (COLUMN()-COLUMN($G$2)) + 1)} -> 10 | O28: =IF(H28=MAX(Tabelle4[[#This Row],[d32_el2_dl2_ff128-ep500]:[d64_el3_dl3_ff128-ep1000]]),1,0) -> 0 | P28: =IF(I28=MAX(Tabelle4[[#This Row],[d32_el2_dl2_ff128-ep500]:[d64_el3_dl3_ff128-ep1000]]),1,0) -> 0 | Q28: =IF(J28=MAX(Tabelle4[[#This Row],[d32_el2_dl2_ff128-ep500]:[d64_el3_dl3_ff128-ep1000]]),1,0) -> 1 | R28: =IF(K28=MAX(Tabelle4[[#This Row],[d32_el2_dl2_ff128-ep500]:[d64_el3_dl3_ff128-ep1000]]),1,0) -> 0 | S28: =IF(L28=MAX(Tabelle4[[#This Row],[d32_el2_dl2_ff128-ep500]:[d64_el3_dl3_ff128-ep1000]]),1,0) -> 0 | T28: =IF(M28=MAX(Tabelle4[[#This Row],[d32_el2_dl2_ff128-ep500]:[d64_el3_dl3_ff128-ep1000]]),1,0) -> 1 | V28: =IF(H28=MIN(Tabelle4[[#This Row],[d32_el2_dl2_ff128-ep500]:[d64_el3_dl3_ff128-ep1000]]),1,0) -> 0 | W28: =IF(I28=MIN(Tabelle4[[#This Row],[d32_el2_dl2_ff128-ep500]:[d64_el3_dl3_ff128-ep1000]]),1,0) -> 0 | X28: =IF(J28=MIN(Tabelle4[[#This Row],[d32_el2_dl2_ff128-ep500]:[d64_el3_dl3_ff128-ep1000]]),1,0) -> 0 | Y28: =IF(K28=MIN(Tabelle4[[#This Row],[d32_el2_dl2_ff128-ep500]:[d64_el3_dl3_ff128-ep1000]]),1,0) -> 0 | Z28: =IF(L28=MIN(Tabelle4[[#This Row],[d32_el2_dl2_ff128-ep500]:[d64_el3_dl3_ff128-ep1000]]),1,0) -> 1 | AA28: =IF(M28=MIN(Tabelle4[[#This Row],[d32_el2_dl2_ff128-ep500]:[d64_el3_dl3_ff128-ep1000]]),1,0) -> 0
A29: 6 | B29: d64_el3_dl3_ff128-ep1000 | C29: ['kann', 'bitte', 'helfen', 'bitte'] | D29: 10 | E29: =D29+E22 -> 25 | G29: 28 | H29: {=INDEX($D$2:$D$701, (ROW()-ROW($G$2))*7 + (COLUMN()-COLUMN($G$2)) + 1)} -> 10 | I29: {=INDEX($D$2:$D$701, (ROW()-ROW($G$2))*7 + (COLUMN()-COLUMN($G$2)) + 1)} -> 10 | J29: {=INDEX($D$2:$D$701, (ROW()-ROW($G$2))*7 + (COLUMN()-COLUMN($G$2)) + 1)} -> 10 | K29: {=INDEX($D$2:$D$701, (ROW()-ROW($G$2))*7 + (COLUMN()-COLUMN($G$2)) + 1)} -> 10 | L29: {=INDEX($D$2:$D$701, (ROW()-ROW($G$2))*7 + (COLUMN()-COLUMN($G$2)) + 1)} -> 7 | M29: {=INDEX($D$2:$D$701, (ROW()-ROW($G$2))*7 + (COLUMN()-COLUMN($G$2)) + 1)} -> 9 | O29: =IF(H29=MAX(Tabelle4[[#This Row],[d32_el2_dl2_ff128-ep500]:[d64_el3_dl3_ff128-ep1000]]),1,0) -> 1 | P29: =IF(I29=MAX(Tabelle4[[#This Row],[d32_el2_dl2_ff128-ep500]:[d64_el3_dl3_ff128-ep1000]]),1,0) -> 1 | Q29: =IF(J29=MAX(Tabelle4[[#This Row],[d32_el2_dl2_ff128-ep500]:[d64_el3_dl3_ff128-ep1000]]),1,0) -> 1 | R29: =IF(K29=MAX(Tabelle4[[#This Row],[d32_el2_dl2_ff128-ep500]:[d64_el3_dl3_ff128-ep1000]]),1,0) -> 1 | S29: =IF(L29=MAX(Tabelle4[[#This Row],[d32_el2_dl2_ff128-ep500]:[d64_el3_dl3_ff128-ep1000]]),1,0) -> 0 | T29: =IF(M29=MAX(Tabelle4[[#This Row],[d32_el2_dl2_ff128-ep500]:[d64_el3_dl3_ff128-ep1000]]),1,0) -> 0 | V29: =IF(H29=MIN(Tabelle4[[#This Row],[d32_el2_dl2_ff128-ep500]:[d64_el3_dl3_ff128-ep1000]]),1,0) -> 0 | W29: =IF(I29=MIN(Tabelle4[[#This Row],[d32_el2_dl2_ff128-ep500]:[d64_el3_dl3_ff128-ep1000]]),1,0) -> 0 | X29: =IF(J29=MIN(Tabelle4[[#This Row],[d32_el2_dl2_ff128-ep500]:[d64_el3_dl3_ff128-ep1000]]),1,0) -> 0 | Y29: =IF(K29=MIN(Tabelle4[[#This Row],[d32_el2_dl2_ff128-ep500]:[d64_el3_dl3_ff128-ep1000]]),1,0) -> 0 | Z29: =IF(L29=MIN(Tabelle4[[#This Row],[d32_el2_dl2_ff128-ep500]:[d64_el3_dl3_ff128-ep1000]]),1,0) -> 1 | AA29: =IF(M29=MIN(Tabelle4[[#This Row],[d32_el2_dl2_ff128-ep500]:[d64_el3_dl3_ff128-ep1000]]),1,0) -> 0
A30: 0 | B30: 5 | C30: Was gibt es heute zu essen? | E30: =D30+E23 -> 0 | G30: 29 | H30: {=INDEX($D$2:$D$701, (ROW()-ROW($G$2))*7 + (COLUMN()-COLUMN($G$2)) + 1)} -> 6 | I30: {=INDEX($D$2:$D$701, (ROW()-ROW($G$2))*7 + (COLUMN()-COLUMN($G$2)) + 1)} -> 8 | J30: {=INDEX($D$2:$D$701, (ROW()-ROW($G$2))*7 + (COLUMN()-COLUMN($G$2)) + 1)} -> 2 | K30: {=INDEX($D$2:$D$701, (ROW()-ROW($G$2))*7 + (COLUMN()-COLUMN($G$2)) + 1)} -> 2 | L30: {=INDEX($D$2:$D$701, (ROW()-ROW($G$2))*7 + (COLUMN()-COLUMN($G$2)) + 1)} -> 0 | M30: {=INDEX($D$2:$D$701, (ROW()-ROW($G$2))*7 + (COLUMN()-COLUMN($G$2)) + 1)} -> 0 | O30: =IF(H30=MAX(Tabelle4[[#This Row],[d32_el2_dl2_ff128-ep500]:[d64_el3_dl3_ff128-ep1000]]),1,0) -> 0 | P30: =IF(I30=MAX(Tabelle4[[#This Row],[d32_el2_dl2_ff128-ep500]:[d64_el3_dl3_ff128-ep1000]]),1,0) -> 1 | Q30: =IF(J30=MAX(Tabelle4[[#This Row],[d32_el2_dl2_ff128-ep500]:[d64_el3_dl3_ff128-ep1000]]),1,0) -> 0 | R30: =IF(K30=MAX(Tabelle4[[#This Row],[d32_el2_dl2_ff128-ep500]:[d64_el3_dl3_ff128-ep1000]]),1,0) -> 0 | S30: =IF(L30=MAX(Tabelle4[[#This Row],[d32_el2_dl2_ff128-ep500]:[d64_el3_dl3_ff128-ep1000]]),1,0) -> 0 | T30: =IF(M30=MAX(Tabelle4[[#This Row],[d32_el2_dl2_ff128-ep500]:[d64_el3_dl3_ff128-ep1000]]),1,0) -> 0 | V30: =IF(H30=MIN(Tabelle4[[#This Row],[d32_el2_dl2_ff128-ep500]:[d64_el3_dl3_ff128-ep1000]]),1,0) -> 0 | W30: =IF(I30=MIN(Tabelle4[[#This Row],[d32_el2_dl2_ff128-ep500]:[d64_el3_dl3_ff128-ep1000]]),1,0) -> 0 | X30: =IF(J30=MIN(Tabelle4[[#This Row],[d32_el2_dl2_ff128-ep500]:[d64_el3_dl3_ff128-ep1000]]),1,0) -> 0 | Y30: =IF(K30=MIN(Tabelle4[[#This Row],[d32_el2_dl2_ff128-ep500]:[d64_el3_dl3_ff128-ep1000]]),1,0) -> 0 | Z30: =IF(L30=MIN(Tabelle4[[#This Row],[d32_el2_dl2_ff128-ep500]:[d64_el3_dl3_ff128-ep1000]]),1,0) -> 1 | AA30: =IF(M30=MIN(Tabelle4[[#This Row],[d32_el2_dl2_ff128-ep500]:[d64_el3_dl3_ff128-ep1000]]),1,0) -> 1
A31: 1 | B31: d32_el2_dl2_ff128-ep500 | C31: ['heute', 'essen', 'heute'] | D31: 9 | E31: =D31+E24 -> 33 | G31: 30 | H31: {=INDEX($D$2:$D$701, (ROW()-ROW($G$2))*7 + (COLUMN()-COLUMN($G$2)) + 1)} -> 10 | I31: {=INDEX($D$2:$D$701, (ROW()-ROW($G$2))*7 + (COLUMN()-COLUMN($G$2)) + 1)} -> 10 | J31: {=INDEX($D$2:$D$701, (ROW()-ROW($G$2))*7 + (COLUMN()-COLUMN($G$2)) + 1)} -> 10 | K31: {=INDEX($D$2:$D$701, (ROW()-ROW($G$2))*7 + (COLUMN()-COLUMN($G$2)) + 1)} -> 10 | L31: {=INDEX($D$2:$D$701, (ROW()-ROW($G$2))*7 + (COLUMN()-COLUMN($G$2)) + 1)} -> 10 | M31: {=INDEX($D$2:$D$701, (ROW()-ROW($G$2))*7 + (COLUMN()-COLUMN($G$2)) + 1)} -> 10 | O31: =IF(H31=MAX(Tabelle4[[#This Row],[d32_el2_dl2_ff128-ep500]:[d64_el3_dl3_ff128-ep1000]]),1,0) -> 1 | P31: =IF(I31=MAX(Tabelle4[[#This Row],[d32_el2_dl2_ff128-ep500]:[d64_el3_dl3_ff128-ep1000]]),1,0) -> 1 | Q31: =IF(J31=MAX(Tabelle4[[#This Row],[d32_el2_dl2_ff128-ep500]:[d64_el3_dl3_ff128-ep1000]]),1,0) -> 1 | R31: =IF(K31=MAX(Tabelle4[[#This Row],[d32_el2_dl2_ff128-ep500]:[d64_el3_dl3_ff128-ep1000]]),1,0) -> 1 | S31: =IF(L31=MAX(Tabelle4[[#This Row],[d32_el2_dl2_ff128-ep500]:[d64_el3_dl3_ff128-ep1000]]),1,0) -> 1 | T31: =IF(M31=MAX(Tabelle4[[#This Row],[d32_el2_dl2_ff128-ep500]:[d64_el3_dl3_ff128-ep1000]]),1,0) -> 1 | V31: =IF(H31=MIN(Tabelle4[[#This Row],[d32_el2_dl2_ff128-ep500]:[d64_el3_dl3_ff128-ep1000]]),1,0) -> 1 | W31: =IF(I31=MIN(Tabelle4[[#This Row],[d32_el2_dl2_ff128-ep500]:[d64_el3_dl3_ff128-ep1000]]),1,0) -> 1 | X31: =IF(J31=MIN(Tabelle4[[#This Row],[d32_el2_dl2_ff128-ep500]:[d64_el3_dl3_ff128-ep1000]]),1,0) -> 1 | Y31: =IF(K31=MIN(Tabelle4[[#This Row],[d32_el2_dl2_ff128-ep500]:[d64_el3_dl3_ff128-ep1000]]),1,0) -> 1 | Z31: =IF(L31=MIN(Tabelle4[[#This Row],[d32_el2_dl2_ff128-ep500]:[d64_el3_dl3_ff128-ep1000]]),1,0) -> 1 | AA31: =IF(M31=MIN(Tabelle4[[#This Row],[d32_el2_dl2_ff128-ep500]:[d64_el3_dl3_ff128-ep1000]]),1,0) -> 1
A32: 2 | B32: d64_el1_dl1_ff64-ep1000 | C32: ['heute', 'essen', 'heute', 'essen'] | D32: 8 | E32: =D32+E25 -> 26 | G32: 31 | H32: {=INDEX($D$2:$D$701, (ROW()-ROW($G$2))*7 + (COLUMN()-COLUMN($G$2)) + 1)} -> 6 | I32: {=INDEX($D$2:$D$701, (ROW()-ROW($G$2))*7 + (COLUMN()-COLUMN($G$2)) + 1)} -> 10 | J32: {=INDEX($D$2:$D$701, (ROW()-ROW($G$2))*7 + (COLUMN()-COLUMN($G$2)) + 1)} -> 8 | K32: {=INDEX($D$2:$D$701, (ROW()-ROW($G$2))*7 + (COLUMN()-COLUMN($G$2)) + 1)} -> 8 | L32: {=INDEX($D$2:$D$701, (ROW()-ROW($G$2))*7 + (COLUMN()-COLUMN($G$2)) + 1)} -> 9 | M32: {=INDEX($D$2:$D$701, (ROW()-ROW($G$2))*7 + (COLUMN()-COLUMN($G$2)) + 1)} -> 6 | O32: =IF(H32=MAX(Tabelle4[[#This Row],[d32_el2_dl2_ff128-ep500]:[d64_el3_dl3_ff128-ep1000]]),1,0) -> 0 | P32: =IF(I32=MAX(Tabelle4[[#This Row],[d32_el2_dl2_ff128-ep500]:[d64_el3_dl3_ff128-ep1000]]),1,0) -> 1 | Q32: =IF(J32=MAX(Tabelle4[[#This Row],[d32_el2_dl2_ff128-ep500]:[d64_el3_dl3_ff128-ep1000]]),1,0) -> 0 | R32: =IF(K32=MAX(Tabelle4[[#This Row],[d32_el2_dl2_ff128-ep500]:[d64_el3_dl3_ff128-ep1000]]),1,0) -> 0 | S32: =IF(L32=MAX(Tabelle4[[#This Row],[d32_el2_dl2_ff128-ep500]:[d64_el3_dl3_ff128-ep1000]]),1,0) -> 0 | T32: =IF(M32=MAX(Tabelle4[[#This Row],[d32_el2_dl2_ff128-ep500]:[d64_el3_dl3_ff128-ep1000]]),1,0) -> 0 | V32: =IF(H32=MIN(Tabelle4[[#This Row],[d32_el2_dl2_ff128-ep500]:[d64_el3_dl3_ff128-ep1000]]),1,0) -> 1 | W32: =IF(I32=MIN(Tabelle4[[#This Row],[d32_el2_dl2_ff128-ep500]:[d64_el3_dl3_ff128-ep1000]]),1,0) -> 0 | X32: =IF(J32=MIN(Tabelle4[[#This Row],[d32_el2_dl2_ff128-ep500]:[d64_el3_dl3_ff128-ep1000]]),1,0) -> 0 | Y32: =IF(K32=MIN(Tabelle4[[#This Row],[d32_el2_dl2_ff128-ep500]:[d64_el3_dl3_ff128-ep1000]]),1,0) -> 0 | Z32: =IF(L32=MIN(Tabelle4[[#This Row],[d32_el2_dl2_ff128-ep500]:[d64_el3_dl3_ff128-ep1000]]),1,0) -> 0 | AA32: =IF(M32=MIN(Tabelle4[[#This Row],[d32_el2_dl2_ff128-ep500]:[d64_el3_dl3_ff128-ep1000]]),1,0) -> 1
A33: 3 | B33: d64_el2_dl2_ff64-ep500 | C33: ['heute', 'essen', 'heute'] | D33: 9 | E33: =D33+E26 -> 33 | G33: 32 | H33: {=INDEX($D$2:$D$701, (ROW()-ROW($G$2))*7 + (COLUMN()-COLUMN($G$2)) + 1)} -> 6 | I33: {=INDEX($D$2:$D$701, (ROW()-ROW($G$2))*7 + (COLUMN()-COLUMN($G$2)) + 1)} -> 10 | J33: {=INDEX($D$2:$D$701, (ROW()-ROW($G$2))*7 + (COLUMN()-COLUMN($G$2)) + 1)} -> 9 | K33: {=INDEX($D$2:$D$701, (ROW()-ROW($G$2))*7 + (COLUMN()-COLUMN($G$2)) + 1)} -> 9 | L33: {=INDEX($D$2:$D$701, (ROW()-ROW($G$2))*7 + (COLUMN()-COLUMN($G$2)) + 1)} -> 5 | M33: {=INDEX($D$2:$D$701, (ROW()-ROW($G$2))*7 + (COLUMN()-COLUMN($G$2)) + 1)} -> 7 | O33: =IF(H33=MAX(Tabelle4[[#This Row],[d32_el2_dl2_ff128-ep500]:[d64_el3_dl3_ff128-ep1000]]),1,0) -> 0 | P33: =IF(I33=MAX(Tabelle4[[#This Row],[d32_el2_dl2_ff128-ep500]:[d64_el3_dl3_ff128-ep1000]]),1,0) -> 1 | Q33: =IF(J33=MAX(Tabelle4[[#This Row],[d32_el2_dl2_ff128-ep500]:[d64_el3_dl3_ff128-ep1000]]),1,0) -> 0 | R33: =IF(K33=MAX(Tabelle4[[#This Row],[d32_el2_dl2_ff128-ep500]:[d64_el3_dl3_ff128-ep1000]]),1,0) -> 0 | S33: =IF(L33=MAX(Tabelle4[[#This Row],[d32_el2_dl2_ff128-ep500]:[d64_el3_dl3_ff128-ep1000]]),1,0) -> 0 | T33: =IF(M33=MAX(Tabelle4[[#This Row],[d32_el2_dl2_ff128-ep500]:[d64_el3_dl3_ff128-ep1000]]),1,0) -> 0 | V33: =IF(H33=MIN(Tabelle4[[#This Row],[d32_el2_dl2_ff128-ep500]:[d64_el3_dl3_ff128-ep1000]]),1,0) -> 0 | W33: =IF(I33=MIN(Tabelle4[[#This Row],[d32_el2_dl2_ff128-ep500]:[d64_el3_dl3_ff128-ep1000]]),1,0) -> 0 | X33: =IF(J33=MIN(Tabelle4[[#This Row],[d32_el2_dl2_ff128-ep500]:[d64_el3_dl3_ff128-ep1000]]),1,0) -> 0 | Y33: =IF(K33=MIN(Tabelle4[[#This Row],[d32_el2_dl2_ff128-ep500]:[d64_el3_dl3_ff128-ep1000]]),1,0) -> 0 | Z33: =IF(L33=MIN(Tabelle4[[#This Row],[d32_el2_dl2_ff128-ep500]:[d64_el3_dl3_ff128-ep1000]]),1,0) -> 1 | AA33: =IF(M33=MIN(Tabelle4[[#This Row],[d32_el2_dl2_ff128-ep500]:[d64_el3_dl3_ff128-ep1000]]),1,0) -> 0
A34: 4 | B34: d64_el2_dl2_ff64-ep1000 | C34: ['heute', 'essen', 'heute'] | D34: 9 | E34: =D34+E27 -> 33 | G34: 33 | H34: {=INDEX($D$2:$D$701, (ROW()-ROW($G$2))*7 + (COLUMN()-COLUMN($G$2)) + 1)} -> 9 | I34: {=INDEX($D$2:$D$701, (ROW()-ROW($G$2))*7 + (COLUMN()-COLUMN($G$2)) + 1)} -> 9 | J34: {=INDEX($D$2:$D$701, (ROW()-ROW($G$2))*7 + (COLUMN()-COLUMN($G$2)) + 1)} -> 9 | K34: {=INDEX($D$2:$D$701, (ROW()-ROW($G$2))*7 + (COLUMN()-COLUMN($G$2)) + 1)} -> 9 | L34: {=INDEX($D$2:$D$701, (ROW()-ROW($G$2))*7 + (COLUMN()-COLUMN($G$2)) + 1)} -> 10 | M34: {=INDEX($D$2:$D$701, (ROW()-ROW($G$2))*7 + (COLUMN()-COLUMN($G$2)) + 1)} -> 10 | O34: =IF(H34=MAX(Tabelle4[[#This Row],[d32_el2_dl2_ff128-ep500]:[d64_el3_dl3_ff128-ep1000]]),1,0) -> 0 | P34: =IF(I34=MAX(Tabelle4[[#This Row],[d32_el2_dl2_ff128-ep500]:[d64_el3_dl3_ff128-ep1000]]),1,0) -> 0 | Q34: =IF(J34=MAX(Tabelle4[[#This Row],[d32_el2_dl2_ff128-ep500]:[d64_el3_dl3_ff128-ep1000]]),1,0) -> 0 | R34: =IF(K34=MAX(Tabelle4[[#This Row],[d32_el2_dl2_ff128-ep500]:[d64_el3_dl3_ff128-ep1000]]),1,0) -> 0 | S34: =IF(L34=MAX(Tabelle4[[#This Row],[d32_el2_dl2_ff128-ep500]:[d64_el3_dl3_ff128-ep1000]]),1,0) -> 1 | T34: =IF(M34=MAX(Tabelle4[[#This Row],[d32_el2_dl2_ff128-ep500]:[d64_el3_dl3_ff128-ep1000]]),1,0) -> 1 | V34: =IF(H34=MIN(Tabelle4[[#This Row],[d32_el2_dl2_ff128-ep500]:[d64_el3_dl3_ff128-ep1000]]),1,0) -> 1 | W34: =IF(I34=MIN(Tabelle4[[#This Row],[d32_el2_dl2_ff128-ep500]:[d64_el3_dl3_ff128-ep1000]]),1,0) -> 1 | X34: =IF(J34=MIN(Tabelle4[[#This Row],[d32_el2_dl2_ff128-ep500]:[d64_el3_dl3_ff128-ep1000]]),1,0) -> 1 | Y34: =IF(K34=MIN(Tabelle4[[#This Row],[d32_el2_dl2_ff128-ep500]:[d64_el3_dl3_ff128-ep1000]]),1,0) -> 1 | Z34: =IF(L34=MIN(Tabelle4[[#This Row],[d32_el2_dl2_ff128-ep500]:[d64_el3_dl3_ff128-ep1000]]),1,0) -> 0 | AA34: =IF(M34=MIN(Tabelle4[[#This Row],[d32_el2_dl2_ff128-ep500]:[d64_el3_dl3_ff128-ep1000]]),1,0) -> 0
A35: 5 | B35: d64_el2_dl2_ff128-ep1000 | C35: ['essen', 'heute', 'essen', 'heute'] | D35: 8 | E35: =D35+E28 -> 30 | G35: 34 | H35: {=INDEX($D$2:$D$701, (ROW()-ROW($G$2))*7 + (COLUMN()-COLUMN($G$2)) + 1)} -> 6 | I35: {=INDEX($D$2:$D$701, (ROW()-ROW($G$2))*7 + (COLUMN()-COLUMN($G$2)) + 1)} -> 8 | J35: {=INDEX($D$2:$D$701, (ROW()-ROW($G$2))*7 + (COLUMN()-COLUMN($G$2)) + 1)} -> 9 | K35: {=INDEX($D$2:$D$701, (ROW()-ROW($G$2))*7 + (COLUMN()-COLUMN($G$2)) + 1)} -> 9 | L35: {=INDEX($D$2:$D$701, (ROW()-ROW($G$2))*7 + (COLUMN()-COLUMN($G$2)) + 1)} -> 9 | M35: {=INDEX($D$2:$D$701, (ROW()-ROW($G$2))*7 + (COLUMN()-COLUMN($G$2)) + 1)} -> 2 | O35: =IF(H35=MAX(Tabelle4[[#This Row],[d32_el2_dl2_ff128-ep500]:[d64_el3_dl3_ff128-ep1000]]),1,0) -> 0 | P35: =IF(I35=MAX(Tabelle4[[#This Row],[d32_el2_dl2_ff128-ep500]:[d64_el3_dl3_ff128-ep1000]]),1,0) -> 0 | Q35: =IF(J35=MAX(Tabelle4[[#This Row],[d32_el2_dl2_ff128-ep500]:[d64_el3_dl3_ff128-ep1000]]),1,0) -> 1 | R35: =IF(K35=MAX(Tabelle4[[#This Row],[d32_el2_dl2_ff128-ep500]:[d64_el3_dl3_ff128-ep1000]]),1,0) -> 1 | S35: =IF(L35=MAX(Tabelle4[[#This Row],[d32_el2_dl2_ff128-ep500]:[d64_el3_dl3_ff128-ep1000]]),1,0) -> 1 | T35: =IF(M35=MAX(Tabelle4[[#This Row],[d32_el2_dl2_ff128-ep500]:[d64_el3_dl3_ff128-ep1000]]),1,0) -> 0 | V35: =IF(H35=MIN(Tabelle4[[#This Row],[d32_el2_dl2_ff128-ep500]:[d64_el3_dl3_ff128-ep1000]]),1,0) -> 0 | W35: =IF(I35=MIN(Tabelle4[[#This Row],[d32_el2_dl2_ff128-ep500]:[d64_el3_dl3_ff128-ep1000]]),1,0) -> 0 | X35: =IF(J35=MIN(Tabelle4[[#This Row],[d32_el2_dl2_ff128-ep500]:[d64_el3_dl3_ff128-ep1000]]),1,0) -> 0 | Y35: =IF(K35=MIN(Tabelle4[[#This Row],[d32_el2_dl2_ff128-ep500]:[d64_el3_dl3_ff128-ep1000]]),1,0) -> 0 | Z35: =IF(L35=MIN(Tabelle4[[#This Row],[d32_el2_dl2_ff128-ep500]:[d64_el3_dl3_ff128-ep1000]]),1,0) -> 0 | AA35: =IF(M35=MIN(Tabelle4[[#This Row],[d32_el2_dl2_ff128-ep500]:[d64_el3_dl3_ff128-ep1000]]),1,0) -> 1
A36: 6 | B36: d64_el3_dl3_ff128-ep1000 | C36: ['heute', 'essen', 'off'] | D36: 9 | E36: =D36+E29 -> 34 | G36: 35 | H36: {=INDEX($D$2:$D$701, (ROW()-ROW($G$2))*7 + (COLUMN()-COLUMN($G$2)) + 1)} -> 8 | I36: {=INDEX($D$2:$D$701, (ROW()-ROW($G$2))*7 + (COLUMN()-COLUMN($G$2)) + 1)} -> 9 | J36: {=INDEX($D$2:$D$701, (ROW()-ROW($G$2))*7 + (COLUMN()-COLUMN($G$2)) + 1)} -> 5 | K36: {=INDEX($D$2:$D$701, (ROW()-ROW($G$2))*7 + (COLUMN()-COLUMN($G$2)) + 1)} -> 10 | L36: {=INDEX($D$2:$D$701, (ROW()-ROW($G$2))*7 + (COLUMN()-COLUMN($G$2)) + 1)} -> 9 | M36: {=INDEX($D$2:$D$701, (ROW()-ROW($G$2))*7 + (COLUMN()-COLUMN($G$2)) + 1)} -> 3 | O36: =IF(H36=MAX(Tabelle4[[#This Row],[d32_el2_dl2_ff128-ep500]:[d64_el3_dl3_ff128-ep1000]]),1,0) -> 0 | P36: =IF(I36=MAX(Tabelle4[[#This Row],[d32_el2_dl2_ff128-ep500]:[d64_el3_dl3_ff128-ep1000]]),1,0) -> 0 | Q36: =IF(J36=MAX(Tabelle4[[#This Row],[d32_el2_dl2_ff128-ep500]:[d64_el3_dl3_ff128-ep1000]]),1,0) -> 0 | R36: =IF(K36=MAX(Tabelle4[[#This Row],[d32_el2_dl2_ff128-ep500]:[d64_el3_dl3_ff128-ep1000]]),1,0) -> 1 | S36: =IF(L36=MAX(Tabelle4[[#This Row],[d32_el2_dl2_ff128-ep500]:[d64_el3_dl3_ff128-ep1000]]),1,0) -> 0 | T36: =IF(M36=MAX(Tabelle4[[#This Row],[d32_el2_dl2_ff128-ep500]:[d64_el3_dl3_ff128-ep1000]]),1,0) -> 0 | V36: =IF(H36=MIN(Tabelle4[[#This Row],[d32_el2_dl2_ff128-ep500]:[d64_el3_dl3_ff128-ep1000]]),1,0) -> 0 | W36: =IF(I36=MIN(Tabelle4[[#This Row],[d32_el2_dl2_ff128-ep500]:[d64_el3_dl3_ff128-ep1000]]),1,0) -> 0 | X36: =IF(J36=MIN(Tabelle4[[#This Row],[d32_el2_dl2_ff128-ep500]:[d64_el3_dl3_ff128-ep1000]]),1,0) -> 0 | Y36: =IF(K36=MIN(Tabelle4[[#This Row],[d32_el2_dl2_ff128-ep500]:[d64_el3_dl3_ff128-ep1000]]),1,0) -> 0 | Z36: =IF(L36=MIN(Tabelle4[[#This Row],[d32_el2_dl2_ff128-ep500]:[d64_el3_dl3_ff128-ep1000]]),1,0) -> 0 | AA36: =IF(M36=MIN(Tabelle4[[#This Row],[d32_el2_dl2_ff128-ep500]:[d64_el3_dl3_ff128-ep1000]]),1,0) -> 1
A37: 0 | B37: 6 | C37: Ich habe meinen SchlÃ¼ssel verloren. | E37: =D37+E30 -> 0 | G37: 36 | H37: {=INDEX($D$2:$D$701, (ROW()-ROW($G$2))*7 + (COLUMN()-COLUMN($G$2)) + 1)} -> 7 | I37: {=INDEX($D$2:$D$701, (ROW()-ROW($G$2))*7 + (COLUMN()-COLUMN($G$2)) + 1)} -> 5 | J37: {=INDEX($D$2:$D$701, (ROW()-ROW($G$2))*7 + (COLUMN()-COLUMN($G$2)) + 1)} -> 5 | K37: {=INDEX($D$2:$D$701, (ROW()-ROW($G$2))*7 + (COLUMN()-COLUMN($G$2)) + 1)} -> 5 | L37: {=INDEX($D$2:$D$701, (ROW()-ROW($G$2))*7 + (COLUMN()-COLUMN($G$2)) + 1)} -> 5 | M37: {=INDEX($D$2:$D$701, (ROW()-ROW($G$2))*7 + (COLUMN()-COLUMN($G$2)) + 1)} -> 10 | O37: =IF(H37=MAX(Tabelle4[[#This Row],[d32_el2_dl2_ff128-ep500]:[d64_el3_dl3_ff128-ep1000]]),1,0) -> 0 | P37: =IF(I37=MAX(Tabelle4[[#This Row],[d32_el2_dl2_ff128-ep500]:[d64_el3_dl3_ff128-ep1000]]),1,0) -> 0 | Q37: =IF(J37=MAX(Tabelle4[[#This Row],[d32_el2_dl2_ff128-ep500]:[d64_el3_dl3_ff128-ep1000]]),1,0) -> 0 | R37: =IF(K37=MAX(Tabelle4[[#This Row],[d32_el2_dl2_ff128-ep500]:[d64_el3_dl3_ff128-ep1000]]),1,0) -> 0 | S37: =IF(L37=MAX(Tabelle4[[#This Row],[d32_el2_dl2_ff128-ep500]:[d64_el3_dl3_ff128-ep1000]]),1,0) -> 0 | T37: =IF(M37=MAX(Tabelle4[[#This Row],[d32_el2_dl2_ff128-ep500]:[d64_el3_dl3_ff128-ep1000]]),1,0) -> 1 | V37: =IF(H37=MIN(Tabelle4[[#This Row],[d32_el2_dl2_ff128-ep500]:[d64_el3_dl3_ff128-ep1000]]),1,0) -> 0 | W37: =IF(I37=MIN(Tabelle4[[#This Row],[d32_el2_dl2_ff128-ep500]:[d64_el3_dl3_ff128-ep1000]]),1,0) -> 1 | X37: =IF(J37=MIN(Tabelle4[[#This Row],[d32_el2_dl2_ff128-ep500]:[d64_el3_dl3_ff128-ep1000]]),1,0) -> 1 | Y37: =IF(K37=MIN(Tabelle4[[#This Row],[d32_el2_dl2_ff128-ep500]:[d64_el3_dl3_ff128-ep1000]]),1,0) -> 1 | Z37: =IF(L37=MIN(Tabelle4[[#This Row],[d32_el2_dl2_ff128-ep500]:[d64_el3_dl3_ff128-ep1000]]),1,0) -> 1 | AA37: =IF(M37=MIN(Tabelle4[[#This Row],[d32_el2_dl2_ff128-ep500]:[d64_el3_dl3_ff128-ep1000]]),1,0) -> 0
A38: 1 | B38: d32_el2_dl2_ff128-ep500 | C38: ['ich', 'verlieren', 'ich', 'verlieren'] | D38: 5 | E38: =D38+E31 -> 38 | G38: 37 | H38: {=INDEX($D$2:$D$701, (ROW()-ROW($G$2))*7 + (COLUMN()-COLUMN($G$2)) + 1)} -> 10 | I38: {=INDEX($D$2:$D$701, (ROW()-ROW($G$2))*7 + (COLUMN()-COLUMN($G$2)) + 1)} -> 8 | J38: {=INDEX($D$2:$D$701, (ROW()-ROW($G$2))*7 + (COLUMN()-COLUMN($G$2)) + 1)} -> 8 | K38: {=INDEX($D$2:$D$701, (ROW()-ROW($G$2))*7 + (COLUMN()-COLUMN($G$2)) + 1)} -> 8 | L38: {=INDEX($D$2:$D$701, (ROW()-ROW($G$2))*7 + (COLUMN()-COLUMN($G$2)) + 1)} -> 10 | M38: {=INDEX($D$2:$D$701, (ROW()-ROW($G$2))*7 + (COLUMN()-COLUMN($G$2)) + 1)} -> 10 | O38: =IF(H38=MAX(Tabelle4[[#This Row],[d32_el2_dl2_ff128-ep500]:[d64_el3_dl3_ff128-ep1000]]),1,0) -> 1 | P38: =IF(I38=MAX(Tabelle4[[#This Row],[d32_el2_dl2_ff128-ep500]:[d64_el3_dl3_ff128-ep1000]]),1,0) -> 0 | Q38: =IF(J38=MAX(Tabelle4[[#This Row],[d32_el2_dl2_ff128-ep500]:[d64_el3_dl3_ff128-ep1000]]),1,0) -> 0 | R38: =IF(K38=MAX(Tabelle4[[#This Row],[d32_el2_dl2_ff128-ep500]:[d64_el3_dl3_ff128-ep1000]]),1,0) -> 0 | S38: =IF(L38=MAX(Tabelle4[[#This Row],[d32_el2_dl2_ff128-ep500]:[d64_el3_dl3_ff128-ep1000]]),1,0) -> 1 | T38: =IF(M38=MAX(Tabelle4[[#This Row],[d32_el2_dl2_ff128-ep500]:[d64_el3_dl3_ff128-ep1000]]),1,0) -> 1 | V38: =IF(H38=MIN(Tabelle4[[#This Row],[d32_el2_dl2_ff128-ep500]:[d64_el3_dl3_ff128-ep1000]]),1,0) -> 0 | W38: =IF(I38=MIN(Tabelle4[[#This Row],[d32_el2_dl2_ff128-ep500]:[d64_el3_dl3_ff128-ep1000]]),1,0) -> 1 | X38: =IF(J38=MIN(Tabelle4[[#This Row],[d32_el2_dl2_ff128-ep500]:[d64_el3_dl3_ff128-ep1000]]),1,0) -> 1 | Y38: =IF(K38=MIN(Tabelle4[[#This Row],[d32_el2_dl2_ff128-ep500]:[d64_el3_dl3_ff128-ep1000]]),1,0) -> 1 | Z38: =IF(L38=MIN(Tabelle4[[#This Row],[d32_el2_dl2_ff128-ep500]:[d64_el3_dl3_ff128-ep1000]]),1,0) -> 0 | AA38: =IF(M38=MIN(Tabelle4[[#This Row],[d32_el2_dl2_ff128-ep500]:[d64_el3_dl3_ff128-ep1000]]),1,0) -> 0
A39: 2 | B39: d64_el1_dl1_ff64-ep1000 | C39: ['ich', 'loser'] | D39: 2 | E39: =D39+E32 -> 28 | G39: 38 | H39: {=INDEX($D$2:$D$701, (ROW()-ROW($G$2))*7 + (COLUMN()-COLUMN($G$2)) + 1)} -> 10 | I39: {=INDEX($D$2:$D$701, (ROW()-ROW($G$2))*7 + (COLUMN()-COLUMN($G$2)) + 1)} -> 9 | J39: {=INDEX($D$2:$D$701, (ROW()-ROW($G$2))*7 + (COLUMN()-COLUMN($G$2)) + 1)} -> 4 | K39: {=INDEX($D$2:$D$701, (ROW()-ROW($G$2))*7 + (COLUMN()-COLUMN($G$2)) + 1)} -> 10 | L39: {=INDEX($D$2:$D$701, (ROW()-ROW($G$2))*7 + (COLUMN()-COLUMN($G$2)) + 1)} -> 10 | M39: {=INDEX($D$2:$D$701, (ROW()-ROW($G$2))*7 + (COLUMN()-COLUMN($G$2)) + 1)} -> 9 | O39: =IF(H39=MAX(Tabelle4[[#This Row],[d32_el2_dl2_ff128-ep500]:[d64_el3_dl3_ff128-ep1000]]),1,0) -> 1 | P39: =IF(I39=MAX(Tabelle4[[#This Row],[d32_el2_dl2_ff128-ep500]:[d64_el3_dl3_ff128-ep1000]]),1,0) -> 0 | Q39: =IF(J39=MAX(Tabelle4[[#This Row],[d32_el2_dl2_ff128-ep500]:[d64_el3_dl3_ff128-ep1000]]),1,0) -> 0 | R39: =IF(K39=MAX(Tabelle4[[#This Row],[d32_el2_dl2_ff128-ep500]:[d64_el3_dl3_ff128-ep1000]]),1,0) -> 1 | S39: =IF(L39=MAX(Tabelle4[[#This Row],[d32_el2_dl2_ff128-ep500]:[d64_el3_dl3_ff128-ep1000]]),1,0) -> 1 | T39: =IF(M39=MAX(Tabelle4[[#This Row],[d32_el2_dl2_ff128-ep500]:[d64_el3_dl3_ff128-ep1000]]),1,0) -> 0 | V39: =IF(H39=MIN(Tabelle4[[#This Row],[d32_el2_dl2_ff128-ep500]:[d64_el3_dl3_ff128-ep1000]]),1,0) -> 0 | W39: =IF(I39=MIN(Tabelle4[[#This Row],[d32_el2_dl2_ff128-ep500]:[d64_el3_dl3_ff128-ep1000]]),1,0) -> 0 | X39: =IF(J39=MIN(Tabelle4[[#This Row],[d32_el2_dl2_ff128-ep500]:[d64_el3_dl3_ff128-ep1000]]),1,0) -> 1 | Y39: =IF(K39=MIN(Tabelle4[[#This Row],[d32_el2_dl2_ff128-ep500]:[d64_el3_dl3_ff128-ep1000]]),1,0) -> 0 | Z39: =IF(L39=MIN(Tabelle4[[#This Row],[d32_el2_dl2_ff128-ep500]:[d64_el3_dl3_ff128-ep1000]]),1,0) -> 0 | AA39: =IF(M39=MIN(Tabelle4[[#This Row],[d32_el2_dl2_ff128-ep500]:[d64_el3_dl3_ff128-ep1000]]),1,0) -> 0
A40: 3 | B40: d64_el2_dl2_ff64-ep500 | C40: ['ich', 'das hätte ich nicht erwartet'] | D40: 1 | E40: =D40+E33 -> 34 | G40: 39 | H40: {=INDEX($D$2:$D$701, (ROW()-ROW($G$2))*7 + (COLUMN()-COLUMN($G$2)) + 1)} -> 10 | I40: {=INDEX($D$2:$D$701, (ROW()-ROW($G$2))*7 + (COLUMN()-COLUMN($G$2)) + 1)} -> 10 | J40: {=INDEX($D$2:$D$701, (ROW()-ROW($G$2))*7 + (COLUMN()-COLUMN($G$2)) + 1)} -> 10 | K40: {=INDEX($D$2:$D$701, (ROW()-ROW($G$2))*7 + (COLUMN()-COLUMN($G$2)) + 1)} -> 10 | L40: {=INDEX($D$2:$D$701, (ROW()-ROW($G$2))*7 + (COLUMN()-COLUMN($G$2)) + 1)} -> 10 | M40: {=INDEX($D$2:$D$701, (ROW()-ROW($G$2))*7 + (COLUMN()-COLUMN($G$2)) + 1)} -> 9 | O40: =IF(H40=MAX(Tabelle4[[#This Row],[d32_el2_dl2_ff128-ep500]:[d64_el3_dl3_ff128-ep1000]]),1,0) -> 1 | P40: =IF(I40=MAX(Tabelle4[[#This Row],[d32_el2_dl2_ff128-ep500]:[d64_el3_dl3_ff128-ep1000]]),1,0) -> 1 | Q40: =IF(J40=MAX(Tabelle4[[#This Row],[d32_el2_dl2_ff128-ep500]:[d64_el3_dl3_ff128-ep1000]]),1,0) -> 1 | R40: =IF(K40=MAX(Tabelle4[[#This Row],[d32_el2_dl2_ff128-ep500]:[d64_el3_dl3_ff128-ep1000]]),1,0) -> 1 | S40: =IF(L40=MAX(Tabelle4[[#This Row],[d32_el2_dl2_ff128-ep500]:[d64_el3_dl3_ff128-ep1000]]),1,0) -> 1 | T40: =IF(M40=MAX(Tabelle4[[#This Row],[d32_el2_dl2_ff128-ep500]:[d64_el3_dl3_ff128-ep1000]]),1,0) -> 0 | V40: =IF(H40=MIN(Tabelle4[[#This Row],[d32_el2_dl2_ff128-ep500]:[d64_el3_dl3_ff128-ep1000]]),1,0) -> 0 | W40: =IF(I40=MIN(Tabelle4[[#This Row],[d32_el2_dl2_ff128-ep500]:[d64_el3_dl3_ff128-ep1000]]),1,0) -> 0 | X40: =IF(J40=MIN(Tabelle4[[#This Row],[d32_el2_dl2_ff128-ep500]:[d64_el3_dl3_ff128-ep1000]]),1,0) -> 0 | Y40: =IF(K40=MIN(Tabelle4[[#This Row],[d32_el2_dl2_ff128-ep500]:[d64_el3_dl3_ff128-ep1000]]),1,0) -> 0 | Z40: =IF(L40=MIN(Tabelle4[[#This Row],[d32_el2_dl2_ff128-ep500]:[d64_el3_dl3_ff128-ep1000]]),1,0) -> 0 | AA40: =IF(M40=MIN(Tabelle4[[#This Row],[d32_el2_dl2_ff128-ep500]:[d64_el3_dl3_ff128-ep1000]]),1,0) -> 1
A41: 4 | B41: d64_el2_dl2_ff64-ep1000 | C41: ['ich', 'das hätte ich nicht erwartet'] | D41: 1 | E41: =D41+E34 -> 34 | G41: 40 | H41: {=INDEX($D$2:$D$701, (ROW()-ROW($G$2))*7 + (COLUMN()-COLUMN($G$2)) + 1)} -> 6 | I41: {=INDEX($D$2:$D$701, (ROW()-ROW($G$2))*7 + (COLUMN()-COLUMN($G$2)) + 1)} -> 9 | J41: {=INDEX($D$2:$D$701, (ROW()-ROW($G$2))*7 + (COLUMN()-COLUMN($G$2)) + 1)} -> 8 | K41: {=INDEX($D$2:$D$701, (ROW()-ROW($G$2))*7 + (COLUMN()-COLUMN($G$2)) + 1)} -> 8 | L41: {=INDEX($D$2:$D$701, (ROW()-ROW($G$2))*7 + (COLUMN()-COLUMN($G$2)) + 1)} -> 8 | M41: {=INDEX($D$2:$D$701, (ROW()-ROW($G$2))*7 + (COLUMN()-COLUMN($G$2)) + 1)} -> 9 | O41: =IF(H41=MAX(Tabelle4[[#This Row],[d32_el2_dl2_ff128-ep500]:[d64_el3_dl3_ff128-ep1000]]),1,0) -> 0 | P41: =IF(I41=MAX(Tabelle4[[#This Row],[d32_el2_dl2_ff128-ep500]:[d64_el3_dl3_ff128-ep1000]]),1,0) -> 1 | Q41: =IF(J41=MAX(Tabelle4[[#This Row],[d32_el2_dl2_ff128-ep500]:[d64_el3_dl3_ff128-ep1000]]),1,0) -> 0 | R41: =IF(K41=MAX(Tabelle4[[#This Row],[d32_el2_dl2_ff128-ep500]:[d64_el3_dl3_ff128-ep1000]]),1,0) -> 0 | S41: =IF(L41=MAX(Tabelle4[[#This Row],[d32_el2_dl2_ff128-ep500]:[d64_el3_dl3_ff128-ep1000]]),1,0) -> 0 | T41: =IF(M41=MAX(Tabelle4[[#This Row],[d32_el2_dl2_ff128-ep500]:[d64_el3_dl3_ff128-ep1000]]),1,0) -> 1 | V41: =IF(H41=MIN(Tabelle4[[#This Row],[d32_el2_dl2_ff128-ep500]:[d64_el3_dl3_ff128-ep1000]]),1,0) -> 1 | W41: =IF(I41=MIN(Tabelle4[[#This Row],[d32_el2_dl2_ff128-ep500]:[d64_el3_dl3_ff128-ep1000]]),1,0) -> 0 | X41: =IF(J41=MIN(Tabelle4[[#This Row],[d32_el2_dl2_ff128-ep500]:[d64_el3_dl3_ff128-ep1000]]),1,0) -> 0 | Y41: =IF(K41=MIN(Tabelle4[[#This Row],[d32_el2_dl2_ff128-ep500]:[d64_el3_dl3_ff128-ep1000]]),1,0) -> 0 | Z41: =IF(L41=MIN(Tabelle4[[#This Row],[d32_el2_dl2_ff128-ep500]:[d64_el3_dl3_ff128-ep1000]]),1,0) -> 0 | AA41: =IF(M41=MIN(Tabelle4[[#This Row],[d32_el2_dl2_ff128-ep500]:[d64_el3_dl3_ff128-ep1000]]),1,0) -> 0
A42: 5 | B42: d64_el2_dl2_ff128-ep1000 | C42: ['ich', 'verlieren', 'ich', 'verlieren'] | D42: 5 | E42: =D42+E35 -> 35 | G42: 41 | H42: {=INDEX($D$2:$D$701, (ROW()-ROW($G$2))*7 + (COLUMN()-COLUMN($G$2)) + 1)} -> 0 | I42: {=INDEX($D$2:$D$701, (ROW()-ROW($G$2))*7 + (COLUMN()-COLUMN($G$2)) + 1)} -> 1 | J42: {=INDEX($D$2:$D$701, (ROW()-ROW($G$2))*7 + (COLUMN()-COLUMN($G$2)) + 1)} -> 4 | K42: {=INDEX($D$2:$D$701, (ROW()-ROW($G$2))*7 + (COLUMN()-COLUMN($G$2)) + 1)} -> 4 | L42: {=INDEX($D$2:$D$701, (ROW()-ROW($G$2))*7 + (COLUMN()-COLUMN($G$2)) + 1)} -> 1 | M42: {=INDEX($D$2:$D$701, (ROW()-ROW($G$2))*7 + (COLUMN()-COLUMN($G$2)) + 1)} -> 0 | O42: =IF(H42=MAX(Tabelle4[[#This Row],[d32_el2_dl2_ff128-ep500]:[d64_el3_dl3_ff128-ep1000]]),1,0) -> 0 | P42: =IF(I42=MAX(Tabelle4[[#This Row],[d32_el2_dl2_ff128-ep500]:[d64_el3_dl3_ff128-ep1000]]),1,0) -> 0 | Q42: =IF(J42=MAX(Tabelle4[[#This Row],[d32_el2_dl2_ff128-ep500]:[d64_el3_dl3_ff128-ep1000]]),1,0) -> 1 | R42: =IF(K42=MAX(Tabelle4[[#This Row],[d32_el2_dl2_ff128-ep500]:[d64_el3_dl3_ff128-ep1000]]),1,0) -> 1 | S42: =IF(L42=MAX(Tabelle4[[#This Row],[d32_el2_dl2_ff128-ep500]:[d64_el3_dl3_ff128-ep1000]]),1,0) -> 0 | T42: =IF(M42=MAX(Tabelle4[[#This Row],[d32_el2_dl2_ff128-ep500]:[d64_el3_dl3_ff128-ep1000]]),1,0) -> 0 | V42: =IF(H42=MIN(Tabelle4[[#This Row],[d32_el2_dl2_ff128-ep500]:[d64_el3_dl3_ff128-ep1000]]),1,0) -> 1 | W42: =IF(I42=MIN(Tabelle4[[#This Row],[d32_el2_dl2_ff128-ep500]:[d64_el3_dl3_ff128-ep1000]]),1,0) -> 0 | X42: =IF(J42=MIN(Tabelle4[[#This Row],[d32_el2_dl2_ff128-ep500]:[d64_el3_dl3_ff128-ep1000]]),1,0) -> 0 | Y42: =IF(K42=MIN(Tabelle4[[#This Row],[d32_el2_dl2_ff128-ep500]:[d64_el3_dl3_ff128-ep1000]]),1,0) -> 0 | Z42: =IF(L42=MIN(Tabelle4[[#This Row],[d32_el2_dl2_ff128-ep500]:[d64_el3_dl3_ff128-ep1000]]),1,0) -> 0 | AA42: =IF(M42=MIN(Tabelle4[[#This Row],[d32_el2_dl2_ff128-ep500]:[d64_el3_dl3_ff128-ep1000]]),1,0) -> 1
A43: 6 | B43: d64_el3_dl3_ff128-ep1000 | C43: ['ich', 'verlieren', 'ich', 'off'] | D43: 5 | E43: =D43+E36 -> 39 | G43: 42 | H43: {=INDEX($D$2:$D$701, (ROW()-ROW($G$2))*7 + (COLUMN()-COLUMN($G$2)) + 1)} -> 0 | I43: {=INDEX($D$2:$D$701, (ROW()-ROW($G$2))*7 + (COLUMN()-COLUMN($G$2)) + 1)} -> 4 | J43: {=INDEX($D$2:$D$701, (ROW()-ROW($G$2))*7 + (COLUMN()-COLUMN($G$2)) + 1)} -> 5 | K43: {=INDEX($D$2:$D$701, (ROW()-ROW($G$2))*7 + (COLUMN()-COLUMN($G$2)) + 1)} -> 0 | L43: {=INDEX($D$2:$D$701, (ROW()-ROW($G$2))*7 + (COLUMN()-COLUMN($G$2)) + 1)} -> 1 | M43: {=INDEX($D$2:$D$701, (ROW()-ROW($G$2))*7 + (COLUMN()-COLUMN($G$2)) + 1)} -> 2 | O43: =IF(H43=MAX(Tabelle4[[#This Row],[d32_el2_dl2_ff128-ep500]:[d64_el3_dl3_ff128-ep1000]]),1,0) -> 0 | P43: =IF(I43=MAX(Tabelle4[[#This Row],[d32_el2_dl2_ff128-ep500]:[d64_el3_dl3_ff128-ep1000]]),1,0) -> 0 | Q43: =IF(J43=MAX(Tabelle4[[#This Row],[d32_el2_dl2_ff128-ep500]:[d64_el3_dl3_ff128-ep1000]]),1,0) -> 1 | R43: =IF(K43=MAX(Tabelle4[[#This Row],[d32_el2_dl2_ff128-ep500]:[d64_el3_dl3_ff128-ep1000]]),1,0) -> 0 | S43: =IF(L43=MAX(Tabelle4[[#This Row],[d32_el2_dl2_ff128-ep500]:[d64_el3_dl3_ff128-ep1000]]),1,0) -> 0 | T43: =IF(M43=MAX(Tabelle4[[#This Row],[d32_el2_dl2_ff128-ep500]:[d64_el3_dl3_ff128-ep1000]]),1,0) -> 0 | V43: =IF(H43=MIN(Tabelle4[[#This Row],[d32_el2_dl2_ff128-ep500]:[d64_el3_dl3_ff128-ep1000]]),1,0) -> 1 | W43: =IF(I43=MIN(Tabelle4[[#This Row],[d32_el2_dl2_ff128-ep500]:[d64_el3_dl3_ff128-ep1000]]),1,0) -> 0 | X43: =IF(J43=MIN(Tabelle4[[#This Row],[d32_el2_dl2_ff128-ep500]:[d64_el3_dl3_ff128-ep1000]]),1,0) -> 0 | Y43: =IF(K43=MIN(Tabelle4[[#This Row],[d32_el2_dl2_ff128-ep500]:[d64_el3_dl3_ff128-ep1000]]),1,0) -> 1 | Z43: =IF(L43=MIN(Tabelle4[[#This Row],[d32_el2_dl2_ff128-ep500]:[d64_el3_dl3_ff128-ep1000]]),1,0) -> 0 | AA43: =IF(M43=MIN(Tabelle4[[#This Row],[d32_el2_dl2_ff128-ep500]:[d64_el3_dl3_ff128-ep1000]]),1,0) -> 0
A44: 0 | B44: 7 | C44: Wie spÃ¤t ist es? | E44: =D44+E37 -> 0 | G44: 43 | H44: {=INDEX($D$2:$D$701, (ROW()-ROW($G$2))*7 + (COLUMN()-COLUMN($G$2)) + 1)} -> 9 | I44: {=INDEX($D$2:$D$701, (ROW()-ROW($G$2))*7 + (COLUMN()-COLUMN($G$2)) + 1)} -> 10 | J44: {=INDEX($D$2:$D$701, (ROW()-ROW($G$2))*7 + (COLUMN()-COLUMN($G$2)) + 1)} -> 10 | K44: {=INDEX($D$2:$D$701, (ROW()-ROW($G$2))*7 + (COLUMN()-COLUMN($G$2)) + 1)} -> 10 | L44: {=INDEX($D$2:$D$701, (ROW()-ROW($G$2))*7 + (COLUMN()-COLUMN($G$2)) + 1)} -> 7 | M44: {=INDEX($D$2:$D$701, (ROW()-ROW($G$2))*7 + (COLUMN()-COLUMN($G$2)) + 1)} -> 8 | O44: =IF(H44=MAX(Tabelle4[[#This Row],[d32_el2_dl2_ff128-ep500]:[d64_el3_dl3_ff128-ep1000]]),1,0) -> 0 | P44: =IF(I44=MAX(Tabelle4[[#This Row],[d32_el2_dl2_ff128-ep500]:[d64_el3_dl3_ff128-ep1000]]),1,0) -> 1 | Q44: =IF(J44=MAX(Tabelle4[[#This Row],[d32_el2_dl2_ff128-ep500]:[d64_el3_dl3_ff128-ep1000]]),1,0) -> 1 | R44: =IF(K44=MAX(Tabelle4[[#This Row],[d32_el2_dl2_ff128-ep500]:[d64_el3_dl3_ff128-ep1000]]),1,0) -> 1 | S44: =IF(L44=MAX(Tabelle4[[#This Row],[d32_el2_dl2_ff128-ep500]:[d64_el3_dl3_ff128-ep1000]]),1,0) -> 0 | T44: =IF(M44=MAX(Tabelle4[[#This Row],[d32_el2_dl2_ff128-ep500]:[d64_el3_dl3_ff128-ep1000]]),1,0) -> 0 | V44: =IF(H44=MIN(Tabelle4[[#This Row],[d32_el2_dl2_ff128-ep500]:[d64_el3_dl3_ff128-ep1000]]),1,0) -> 0 | W44: =IF(I44=MIN(Tabelle4[[#This Row],[d32_el2_dl2_ff128-ep500]:[d64_el3_dl3_ff128-ep1000]]),1,0) -> 0 | X44: =IF(J44=MIN(Tabelle4[[#This Row],[d32_el2_dl2_ff128-ep500]:[d64_el3_dl3_ff128-ep1000]]),1,0) -> 0 | Y44: =IF(K44=MIN(Tabelle4[[#This Row],[d32_el2_dl2_ff128-ep500]:[d64_el3_dl3_ff128-ep1000]]),1,0) -> 0 | Z44: =IF(L44=MIN(Tabelle4[[#This Row],[d32_el2_dl2_ff128-ep500]:[d64_el3_dl3_ff128-ep1000]]),1,0) -> 1 | AA44: =IF(M44=MIN(Tabelle4[[#This Row],[d32_el2_dl2_ff128-ep500]:[d64_el3_dl3_ff128-ep1000]]),1,0) -> 0
A45: 1 | B45: d32_el2_dl2_ff128-ep500 | C45: ['index', 'ich', 'denken', 'index'] | D45: 0 | E45: =D45+E38 -> 38 | G45: 44 | H45: {=INDEX($D$2:$D$701, (ROW()-ROW($G$2))*7 + (COLUMN()-COLUMN($G$2)) + 1)} -> 8 | I45: {=INDEX($D$2:$D$701, (ROW()-ROW($G$2))*7 + (COLUMN()-COLUMN($G$2)) + 1)} -> 7 | J45: {=INDEX($D$2:$D$701, (ROW()-ROW($G$2))*7 + (COLUMN()-COLUMN($G$2)) + 1)} -> 9 | K45: {=INDEX($D$2:$D$701, (ROW()-ROW($G$2))*7 + (COLUMN()-COLUMN($G$2)) + 1)} -> 8 | L45: {=INDEX($D$2:$D$701, (ROW()-ROW($G$2))*7 + (COLUMN()-COLUMN($G$2)) + 1)} -> 8 | M45: {=INDEX($D$2:$D$701, (ROW()-ROW($G$2))*7 + (COLUMN()-COLUMN($G$2)) + 1)} -> 9 | O45: =IF(H45=MAX(Tabelle4[[#This Row],[d32_el2_dl2_ff128-ep500]:[d64_el3_dl3_ff128-ep1000]]),1,0) -> 0 | P45: =IF(I45=MAX(Tabelle4[[#This Row],[d32_el2_dl2_ff128-ep500]:[d64_el3_dl3_ff128-ep1000]]),1,0) -> 0 | Q45: =IF(J45=MAX(Tabelle4[[#This Row],[d32_el2_dl2_ff128-ep500]:[d64_el3_dl3_ff128-ep1000]]),1,0) -> 1 | R45: =IF(K45=MAX(Tabelle4[[#This Row],[d32_el2_dl2_ff128-ep500]:[d64_el3_dl3_ff128-ep1000]]),1,0) -> 0 | S45: =IF(L45=MAX(Tabelle4[[#This Row],[d32_el2_dl2_ff128-ep500]:[d64_el3_dl3_ff128-ep1000]]),1,0) -> 0 | T45: =IF(M45=MAX(Tabelle4[[#This Row],[d32_el2_dl2_ff128-ep500]:[d64_el3_dl3_ff128-ep1000]]),1,0) -> 1 | V45: =IF(H45=MIN(Tabelle4[[#This Row],[d32_el2_dl2_ff128-ep500]:[d64_el3_dl3_ff128-ep1000]]),1,0) -> 0 | W45: =IF(I45=MIN(Tabelle4[[#This Row],[d32_el2_dl2_ff128-ep500]:[d64_el3_dl3_ff128-ep1000]]),1,0) -> 1 | X45: =IF(J45=MIN(Tabelle4[[#This Row],[d32_el2_dl2_ff128-ep500]:[d64_el3_dl3_ff128-ep1000]]),1,0) -> 0 | Y45: =IF(K45=MIN(Tabelle4[[#This Row],[d32_el2_dl2_ff128-ep500]:[d64_el3_dl3_ff128-ep1000]]),1,0) -> 0 | Z45: =IF(L45=MIN(Tabelle4[[#This Row],[d32_el2_dl2_ff128-ep500]:[d64_el3_dl3_ff128-ep1000]]),1,0) -> 0 | AA45: =IF(M45=MIN(Tabelle4[[#This Row],[d32_el2_dl2_ff128-ep500]:[d64_el3_dl3_ff128-ep1000]]),1,0) -> 0
A46: 2 | B46: d64_el1_dl1_ff64-ep1000 | C46: ['ich', 'kennen', 'nicht'] | D46: 1 | E46: =D46+E39 -> 29 | G46: 45 | H46: {=INDEX($D$2:$D$701, (ROW()-ROW($G$2))*7 + (COLUMN()-COLUMN($G$2)) + 1)} -> 9 | I46: {=INDEX($D$2:$D$701, (ROW()-ROW($G$2))*7 + (COLUMN()-COLUMN($G$2)) + 1)} -> 7 | J46: {=INDEX($D$2:$D$701, (ROW()-ROW($G$2))*7 + (COLUMN()-COLUMN($G$2)) + 1)} -> 4 | K46: {=INDEX($D$2:$D$701, (ROW()-ROW($G$2))*7 + (COLUMN()-COLUMN($G$2)) + 1)} -> 4 | L46: {=INDEX($D$2:$D$701, (ROW()-ROW($G$2))*7 + (COLUMN()-COLUMN($G$2)) + 1)} -> 10 | M46: {=INDEX($D$2:$D$701, (ROW()-ROW($G$2))*7 + (COLUMN()-COLUMN($G$2)) + 1)} -> 2 | O46: =IF(H46=MAX(Tabelle4[[#This Row],[d32_el2_dl2_ff128-ep500]:[d64_el3_dl3_ff128-ep1000]]),1,0) -> 0 | P46: =IF(I46=MAX(Tabelle4[[#This Row],[d32_el2_dl2_ff128-ep500]:[d64_el3_dl3_ff128-ep1000]]),1,0) -> 0 | Q46: =IF(J46=MAX(Tabelle4[[#This Row],[d32_el2_dl2_ff128-ep500]:[d64_el3_dl3_ff128-ep1000]]),1,0) -> 0 | R46: =IF(K46=MAX(Tabelle4[[#This Row],[d32_el2_dl2_ff128-ep500]:[d64_el3_dl3_ff128-ep1000]]),1,0) -> 0 | S46: =IF(L46=MAX(Tabelle4[[#This Row],[d32_el2_dl2_ff128-ep500]:[d64_el3_dl3_ff128-ep1000]]),1,0) -> 1 | T46: =IF(M46=MAX(Tabelle4[[#This Row],[d32_el2_dl2_ff128-ep500]:[d64_el3_dl3_ff128-ep1000]]),1,0) -> 0 | V46: =IF(H46=MIN(Tabelle4[[#This Row],[d32_el2_dl2_ff128-ep500]:[d64_el3_dl3_ff128-ep1000]]),1,0) -> 0 | W46: =IF(I46=MIN(Tabelle4[[#This Row],[d32_el2_dl2_ff128-ep500]:[d64_el3_dl3_ff128-ep1000]]),1,0) -> 0 | X46: =IF(J46=MIN(Tabelle4[[#This Row],[d32_el2_dl2_ff128-ep500]:[d64_el3_dl3_ff128-ep1000]]),1,0) -> 0 | Y46: =IF(K46=MIN(Tabelle4[[#This Row],[d32_el2_dl2_ff128-ep500]:[d64_el3_dl3_ff128-ep1000]]),1,0) -> 0 | Z46: =IF(L46=MIN(Tabelle4[[#This Row],[d32_el2_dl2_ff128-ep500]:[d64_el3_dl3_ff128-ep1000]]),1,0) -> 0 | AA46: =IF(M46=MIN(Tabelle4[[#This Row],[d32_el2_dl2_ff128-ep500]:[d64_el3_dl3_ff128-ep1000]]),1,0) -> 1
A47: 3 | B47: d64_el2_dl2_ff64-ep500 | C47: ['wie', 'arbeiten', 'index'] | D47: 1 | E47: =D47+E40 -> 35 | G47: 46 | H47: {=INDEX($D$2:$D$701, (ROW()-ROW($G$2))*7 + (COLUMN()-COLUMN($G$2)) + 1)} -> 8 | I47: {=INDEX($D$2:$D$701, (ROW()-ROW($G$2))*7 + (COLUMN()-COLUMN($G$2)) + 1)} -> 8 | J47: {=INDEX($D$2:$D$701, (ROW()-ROW($G$2))*7 + (COLUMN()-COLUMN($G$2)) + 1)} -> 8 | K47: {=INDEX($D$2:$D$701, (ROW()-ROW($G$2))*7 + (COLUMN()-COLUMN($G$2)) + 1)} -> 8 | L47: {=INDEX($D$2:$D$701, (ROW()-ROW($G$2))*7 + (COLUMN()-COLUMN($G$2)) + 1)} -> 8 | M47: {=INDEX($D$2:$D$701, (ROW()-ROW($G$2))*7 + (COLUMN()-COLUMN($G$2)) + 1)} -> 8 | O47: =IF(H47=MAX(Tabelle4[[#This Row],[d32_el2_dl2_ff128-ep500]:[d64_el3_dl3_ff128-ep1000]]),1,0) -> 1 | P47: =IF(I47=MAX(Tabelle4[[#This Row],[d32_el2_dl2_ff128-ep500]:[d64_el3_dl3_ff128-ep1000]]),1,0) -> 1 | Q47: =IF(J47=MAX(Tabelle4[[#This Row],[d32_el2_dl2_ff128-ep500]:[d64_el3_dl3_ff128-ep1000]]),1,0) -> 1 | R47: =IF(K47=MAX(Tabelle4[[#This Row],[d32_el2_dl2_ff128-ep500]:[d64_el3_dl3_ff128-ep1000]]),1,0) -> 1 | S47: =IF(L47=MAX(Tabelle4[[#This Row],[d32_el2_dl2_ff128-ep500]:[d64_el3_dl3_ff128-ep1000]]),1,0) -> 1 | T47: =IF(M47=MAX(Tabelle4[[#This Row],[d32_el2_dl2_ff128-ep500]:[d64_el3_dl3_ff128-ep1000]]),1,0) -> 1 | V47: =IF(H47=MIN(Tabelle4[[#This Row],[d32_el2_dl2_ff128-ep500]:[d64_el3_dl3_ff128-ep1000]]),1,0) -> 1 | W47: =IF(I47=MIN(Tabelle4[[#This Row],[d32_el2_dl2_ff128-ep500]:[d64_el3_dl3_ff128-ep1000]]),1,0) -> 1 | X47: =IF(J47=MIN(Tabelle4[[#This Row],[d32_el2_dl2_ff128-ep500]:[d64_el3_dl3_ff128-ep1000]]),1,0) -> 1 | Y47: =IF(K47=MIN(Tabelle4[[#This Row],[d32_el2_dl2_ff128-ep500]:[d64_el3_dl3_ff128-ep1000]]),1,0) -> 1 | Z47: =IF(L47=MIN(Tabelle4[[#This Row],[d32_el2_dl2_ff128-ep500]:[d64_el3_dl3_ff128-ep1000]]),1,0) -> 1 | AA47: =IF(M47=MIN(Tabelle4[[#This Row],[d32_el2_dl2_ff128-ep500]:[d64_el3_dl3_ff128-ep1000]]),1,0) -> 1
A48: 4 | B48: d64_el2_dl2_ff64-ep1000 | C48: ['wie', 'arbeiten', 'index'] | D48: 1 | E48: =D48+E41 -> 35 | G48: 47 | H48: {=INDEX($D$2:$D$701, (ROW()-ROW($G$2))*7 + (COLUMN()-COLUMN($G$2)) + 1)} -> 8 | I48: {=INDEX($D$2:$D$701, (ROW()-ROW($G$2))*7 + (COLUMN()-COLUMN($G$2)) + 1)} -> 8 | J48: {=INDEX($D$2:$D$701, (ROW()-ROW($G$2))*7 + (COLUMN()-COLUMN($G$2)) + 1)} -> 8 | K48: {=INDEX($D$2:$D$701, (ROW()-ROW($G$2))*7 + (COLUMN()-COLUMN($G$2)) + 1)} -> 8 | L48: {=INDEX($D$2:$D$701, (ROW()-ROW($G$2))*7 + (COLUMN()-COLUMN($G$2)) + 1)} -> 9 | M48: {=INDEX($D$2:$D$701, (ROW()-ROW($G$2))*7 + (COLUMN()-COLUMN($G$2)) + 1)} -> 8 | O48: =IF(H48=MAX(Tabelle4[[#This Row],[d32_el2_dl2_ff128-ep500]:[d64_el3_dl3_ff128-ep1000]]),1,0) -> 0 | P48: =IF(I48=MAX(Tabelle4[[#This Row],[d32_el2_dl2_ff128-ep500]:[d64_el3_dl3_ff128-ep1000]]),1,0) -> 0 | Q48: =IF(J48=MAX(Tabelle4[[#This Row],[d32_el2_dl2_ff128-ep500]:[d64_el3_dl3_ff128-ep1000]]),1,0) -> 0 | R48: =IF(K48=MAX(Tabelle4[[#This Row],[d32_el2_dl2_ff128-ep500]:[d64_el3_dl3_ff128-ep1000]]),1,0) -> 0 | S48: =IF(L48=MAX(Tabelle4[[#This Row],[d32_el2_dl2_ff128-ep500]:[d64_el3_dl3_ff128-ep1000]]),1,0) -> 1 | T48: =IF(M48=MAX(Tabelle4[[#This Row],[d32_el2_dl2_ff128-ep500]:[d64_el3_dl3_ff128-ep1000]]),1,0) -> 0 | V48: =IF(H48=MIN(Tabelle4[[#This Row],[d32_el2_dl2_ff128-ep500]:[d64_el3_dl3_ff128-ep1000]]),1,0) -> 1 | W48: =IF(I48=MIN(Tabelle4[[#This Row],[d32_el2_dl2_ff128-ep500]:[d64_el3_dl3_ff128-ep1000]]),1,0) -> 1 | X48: =IF(J48=MIN(Tabelle4[[#This Row],[d32_el2_dl2_ff128-ep500]:[d64_el3_dl3_ff128-ep1000]]),1,0) -> 1 | Y48: =IF(K48=MIN(Tabelle4[[#This Row],[d32_el2_dl2_ff128-ep500]:[d64_el3_dl3_ff128-ep1000]]),1,0) -> 1 | Z48: =IF(L48=MIN(Tabelle4[[#This Row],[d32_el2_dl2_ff128-ep500]:[d64_el3_dl3_ff128-ep1000]]),1,0) -> 0 | AA48: =IF(M48=MIN(Tabelle4[[#This Row],[d32_el2_dl2_ff128-ep500]:[d64_el3_dl3_ff128-ep1000]]),1,0) -> 1
A49: 5 | B49: d64_el2_dl2_ff128-ep1000 | C49: ['wie', 'wurscht sein', 'mord', 'off'] | D49: 0 | E49: =D49+E42 -> 35 | G49: 48 | H49: {=INDEX($D$2:$D$701, (ROW()-ROW($G$2))*7 + (COLUMN()-COLUMN($G$2)) + 1)} -> 8 | I49: {=INDEX($D$2:$D$701, (ROW()-ROW($G$2))*7 + (COLUMN()-COLUMN($G$2)) + 1)} -> 3 | J49: {=INDEX($D$2:$D$701, (ROW()-ROW($G$2))*7 + (COLUMN()-COLUMN($G$2)) + 1)} -> 9 | K49: {=INDEX($D$2:$D$701, (ROW()-ROW($G$2))*7 + (COLUMN()-COLUMN($G$2)) + 1)} -> 9 | L49: {=INDEX($D$2:$D$701, (ROW()-ROW($G$2))*7 + (COLUMN()-COLUMN($G$2)) + 1)} -> 7 | M49: {=INDEX($D$2:$D$701, (ROW()-ROW($G$2))*7 + (COLUMN()-COLUMN($G$2)) + 1)} -> 8 | O49: =IF(H49=MAX(Tabelle4[[#This Row],[d32_el2_dl2_ff128-ep500]:[d64_el3_dl3_ff128-ep1000]]),1,0) -> 0 | P49: =IF(I49=MAX(Tabelle4[[#This Row],[d32_el2_dl2_ff128-ep500]:[d64_el3_dl3_ff128-ep1000]]),1,0) -> 0 | Q49: =IF(J49=MAX(Tabelle4[[#This Row],[d32_el2_dl2_ff128-ep500]:[d64_el3_dl3_ff128-ep1000]]),1,0) -> 1 | R49: =IF(K49=MAX(Tabelle4[[#This Row],[d32_el2_dl2_ff128-ep500]:[d64_el3_dl3_ff128-ep1000]]),1,0) -> 1 | S49: =IF(L49=MAX(Tabelle4[[#This Row],[d32_el2_dl2_ff128-ep500]:[d64_el3_dl3_ff128-ep1000]]),1,0) -> 0 | T49: =IF(M49=MAX(Tabelle4[[#This Row],[d32_el2_dl2_ff128-ep500]:[d64_el3_dl3_ff128-ep1000]]),1,0) -> 0 | V49: =IF(H49=MIN(Tabelle4[[#This Row],[d32_el2_dl2_ff128-ep500]:[d64_el3_dl3_ff128-ep1000]]),1,0) -> 0 | W49: =IF(I49=MIN(Tabelle4[[#This Row],[d32_el2_dl2_ff128-ep500]:[d64_el3_dl3_ff128-ep1000]]),1,0) -> 1 | X49: =IF(J49=MIN(Tabelle4[[#This Row],[d32_el2_dl2_ff128-ep500]:[d64_el3_dl3_ff128-ep1000]]),1,0) -> 0 | Y49: =IF(K49=MIN(Tabelle4[[#This Row],[d32_el2_dl2_ff128-ep500]:[d64_el3_dl3_ff128-ep1000]]),1,0) -> 0 | Z49: =IF(L49=MIN(Tabelle4[[#This Row],[d32_el2_dl2_ff128-ep500]:[d64_el3_dl3_ff128-ep1000]]),1,0) -> 0 | AA49: =IF(M49=MIN(Tabelle4[[#This Row],[d32_el2_dl2_ff128-ep500]:[d64_el3_dl3_ff128-ep1000]]),1,0) -> 0
A50: 6 | B50: d64_el3_dl3_ff128-ep1000 | C50: ['spinnen verrückt sein', 'gest', 'wie frage vergleich', 'off', 'geld', 'hineinstecken', 'off'] | D50: 0 | E50: =D50+E43 -> 39 | G50: 49 | H50: {=INDEX($D$2:$D$701, (ROW()-ROW($G$2))*7 + (COLUMN()-COLUMN($G$2)) + 1)} -> 5 | I50: {=INDEX($D$2:$D$701, (ROW()-ROW($G$2))*7 + (COLUMN()-COLUMN($G$2)) + 1)} -> 6 | J50: {=INDEX($D$2:$D$701, (ROW()-ROW($G$2))*7 + (COLUMN()-COLUMN($G$2)) + 1)} -> 5 | K50: {=INDEX($D$2:$D$701, (ROW()-ROW($G$2))*7 + (COLUMN()-COLUMN($G$2)) + 1)} -> 2 | L50: {=INDEX($D$2:$D$701, (ROW()-ROW($G$2))*7 + (COLUMN()-COLUMN($G$2)) + 1)} -> 5 | M50: {=INDEX($D$2:$D$701, (ROW()-ROW($G$2))*7 + (COLUMN()-COLUMN($G$2)) + 1)} -> 10 | O50: =IF(H50=MAX(Tabelle4[[#This Row],[d32_el2_dl2_ff128-ep500]:[d64_el3_dl3_ff128-ep1000]]),1,0) -> 0 | P50: =IF(I50=MAX(Tabelle4[[#This Row],[d32_el2_dl2_ff128-ep500]:[d64_el3_dl3_ff128-ep1000]]),1,0) -> 0 | Q50: =IF(J50=MAX(Tabelle4[[#This Row],[d32_el2_dl2_ff128-ep500]:[d64_el3_dl3_ff128-ep1000]]),1,0) -> 0 | R50: =IF(K50=MAX(Tabelle4[[#This Row],[d32_el2_dl2_ff128-ep500]:[d64_el3_dl3_ff128-ep1000]]),1,0) -> 0 | S50: =IF(L50=MAX(Tabelle4[[#This Row],[d32_el2_dl2_ff128-ep500]:[d64_el3_dl3_ff128-ep1000]]),1,0) -> 0 | T50: =IF(M50=MAX(Tabelle4[[#This Row],[d32_el2_dl2_ff128-ep500]:[d64_el3_dl3_ff128-ep1000]]),1,0) -> 1 | V50: =IF(H50=MIN(Tabelle4[[#This Row],[d32_el2_dl2_ff128-ep500]:[d64_el3_dl3_ff128-ep1000]]),1,0) -> 0 | W50: =IF(I50=MIN(Tabelle4[[#This Row],[d32_el2_dl2_ff128-ep500]:[d64_el3_dl3_ff128-ep1000]]),1,0) -> 0 | X50: =IF(J50=MIN(Tabelle4[[#This Row],[d32_el2_dl2_ff128-ep500]:[d64_el3_dl3_ff128-ep1000]]),1,0) -> 0 | Y50: =IF(K50=MIN(Tabelle4[[#This Row],[d32_el2_dl2_ff128-ep500]:[d64_el3_dl3_ff128-ep1000]]),1,0) -> 1 | Z50: =IF(L50=MIN(Tabelle4[[#This Row],[d32_el2_dl2_ff128-ep500]:[d64_el3_dl3_ff128-ep1000]]),1,0) -> 0 | AA50: =IF(M50=MIN(Tabelle4[[#This Row],[d32_el2_dl2_ff128-ep500]:[d64_el3_dl3_ff128-ep1000]]),1,0) -> 0
A51: 0 | B51: 8 | C51: Hast du die Nachrichten schon gelesen? | E51: =D51+E44 -> 0 | G51: 50 | H51: {=INDEX($D$2:$D$701, (ROW()-ROW($G$2))*7 + (COLUMN()-COLUMN($G$2)) + 1)} -> 9 | I51: {=INDEX($D$2:$D$701, (ROW()-ROW($G$2))*7 + (COLUMN()-COLUMN($G$2)) + 1)} -> 1 | J51: {=INDEX($D$2:$D$701, (ROW()-ROW($G$2))*7 + (COLUMN()-COLUMN($G$2)) + 1)} -> 7 | K51: {=INDEX($D$2:$D$701, (ROW()-ROW($G$2))*7 + (COLUMN()-COLUMN($G$2)) + 1)} -> 7 | L51: {=INDEX($D$2:$D$701, (ROW()-ROW($G$2))*7 + (COLUMN()-COLUMN($G$2)) + 1)} -> 0 | M51: {=INDEX($D$2:$D$701, (ROW()-ROW($G$2))*7 + (COLUMN()-COLUMN($G$2)) + 1)} -> 0 | O51: =IF(H51=MAX(Tabelle4[[#This Row],[d32_el2_dl2_ff128-ep500]:[d64_el3_dl3_ff128-ep1000]]),1,0) -> 1 | P51: =IF(I51=MAX(Tabelle4[[#This Row],[d32_el2_dl2_ff128-ep500]:[d64_el3_dl3_ff128-ep1000]]),1,0) -> 0 | Q51: =IF(J51=MAX(Tabelle4[[#This Row],[d32_el2_dl2_ff128-ep500]:[d64_el3_dl3_ff128-ep1000]]),1,0) -> 0 | R51: =IF(K51=MAX(Tabelle4[[#This Row],[d32_el2_dl2_ff128-ep500]:[d64_el3_dl3_ff128-ep1000]]),1,0) -> 0 | S51: =IF(L51=MAX(Tabelle4[[#This Row],[d32_el2_dl2_ff128-ep500]:[d64_el3_dl3_ff128-ep1000]]),1,0) -> 0 | T51: =IF(M51=MAX(Tabelle4[[#This Row],[d32_el2_dl2_ff128-ep500]:[d64_el3_dl3_ff128-ep1000]]),1,0) -> 0 | V51: =IF(H51=MIN(Tabelle4[[#This Row],[d32_el2_dl2_ff128-ep500]:[d64_el3_dl3_ff128-ep1000]]),1,0) -> 0 | W51: =IF(I51=MIN(Tabelle4[[#This Row],[d32_el2_dl2_ff128-ep500]:[d64_el3_dl3_ff128-ep1000]]),1,0) -> 0 | X51: =IF(J51=MIN(Tabelle4[[#This Row],[d32_el2_dl2_ff128-ep500]:[d64_el3_dl3_ff128-ep1000]]),1,0) -> 0 | Y51: =IF(K51=MIN(Tabelle4[[#This Row],[d32_el2_dl2_ff128-ep500]:[d64_el3_dl3_ff128-ep1000]]),1,0) -> 0 | Z51: =IF(L51=MIN(Tabelle4[[#This Row],[d32_el2_dl2_ff128-ep500]:[d64_el3_dl3_ff128-ep1000]]),1,0) -> 1 | AA51: =IF(M51=MIN(Tabelle4[[#This Row],[d32_el2_dl2_ff128-ep500]:[d64_el3_dl3_ff128-ep1000]]),1,0) -> 1
A52: 1 | B52: d32_el2_dl2_ff128-ep500 | C52: ['du', 'lesen'] | D52: 6 | E52: =D52+E45 -> 44 | G52: 51 | H52: {=INDEX($D$2:$D$701, (ROW()-ROW($G$2))*7 + (COLUMN()-COLUMN($G$2)) + 1)} -> 7 | I52: {=INDEX($D$2:$D$701, (ROW()-ROW($G$2))*7 + (COLUMN()-COLUMN($G$2)) + 1)} -> 6 | J52: {=INDEX($D$2:$D$701, (ROW()-ROW($G$2))*7 + (COLUMN()-COLUMN($G$2)) + 1)} -> 7 | K52: {=INDEX($D$2:$D$701, (ROW()-ROW($G$2))*7 + (COLUMN()-COLUMN($G$2)) + 1)} -> 7 | L52: {=INDEX($D$2:$D$701, (ROW()-ROW($G$2))*7 + (COLUMN()-COLUMN($G$2)) + 1)} -> 5 | M52: {=INDEX($D$2:$D$701, (ROW()-ROW($G$2))*7 + (COLUMN()-COLUMN($G$2)) + 1)} -> 3 | O52: =IF(H52=MAX(Tabelle4[[#This Row],[d32_el2_dl2_ff128-ep500]:[d64_el3_dl3_ff128-ep1000]]),1,0) -> 1 | P52: =IF(I52=MAX(Tabelle4[[#This Row],[d32_el2_dl2_ff128-ep500]:[d64_el3_dl3_ff128-ep1000]]),1,0) -> 0 | Q52: =IF(J52=MAX(Tabelle4[[#This Row],[d32_el2_dl2_ff128-ep500]:[d64_el3_dl3_ff128-ep1000]]),1,0) -> 1 | R52: =IF(K52=MAX(Tabelle4[[#This Row],[d32_el2_dl2_ff128-ep500]:[d64_el3_dl3_ff128-ep1000]]),1,0) -> 1 | S52: =IF(L52=MAX(Tabelle4[[#This Row],[d32_el2_dl2_ff128-ep500]:[d64_el3_dl3_ff128-ep1000]]),1,0) -> 0 | T52: =IF(M52=MAX(Tabelle4[[#This Row],[d32_el2_dl2_ff128-ep500]:[d64_el3_dl3_ff128-ep1000]]),1,0) -> 0 | V52: =IF(H52=MIN(Tabelle4[[#This Row],[d32_el2_dl2_ff128-ep500]:[d64_el3_dl3_ff128-ep1000]]),1,0) -> 0 | W52: =IF(I52=MIN(Tabelle4[[#This Row],[d32_el2_dl2_ff128-ep500]:[d64_el3_dl3_ff128-ep1000]]),1,0) -> 0 | X52: =IF(J52=MIN(Tabelle4[[#This Row],[d32_el2_dl2_ff128-ep500]:[d64_el3_dl3_ff128-ep1000]]),1,0) -> 0 | Y52: =IF(K52=MIN(Tabelle4[[#This Row],[d32_el2_dl2_ff128-ep500]:[d64_el3_dl3_ff128-ep1000]]),1,0) -> 0 | Z52: =IF(L52=MIN(Tabelle4[[#This Row],[d32_el2_dl2_ff128-ep500]:[d64_el3_dl3_ff128-ep1000]]),1,0) -> 0 | AA52: =IF(M52=MIN(Tabelle4[[#This Row],[d32_el2_dl2_ff128-ep500]:[d64_el3_dl3_ff128-ep1000]]),1,0) -> 1
A53: 2 | B53: d64_el1_dl1_ff64-ep1000 | C53: ['ich', 'lesen', 'du'] | D53: 4 | E53: =D53+E46 -> 33 | G53: 52 | H53: {=INDEX($D$2:$D$701, (ROW()-ROW($G$2))*7 + (COLUMN()-COLUMN($G$2)) + 1)} -> 6 | I53: {=INDEX($D$2:$D$701, (ROW()-ROW($G$2))*7 + (COLUMN()-COLUMN($G$2)) + 1)} -> 4 | J53: {=INDEX($D$2:$D$701, (ROW()-ROW($G$2))*7 + (COLUMN()-COLUMN($G$2)) + 1)} -> 8 | K53: {=INDEX($D$2:$D$701, (ROW()-ROW($G$2))*7 + (COLUMN()-COLUMN($G$2)) + 1)} -> 6 | L53: {=INDEX($D$2:$D$701, (ROW()-ROW($G$2))*7 + (COLUMN()-COLUMN($G$2)) + 1)} -> 7 | M53: {=INDEX($D$2:$D$701, (ROW()-ROW($G$2))*7 + (COLUMN()-COLUMN($G$2)) + 1)} -> 4 | O53: =IF(H53=MAX(Tabelle4[[#This Row],[d32_el2_dl2_ff128-ep500]:[d64_el3_dl3_ff128-ep1000]]),1,0) -> 0 | P53: =IF(I53=MAX(Tabelle4[[#This Row],[d32_el2_dl2_ff128-ep500]:[d64_el3_dl3_ff128-ep1000]]),1,0) -> 0 | Q53: =IF(J53=MAX(Tabelle4[[#This Row],[d32_el2_dl2_ff128-ep500]:[d64_el3_dl3_ff128-ep1000]]),1,0) -> 1 | R53: =IF(K53=MAX(Tabelle4[[#This Row],[d32_el2_dl2_ff128-ep500]:[d64_el3_dl3_ff128-ep1000]]),1,0) -> 0 | S53: =IF(L53=MAX(Tabelle4[[#This Row],[d32_el2_dl2_ff128-ep500]:[d64_el3_dl3_ff128-ep1000]]),1,0) -> 0 | T53: =IF(M53=MAX(Tabelle4[[#This Row],[d32_el2_dl2_ff128-ep500]:[d64_el3_dl3_ff128-ep1000]]),1,0) -> 0 | V53: =IF(H53=MIN(Tabelle4[[#This Row],[d32_el2_dl2_ff128-ep500]:[d64_el3_dl3_ff128-ep1000]]),1,0) -> 0 | W53: =IF(I53=MIN(Tabelle4[[#This Row],[d32_el2_dl2_ff128-ep500]:[d64_el3_dl3_ff128-ep1000]]),1,0) -> 1 | X53: =IF(J53=MIN(Tabelle4[[#This Row],[d32_el2_dl2_ff128-ep500]:[d64_el3_dl3_ff128-ep1000]]),1,0) -> 0 | Y53: =IF(K53=MIN(Tabelle4[[#This Row],[d32_el2_dl2_ff128-ep500]:[d64_el3_dl3_ff128-ep1000]]),1,0) -> 0 | Z53: =IF(L53=MIN(Tabelle4[[#This Row],[d32_el2_dl2_ff128-ep500]:[d64_el3_dl3_ff128-ep1000]]),1,0) -> 0 | AA53: =IF(M53=MIN(Tabelle4[[#This Row],[d32_el2_dl2_ff128-ep500]:[d64_el3_dl3_ff128-ep1000]]),1,0) -> 1
A54: 3 | B54: d64_el2_dl2_ff64-ep500 | C54: ['lesen'] | D54: 5 | E54: =D54+E47 -> 40 | G54: 53 | H54: {=INDEX($D$2:$D$701, (ROW()-ROW($G$2))*7 + (COLUMN()-COLUMN($G$2)) + 1)} -> 1 | I54: {=INDEX($D$2:$D$701, (ROW()-ROW($G$2))*7 + (COLUMN()-COLUMN($G$2)) + 1)} -> 10 | J54: {=INDEX($D$2:$D$701, (ROW()-ROW($G$2))*7 + (COLUMN()-COLUMN($G$2)) + 1)} -> 10 | K54: {=INDEX($D$2:$D$701, (ROW()-ROW($G$2))*7 + (COLUMN()-COLUMN($G$2)) + 1)} -> 10 | L54: {=INDEX($D$2:$D$701, (ROW()-ROW($G$2))*7 + (COLUMN()-COLUMN($G$2)) + 1)} -> 0 | M54: {=INDEX($D$2:$D$701, (ROW()-ROW($G$2))*7 + (COLUMN()-COLUMN($G$2)) + 1)} -> 0 | O54: =IF(H54=MAX(Tabelle4[[#This Row],[d32_el2_dl2_ff128-ep500]:[d64_el3_dl3_ff128-ep1000]]),1,0) -> 0 | P54: =IF(I54=MAX(Tabelle4[[#This Row],[d32_el2_dl2_ff128-ep500]:[d64_el3_dl3_ff128-ep1000]]),1,0) -> 1 | Q54: =IF(J54=MAX(Tabelle4[[#This Row],[d32_el2_dl2_ff128-ep500]:[d64_el3_dl3_ff128-ep1000]]),1,0) -> 1 | R54: =IF(K54=MAX(Tabelle4[[#This Row],[d32_el2_dl2_ff128-ep500]:[d64_el3_dl3_ff128-ep1000]]),1,0) -> 1 | S54: =IF(L54=MAX(Tabelle4[[#This Row],[d32_el2_dl2_ff128-ep500]:[d64_el3_dl3_ff128-ep1000]]),1,0) -> 0 | T54: =IF(M54=MAX(Tabelle4[[#This Row],[d32_el2_dl2_ff128-ep500]:[d64_el3_dl3_ff128-ep1000]]),1,0) -> 0 | V54: =IF(H54=MIN(Tabelle4[[#This Row],[d32_el2_dl2_ff128-ep500]:[d64_el3_dl3_ff128-ep1000]]),1,0) -> 0 | W54: =IF(I54=MIN(Tabelle4[[#This Row],[d32_el2_dl2_ff128-ep500]:[d64_el3_dl3_ff128-ep1000]]),1,0) -> 0 | X54: =IF(J54=MIN(Tabelle4[[#This Row],[d32_el2_dl2_ff128-ep500]:[d64_el3_dl3_ff128-ep1000]]),1,0) -> 0 | Y54: =IF(K54=MIN(Tabelle4[[#This Row],[d32_el2_dl2_ff128-ep500]:[d64_el3_dl3_ff128-ep1000]]),1,0) -> 0 | Z54: =IF(L54=MIN(Tabelle4[[#This Row],[d32_el2_dl2_ff128-ep500]:[d64_el3_dl3_ff128-ep1000]]),1,0) -> 1 | AA54: =IF(M54=MIN(Tabelle4[[#This Row],[d32_el2_dl2_ff128-ep500]:[d64_el3_dl3_ff128-ep1000]]),1,0) -> 1
A55: 4 | B55: d64_el2_dl2_ff64-ep1000 | C55: ['lesen', 'täglich', 'lesen'] | D55: 6 | E55: =D55+E48 -> 41 | G55: 54 | H55: {=INDEX($D$2:$D$701, (ROW()-ROW($G$2))*7 + (COLUMN()-COLUMN($G$2)) + 1)} -> 1 | I55: {=INDEX($D$2:$D$701, (ROW()-ROW($G$2))*7 + (COLUMN()-COLUMN($G$2)) + 1)} -> 2 | J55: {=INDEX($D$2:$D$701, (ROW()-ROW($G$2))*7 + (COLUMN()-COLUMN($G$2)) + 1)} -> 1 | K55: {=INDEX($D$2:$D$701, (ROW()-ROW($G$2))*7 + (COLUMN()-COLUMN($G$2)) + 1)} -> 1 | L55: {=INDEX($D$2:$D$701, (ROW()-ROW($G$2))*7 + (COLUMN()-COLUMN($G$2)) + 1)} -> 1 | M55: {=INDEX($D$2:$D$701, (ROW()-ROW($G$2))*7 + (COLUMN()-COLUMN($G$2)) + 1)} -> 1 | O55: =IF(H55=MAX(Tabelle4[[#This Row],[d32_el2_dl2_ff128-ep500]:[d64_el3_dl3_ff128-ep1000]]),1,0) -> 0 | P55: =IF(I55=MAX(Tabelle4[[#This Row],[d32_el2_dl2_ff128-ep500]:[d64_el3_dl3_ff128-ep1000]]),1,0) -> 1 | Q55: =IF(J55=MAX(Tabelle4[[#This Row],[d32_el2_dl2_ff128-ep500]:[d64_el3_dl3_ff128-ep1000]]),1,0) -> 0 | R55: =IF(K55=MAX(Tabelle4[[#This Row],[d32_el2_dl2_ff128-ep500]:[d64_el3_dl3_ff128-ep1000]]),1,0) -> 0 | S55: =IF(L55=MAX(Tabelle4[[#This Row],[d32_el2_dl2_ff128-ep500]:[d64_el3_dl3_ff128-ep1000]]),1,0) -> 0 | T55: =IF(M55=MAX(Tabelle4[[#This Row],[d32_el2_dl2_ff128-ep500]:[d64_el3_dl3_ff128-ep1000]]),1,0) -> 0 | V55: =IF(H55=MIN(Tabelle4[[#This Row],[d32_el2_dl2_ff128-ep500]:[d64_el3_dl3_ff128-ep1000]]),1,0) -> 1 | W55: =IF(I55=MIN(Tabelle4[[#This Row],[d32_el2_dl2_ff128-ep500]:[d64_el3_dl3_ff128-ep1000]]),1,0) -> 0 | X55: =IF(J55=MIN(Tabelle4[[#This Row],[d32_el2_dl2_ff128-ep500]:[d64_el3_dl3_ff128-ep1000]]),1,0) -> 1 | Y55: =IF(K55=MIN(Tabelle4[[#This Row],[d32_el2_dl2_ff128-ep500]:[d64_el3_dl3_ff128-ep1000]]),1,0) -> 1 | Z55: =IF(L55=MIN(Tabelle4[[#This Row],[d32_el2_dl2_ff128-ep500]:[d64_el3_dl3_ff128-ep1000]]),1,0) -> 1 | AA55: =IF(M55=MIN(Tabelle4[[#This Row],[d32_el2_dl2_ff128-ep500]:[d64_el3_dl3_ff128-ep1000]]),1,0) -> 1
A56: 5 | B56: d64_el2_dl2_ff128-ep1000 | C56: ['lesen', 'du'] | D56: 6 | E56: =D56+E49 -> 41 | G56: 55 | H56: {=INDEX($D$2:$D$701, (ROW()-ROW($G$2))*7 + (COLUMN()-COLUMN($G$2)) + 1)} -> 10 | I56: {=INDEX($D$2:$D$701, (ROW()-ROW($G$2))*7 + (COLUMN()-COLUMN($G$2)) + 1)} -> 10 | J56: {=INDEX($D$2:$D$701, (ROW()-ROW($G$2))*7 + (COLUMN()-COLUMN($G$2)) + 1)} -> 7 | K56: {=INDEX($D$2:$D$701, (ROW()-ROW($G$2))*7 + (COLUMN()-COLUMN($G$2)) + 1)} -> 7 | L56: {=INDEX($D$2:$D$701, (ROW()-ROW($G$2))*7 + (COLUMN()-COLUMN($G$2)) + 1)} -> 7 | M56: {=INDEX($D$2:$D$701, (ROW()-ROW($G$2))*7 + (COLUMN()-COLUMN($G$2)) + 1)} -> 8 | O56: =IF(H56=MAX(Tabelle4[[#This Row],[d32_el2_dl2_ff128-ep500]:[d64_el3_dl3_ff128-ep1000]]),1,0) -> 1 | P56: =IF(I56=MAX(Tabelle4[[#This Row],[d32_el2_dl2_ff128-ep500]:[d64_el3_dl3_ff128-ep1000]]),1,0) -> 1 | Q56: =IF(J56=MAX(Tabelle4[[#This Row],[d32_el2_dl2_ff128-ep500]:[d64_el3_dl3_ff128-ep1000]]),1,0) -> 0 | R56: =IF(K56=MAX(Tabelle4[[#This Row],[d32_el2_dl2_ff128-ep500]:[d64_el3_dl3_ff128-ep1000]]),1,0) -> 0 | S56: =IF(L56=MAX(Tabelle4[[#This Row],[d32_el2_dl2_ff128-ep500]:[d64_el3_dl3_ff128-ep1000]]),1,0) -> 0 | T56: =IF(M56=MAX(Tabelle4[[#This Row],[d32_el2_dl2_ff128-ep500]:[d64_el3_dl3_ff128-ep1000]]),1,0) -> 0 | V56: =IF(H56=MIN(Tabelle4[[#This Row],[d32_el2_dl2_ff128-ep500]:[d64_el3_dl3_ff128-ep1000]]),1,0) -> 0 | W56: =IF(I56=MIN(Tabelle4[[#This Row],[d32_el2_dl2_ff128-ep500]:[d64_el3_dl3_ff128-ep1000]]),1,0) -> 0 | X56: =IF(J56=MIN(Tabelle4[[#This Row],[d32_el2_dl2_ff128-ep500]:[d64_el3_dl3_ff128-ep1000]]),1,0) -> 1 | Y56: =IF(K56=MIN(Tabelle4[[#This Row],[d32_el2_dl2_ff128-ep500]:[d64_el3_dl3_ff128-ep1000]]),1,0) -> 1 | Z56: =IF(L56=MIN(Tabelle4[[#This Row],[d32_el2_dl2_ff128-ep500]:[d64_el3_dl3_ff128-ep1000]]),1,0) -> 1 | AA56: =IF(M56=MIN(Tabelle4[[#This Row],[d32_el2_dl2_ff128-ep500]:[d64_el3_dl3_ff128-ep1000]]),1,0) -> 0
A57: 6 | B57: d64_el3_dl3_ff128-ep1000 | C57: ['du', 'lesen', 'du'] | D57: 6 | E57: =D57+E50 -> 45 | G57: 56 | H57: {=INDEX($D$2:$D$701, (ROW()-ROW($G$2))*7 + (COLUMN()-COLUMN($G$2)) + 1)} -> 7 | I57: {=INDEX($D$2:$D$701, (ROW()-ROW($G$2))*7 + (COLUMN()-COLUMN($G$2)) + 1)} -> 10 | J57: {=INDEX($D$2:$D$701, (ROW()-ROW($G$2))*7 + (COLUMN()-COLUMN($G$2)) + 1)} -> 8 | K57: {=INDEX($D$2:$D$701, (ROW()-ROW($G$2))*7 + (COLUMN()-COLUMN($G$2)) + 1)} -> 5 | L57: {=INDEX($D$2:$D$701, (ROW()-ROW($G$2))*7 + (COLUMN()-COLUMN($G$2)) + 1)} -> 10 | M57: {=INDEX($D$2:$D$701, (ROW()-ROW($G$2))*7 + (COLUMN()-COLUMN($G$2)) + 1)} -> 10 | O57: =IF(H57=MAX(Tabelle4[[#This Row],[d32_el2_dl2_ff128-ep500]:[d64_el3_dl3_ff128-ep1000]]),1,0) -> 0 | P57: =IF(I57=MAX(Tabelle4[[#This Row],[d32_el2_dl2_ff128-ep500]:[d64_el3_dl3_ff128-ep1000]]),1,0) -> 1 | Q57: =IF(J57=MAX(Tabelle4[[#This Row],[d32_el2_dl2_ff128-ep500]:[d64_el3_dl3_ff128-ep1000]]),1,0) -> 0 | R57: =IF(K57=MAX(Tabelle4[[#This Row],[d32_el2_dl2_ff128-ep500]:[d64_el3_dl3_ff128-ep1000]]),1,0) -> 0 | S57: =IF(L57=MAX(Tabelle4[[#This Row],[d32_el2_dl2_ff128-ep500]:[d64_el3_dl3_ff128-ep1000]]),1,0) -> 1 | T57: =IF(M57=MAX(Tabelle4[[#This Row],[d32_el2_dl2_ff128-ep500]:[d64_el3_dl3_ff128-ep1000]]),1,0) -> 1 | V57: =IF(H57=MIN(Tabelle4[[#This Row],[d32_el2_dl2_ff128-ep500]:[d64_el3_dl3_ff128-ep1000]]),1,0) -> 0 | W57: =IF(I57=MIN(Tabelle4[[#This Row],[d32_el2_dl2_ff128-ep500]:[d64_el3_dl3_ff128-ep1000]]),1,0) -> 0 | X57: =IF(J57=MIN(Tabelle4[[#This Row],[d32_el2_dl2_ff128-ep500]:[d64_el3_dl3_ff128-ep1000]]),1,0) -> 0 | Y57: =IF(K57=MIN(Tabelle4[[#This Row],[d32_el2_dl2_ff128-ep500]:[d64_el3_dl3_ff128-ep1000]]),1,0) -> 1 | Z57: =IF(L57=MIN(Tabelle4[[#This Row],[d32_el2_dl2_ff128-ep500]:[d64_el3_dl3_ff128-ep1000]]),1,0) -> 0 | AA57: =IF(M57=MIN(Tabelle4[[#This Row],[d32_el2_dl2_ff128-ep500]:[d64_el3_dl3_ff128-ep1000]]),1,0) -> 0
A58: 0 | B58: 9 | C58: KÃ¶nnten Sie das bitte wiederholen? | E58: =D58+E51 -> 0 | G58: 57 | H58: {=INDEX($D$2:$D$701, (ROW()-ROW($G$2))*7 + (COLUMN()-COLUMN($G$2)) + 1)} -> 5 | I58: {=INDEX($D$2:$D$701, (ROW()-ROW($G$2))*7 + (COLUMN()-COLUMN($G$2)) + 1)} -> 3 | J58: {=INDEX($D$2:$D$701, (ROW()-ROW($G$2))*7 + (COLUMN()-COLUMN($G$2)) + 1)} -> 6 | K58: {=INDEX($D$2:$D$701, (ROW()-ROW($G$2))*7 + (COLUMN()-COLUMN($G$2)) + 1)} -> 6 | L58: {=INDEX($D$2:$D$701, (ROW()-ROW($G$2))*7 + (COLUMN()-COLUMN($G$2)) + 1)} -> 8 | M58: {=INDEX($D$2:$D$701, (ROW()-ROW($G$2))*7 + (COLUMN()-COLUMN($G$2)) + 1)} -> 5 | O58: =IF(H58=MAX(Tabelle4[[#This Row],[d32_el2_dl2_ff128-ep500]:[d64_el3_dl3_ff128-ep1000]]),1,0) -> 0 | P58: =IF(I58=MAX(Tabelle4[[#This Row],[d32_el2_dl2_ff128-ep500]:[d64_el3_dl3_ff128-ep1000]]),1,0) -> 0 | Q58: =IF(J58=MAX(Tabelle4[[#This Row],[d32_el2_dl2_ff128-ep500]:[d64_el3_dl3_ff128-ep1000]]),1,0) -> 0 | R58: =IF(K58=MAX(Tabelle4[[#This Row],[d32_el2_dl2_ff128-ep500]:[d64_el3_dl3_ff128-ep1000]]),1,0) -> 0 | S58: =IF(L58=MAX(Tabelle4[[#This Row],[d32_el2_dl2_ff128-ep500]:[d64_el3_dl3_ff128-ep1000]]),1,0) -> 1 | T58: =IF(M58=MAX(Tabelle4[[#This Row],[d32_el2_dl2_ff128-ep500]:[d64_el3_dl3_ff128-ep1000]]),1,0) -> 0 | V58: =IF(H58=MIN(Tabelle4[[#This Row],[d32_el2_dl2_ff128-ep500]:[d64_el3_dl3_ff128-ep1000]]),1,0) -> 0 | W58: =IF(I58=MIN(Tabelle4[[#This Row],[d32_el2_dl2_ff128-ep500]:[d64_el3_dl3_ff128-ep1000]]),1,0) -> 1 | X58: =IF(J58=MIN(Tabelle4[[#This Row],[d32_el2_dl2_ff128-ep500]:[d64_el3_dl3_ff128-ep1000]]),1,0) -> 0 | Y58: =IF(K58=MIN(Tabelle4[[#This Row],[d32_el2_dl2_ff128-ep500]:[d64_el3_dl3_ff128-ep1000]]),1,0) -> 0 | Z58: =IF(L58=MIN(Tabelle4[[#This Row],[d32_el2_dl2_ff128-ep500]:[d64_el3_dl3_ff128-ep1000]]),1,0) -> 0 | AA58: =IF(M58=MIN(Tabelle4[[#This Row],[d32_el2_dl2_ff128-ep500]:[d64_el3_dl3_ff128-ep1000]]),1,0) -> 0
A59: 1 | B59: d32_el2_dl2_ff128-ep500 | C59: ['index', 'frage', 'index', 'index', 'index'] | D59: 4 | E59: =D59+E52 -> 48 | G59: 58 | H59: {=INDEX($D$2:$D$701, (ROW()-ROW($G$2))*7 + (COLUMN()-COLUMN($G$2)) + 1)} -> 7 | I59: {=INDEX($D$2:$D$701, (ROW()-ROW($G$2))*7 + (COLUMN()-COLUMN($G$2)) + 1)} -> 1 | J59: {=INDEX($D$2:$D$701, (ROW()-ROW($G$2))*7 + (COLUMN()-COLUMN($G$2)) + 1)} -> 2 | K59: {=INDEX($D$2:$D$701, (ROW()-ROW($G$2))*7 + (COLUMN()-COLUMN($G$2)) + 1)} -> 0 | L59: {=INDEX($D$2:$D$701, (ROW()-ROW($G$2))*7 + (COLUMN()-COLUMN($G$2)) + 1)} -> 1 | M59: {=INDEX($D$2:$D$701, (ROW()-ROW($G$2))*7 + (COLUMN()-COLUMN($G$2)) + 1)} -> 0 | O59: =IF(H59=MAX(Tabelle4[[#This Row],[d32_el2_dl2_ff128-ep500]:[d64_el3_dl3_ff128-ep1000]]),1,0) -> 1 | P59: =IF(I59=MAX(Tabelle4[[#This Row],[d32_el2_dl2_ff128-ep500]:[d64_el3_dl3_ff128-ep1000]]),1,0) -> 0 | Q59: =IF(J59=MAX(Tabelle4[[#This Row],[d32_el2_dl2_ff128-ep500]:[d64_el3_dl3_ff128-ep1000]]),1,0) -> 0 | R59: =IF(K59=MAX(Tabelle4[[#This Row],[d32_el2_dl2_ff128-ep500]:[d64_el3_dl3_ff128-ep1000]]),1,0) -> 0 | S59: =IF(L59=MAX(Tabelle4[[#This Row],[d32_el2_dl2_ff128-ep500]:[d64_el3_dl3_ff128-ep1000]]),1,0) -> 0 | T59: =IF(M59=MAX(Tabelle4[[#This Row],[d32_el2_dl2_ff128-ep500]:[d64_el3_dl3_ff128-ep1000]]),1,0) -> 0 | V59: =IF(H59=MIN(Tabelle4[[#This Row],[d32_el2_dl2_ff128-ep500]:[d64_el3_dl3_ff128-ep1000]]),1,0) -> 0 | W59: =IF(I59=MIN(Tabelle4[[#This Row],[d32_el2_dl2_ff128-ep500]:[d64_el3_dl3_ff128-ep1000]]),1,0) -> 0 | X59: =IF(J59=MIN(Tabelle4[[#This Row],[d32_el2_dl2_ff128-ep500]:[d64_el3_dl3_ff128-ep1000]]),1,0) -> 0 | Y59: =IF(K59=MIN(Tabelle4[[#This Row],[d32_el2_dl2_ff128-ep500]:[d64_el3_dl3_ff128-ep1000]]),1,0) -> 1 | Z59: =IF(L59=MIN(Tabelle4[[#This Row],[d32_el2_dl2_ff128-ep500]:[d64_el3_dl3_ff128-ep1000]]),1,0) -> 0 | AA59: =IF(M59=MIN(Tabelle4[[#This Row],[d32_el2_dl2_ff128-ep500]:[d64_el3_dl3_ff128-ep1000]]),1,0) -> 1
A60: 2 | B60: d64_el1_dl1_ff64-ep1000 | C60: ['aber', 'nur', 'index', 'alpha', 'wiederholung', 'off'] | D60: 6 | E60: =D60+E53 -> 39 | G60: 59 | H60: {=INDEX($D$2:$D$701, (ROW()-ROW($G$2))*7 + (COLUMN()-COLUMN($G$2)) + 1)} -> 8 | I60: {=INDEX($D$2:$D$701, (ROW()-ROW($G$2))*7 + (COLUMN()-COLUMN($G$2)) + 1)} -> 9 | J60: {=INDEX($D$2:$D$701, (ROW()-ROW($G$2))*7 + (COLUMN()-COLUMN($G$2)) + 1)} -> 9 | K60: {=INDEX($D$2:$D$701, (ROW()-ROW($G$2))*7 + (COLUMN()-COLUMN($G$2)) + 1)} -> 9 | L60: {=INDEX($D$2:$D$701, (ROW()-ROW($G$2))*7 + (COLUMN()-COLUMN($G$2)) + 1)} -> 8 | M60: {=INDEX($D$2:$D$701, (ROW()-ROW($G$2))*7 + (COLUMN()-COLUMN($G$2)) + 1)} -> 3 | O60: =IF(H60=MAX(Tabelle4[[#This Row],[d32_el2_dl2_ff128-ep500]:[d64_el3_dl3_ff128-ep1000]]),1,0) -> 0 | P60: =IF(I60=MAX(Tabelle4[[#This Row],[d32_el2_dl2_ff128-ep500]:[d64_el3_dl3_ff128-ep1000]]),1,0) -> 1 | Q60: =IF(J60=MAX(Tabelle4[[#This Row],[d32_el2_dl2_ff128-ep500]:[d64_el3_dl3_ff128-ep1000]]),1,0) -> 1 | R60: =IF(K60=MAX(Tabelle4[[#This Row],[d32_el2_dl2_ff128-ep500]:[d64_el3_dl3_ff128-ep1000]]),1,0) -> 1 | S60: =IF(L60=MAX(Tabelle4[[#This Row],[d32_el2_dl2_ff128-ep500]:[d64_el3_dl3_ff128-ep1000]]),1,0) -> 0 | T60: =IF(M60=MAX(Tabelle4[[#This Row],[d32_el2_dl2_ff128-ep500]:[d64_el3_dl3_ff128-ep1000]]),1,0) -> 0 | V60: =IF(H60=MIN(Tabelle4[[#This Row],[d32_el2_dl2_ff128-ep500]:[d64_el3_dl3_ff128-ep1000]]),1,0) -> 0 | W60: =IF(I60=MIN(Tabelle4[[#This Row],[d32_el2_dl2_ff128-ep500]:[d64_el3_dl3_ff128-ep1000]]),1,0) -> 0 | X60: =IF(J60=MIN(Tabelle4[[#This Row],[d32_el2_dl2_ff128-ep500]:[d64_el3_dl3_ff128-ep1000]]),1,0) -> 0 | Y60: =IF(K60=MIN(Tabelle4[[#This Row],[d32_el2_dl2_ff128-ep500]:[d64_el3_dl3_ff128-ep1000]]),1,0) -> 0 | Z60: =IF(L60=MIN(Tabelle4[[#This Row],[d32_el2_dl2_ff128-ep500]:[d64_el3_dl3_ff128-ep1000]]),1,0) -> 0 | AA60: =IF(M60=MIN(Tabelle4[[#This Row],[d32_el2_dl2_ff128-ep500]:[d64_el3_dl3_ff128-ep1000]]),1,0) -> 1
A61: 3 | B61: d64_el2_dl2_ff64-ep500 | C61: ['index', 'neu', 'maschine'] | D61: 0 | E61: =D61+E54 -> 40 | G61: 60 | H61: {=INDEX($D$2:$D$701, (ROW()-ROW($G$2))*7 + (COLUMN()-COLUMN($G$2)) + 1)} -> 6 | I61: {=INDEX($D$2:$D$701, (ROW()-ROW($G$2))*7 + (COLUMN()-COLUMN($G$2)) + 1)} -> 6 | J61: {=INDEX($D$2:$D$701, (ROW()-ROW($G$2))*7 + (COLUMN()-COLUMN($G$2)) + 1)} -> 8 | K61: {=INDEX($D$2:$D$701, (ROW()-ROW($G$2))*7 + (COLUMN()-COLUMN($G$2)) + 1)} -> 8 | L61: {=INDEX($D$2:$D$701, (ROW()-ROW($G$2))*7 + (COLUMN()-COLUMN($G$2)) + 1)} -> 10 | M61: {=INDEX($D$2:$D$701, (ROW()-ROW($G$2))*7 + (COLUMN()-COLUMN($G$2)) + 1)} -> 10 | O61: =IF(H61=MAX(Tabelle4[[#This Row],[d32_el2_dl2_ff128-ep500]:[d64_el3_dl3_ff128-ep1000]]),1,0) -> 0 | P61: =IF(I61=MAX(Tabelle4[[#This Row],[d32_el2_dl2_ff128-ep500]:[d64_el3_dl3_ff128-ep1000]]),1,0) -> 0 | Q61: =IF(J61=MAX(Tabelle4[[#This Row],[d32_el2_dl2_ff128-ep500]:[d64_el3_dl3_ff128-ep1000]]),1,0) -> 0 | R61: =IF(K61=MAX(Tabelle4[[#This Row],[d32_el2_dl2_ff128-ep500]:[d64_el3_dl3_ff128-ep1000]]),1,0) -> 0 | S61: =IF(L61=MAX(Tabelle4[[#This Row],[d32_el2_dl2_ff128-ep500]:[d64_el3_dl3_ff128-ep1000]]),1,0) -> 1 | T61: =IF(M61=MAX(Tabelle4[[#This Row],[d32_el2_dl2_ff128-ep500]:[d64_el3_dl3_ff128-ep1000]]),1,0) -> 1 | V61: =IF(H61=MIN(Tabelle4[[#This Row],[d32_el2_dl2_ff128-ep500]:[d64_el3_dl3_ff128-ep1000]]),1,0) -> 1 | W61: =IF(I61=MIN(Tabelle4[[#This Row],[d32_el2_dl2_ff128-ep500]:[d64_el3_dl3_ff128-ep1000]]),1,0) -> 1 | X61: =IF(J61=MIN(Tabelle4[[#This Row],[d32_el2_dl2_ff128-ep500]:[d64_el3_dl3_ff128-ep1000]]),1,0) -> 0 | Y61: =IF(K61=MIN(Tabelle4[[#This Row],[d32_el2_dl2_ff128-ep500]:[d64_el3_dl3_ff128-ep1000]]),1,0) -> 0 | Z61: =IF(L61=MIN(Tabelle4[[#This Row],[d32_el2_dl2_ff128-ep500]:[d64_el3_dl3_ff128-ep1000]]),1,0) -> 0 | AA61: =IF(M61=MIN(Tabelle4[[#This Row],[d32_el2_dl2_ff128-ep500]:[d64_el3_dl3_ff128-ep1000]]),1,0) -> 0
A62: 4 | B62: d64_el2_dl2_ff64-ep1000 | C62: ['index', 'arbeiten', 'wo', 'bleiben'] | D62: 0 | E62: =D62+E55 -> 41 | G62: 61 | H62: {=INDEX($D$2:$D$701, (ROW()-ROW($G$2))*7 + (COLUMN()-COLUMN($G$2)) + 1)} -> 8 | I62: {=INDEX($D$2:$D$701, (ROW()-ROW($G$2))*7 + (COLUMN()-COLUMN($G$2)) + 1)} -> 10 | J62: {=INDEX($D$2:$D$701, (ROW()-ROW($G$2))*7 + (COLUMN()-COLUMN($G$2)) + 1)} -> 10 | K62: {=INDEX($D$2:$D$701, (ROW()-ROW($G$2))*7 + (COLUMN()-COLUMN($G$2)) + 1)} -> 10 | L62: {=INDEX($D$2:$D$701, (ROW()-ROW($G$2))*7 + (COLUMN()-COLUMN($G$2)) + 1)} -> 10 | M62: {=INDEX($D$2:$D$701, (ROW()-ROW($G$2))*7 + (COLUMN()-COLUMN($G$2)) + 1)} -> 10 | O62: =IF(H62=MAX(Tabelle4[[#This Row],[d32_el2_dl2_ff128-ep500]:[d64_el3_dl3_ff128-ep1000]]),1,0) -> 0 | P62: =IF(I62=MAX(Tabelle4[[#This Row],[d32_el2_dl2_ff128-ep500]:[d64_el3_dl3_ff128-ep1000]]),1,0) -> 1 | Q62: =IF(J62=MAX(Tabelle4[[#This Row],[d32_el2_dl2_ff128-ep500]:[d64_el3_dl3_ff128-ep1000]]),1,0) -> 1 | R62: =IF(K62=MAX(Tabelle4[[#This Row],[d32_el2_dl2_ff128-ep500]:[d64_el3_dl3_ff128-ep1000]]),1,0) -> 1 | S62: =IF(L62=MAX(Tabelle4[[#This Row],[d32_el2_dl2_ff128-ep500]:[d64_el3_dl3_ff128-ep1000]]),1,0) -> 1 | T62: =IF(M62=MAX(Tabelle4[[#This Row],[d32_el2_dl2_ff128-ep500]:[d64_el3_dl3_ff128-ep1000]]),1,0) -> 1 | V62: =IF(H62=MIN(Tabelle4[[#This Row],[d32_el2_dl2_ff128-ep500]:[d64_el3_dl3_ff128-ep1000]]),1,0) -> 1 | W62: =IF(I62=MIN(Tabelle4[[#This Row],[d32_el2_dl2_ff128-ep500]:[d64_el3_dl3_ff128-ep1000]]),1,0) -> 0 | X62: =IF(J62=MIN(Tabelle4[[#This Row],[d32_el2_dl2_ff128-ep500]:[d64_el3_dl3_ff128-ep1000]]),1,0) -> 0 | Y62: =IF(K62=MIN(Tabelle4[[#This Row],[d32_el2_dl2_ff128-ep500]:[d64_el3_dl3_ff128-ep1000]]),1,0) -> 0 | Z62: =IF(L62=MIN(Tabelle4[[#This Row],[d32_el2_dl2_ff128-ep500]:[d64_el3_dl3_ff128-ep1000]]),1,0) -> 0 | AA62: =IF(M62=MIN(Tabelle4[[#This Row],[d32_el2_dl2_ff128-ep500]:[d64_el3_dl3_ff128-ep1000]]),1,0) -> 0
A63: 5 | B63: d64_el2_dl2_ff128-ep1000 | C63: ['bild', 'wiederholung', 'zeigen'] | D63: 6 | E63: =D63+E56 -> 47 | G63: 62 | H63: {=INDEX($D$2:$D$701, (ROW()-ROW($G$2))*7 + (COLUMN()-COLUMN($G$2)) + 1)} -> 3 | I63: {=INDEX($D$2:$D$701, (ROW()-ROW($G$2))*7 + (COLUMN()-COLUMN($G$2)) + 1)} -> 8 | J63: {=INDEX($D$2:$D$701, (ROW()-ROW($G$2))*7 + (COLUMN()-COLUMN($G$2)) + 1)} -> 1 | K63: {=INDEX($D$2:$D$701, (ROW()-ROW($G$2))*7 + (COLUMN()-COLUMN($G$2)) + 1)} -> 8 | L63: {=INDEX($D$2:$D$701, (ROW()-ROW($G$2))*7 + (COLUMN()-COLUMN($G$2)) + 1)} -> 1 | M63: {=INDEX($D$2:$D$701, (ROW()-ROW($G$2))*7 + (COLUMN()-COLUMN($G$2)) + 1)} -> 3 | O63: =IF(H63=MAX(Tabelle4[[#This Row],[d32_el2_dl2_ff128-ep500]:[d64_el3_dl3_ff128-ep1000]]),1,0) -> 0 | P63: =IF(I63=MAX(Tabelle4[[#This Row],[d32_el2_dl2_ff128-ep500]:[d64_el3_dl3_ff128-ep1000]]),1,0) -> 1 | Q63: =IF(J63=MAX(Tabelle4[[#This Row],[d32_el2_dl2_ff128-ep500]:[d64_el3_dl3_ff128-ep1000]]),1,0) -> 0 | R63: =IF(K63=MAX(Tabelle4[[#This Row],[d32_el2_dl2_ff128-ep500]:[d64_el3_dl3_ff128-ep1000]]),1,0) -> 1 | S63: =IF(L63=MAX(Tabelle4[[#This Row],[d32_el2_dl2_ff128-ep500]:[d64_el3_dl3_ff128-ep1000]]),1,0) -> 0 | T63: =IF(M63=MAX(Tabelle4[[#This Row],[d32_el2_dl2_ff128-ep500]:[d64_el3_dl3_ff128-ep1000]]),1,0) -> 0 | V63: =IF(H63=MIN(Tabelle4[[#This Row],[d32_el2_dl2_ff128-ep500]:[d64_el3_dl3_ff128-ep1000]]),1,0) -> 0 | W63: =IF(I63=MIN(Tabelle4[[#This Row],[d32_el2_dl2_ff128-ep500]:[d64_el3_dl3_ff128-ep1000]]),1,0) -> 0 | X63: =IF(J63=MIN(Tabelle4[[#This Row],[d32_el2_dl2_ff128-ep500]:[d64_el3_dl3_ff128-ep1000]]),1,0) -> 1 | Y63: =IF(K63=MIN(Tabelle4[[#This Row],[d32_el2_dl2_ff128-ep500]:[d64_el3_dl3_ff128-ep1000]]),1,0) -> 0 | Z63: =IF(L63=MIN(Tabelle4[[#This Row],[d32_el2_dl2_ff128-ep500]:[d64_el3_dl3_ff128-ep1000]]),1,0) -> 1 | AA63: =IF(M63=MIN(Tabelle4[[#This Row],[d32_el2_dl2_ff128-ep500]:[d64_el3_dl3_ff128-ep1000]]),1,0) -> 0
A64: 6 | B64: d64_el3_dl3_ff128-ep1000 | C64: ['index', 'wollen', 'hören', 'handlung', 'vorbei', 'wiederholung', 'index'] | D64: 6 | E64: =D64+E57 -> 51 | G64: 63 | H64: {=INDEX($D$2:$D$701, (ROW()-ROW($G$2))*7 + (COLUMN()-COLUMN($G$2)) + 1)} -> 8 | I64: {=INDEX($D$2:$D$701, (ROW()-ROW($G$2))*7 + (COLUMN()-COLUMN($G$2)) + 1)} -> 8 | J64: {=INDEX($D$2:$D$701, (ROW()-ROW($G$2))*7 + (COLUMN()-COLUMN($G$2)) + 1)} -> 9 | K64: {=INDEX($D$2:$D$701, (ROW()-ROW($G$2))*7 + (COLUMN()-COLUMN($G$2)) + 1)} -> 8 | L64: {=INDEX($D$2:$D$701, (ROW()-ROW($G$2))*7 + (COLUMN()-COLUMN($G$2)) + 1)} -> 6 | M64: {=INDEX($D$2:$D$701, (ROW()-ROW($G$2))*7 + (COLUMN()-COLUMN($G$2)) + 1)} -> 9 | O64: =IF(H64=MAX(Tabelle4[[#This Row],[d32_el2_dl2_ff128-ep500]:[d64_el3_dl3_ff128-ep1000]]),1,0) -> 0 | P64: =IF(I64=MAX(Tabelle4[[#This Row],[d32_el2_dl2_ff128-ep500]:[d64_el3_dl3_ff128-ep1000]]),1,0) -> 0 | Q64: =IF(J64=MAX(Tabelle4[[#This Row],[d32_el2_dl2_ff128-ep500]:[d64_el3_dl3_ff128-ep1000]]),1,0) -> 1 | R64: =IF(K64=MAX(Tabelle4[[#This Row],[d32_el2_dl2_ff128-ep500]:[d64_el3_dl3_ff128-ep1000]]),1,0) -> 0 | S64: =IF(L64=MAX(Tabelle4[[#This Row],[d32_el2_dl2_ff128-ep500]:[d64_el3_dl3_ff128-ep1000]]),1,0) -> 0 | T64: =IF(M64=MAX(Tabelle4[[#This Row],[d32_el2_dl2_ff128-ep500]:[d64_el3_dl3_ff128-ep1000]]),1,0) -> 1 | V64: =IF(H64=MIN(Tabelle4[[#This Row],[d32_el2_dl2_ff128-ep500]:[d64_el3_dl3_ff128-ep1000]]),1,0) -> 0 | W64: =IF(I64=MIN(Tabelle4[[#This Row],[d32_el2_dl2_ff128-ep500]:[d64_el3_dl3_ff128-ep1000]]),1,0) -> 0 | X64: =IF(J64=MIN(Tabelle4[[#This Row],[d32_el2_dl2_ff128-ep500]:[d64_el3_dl3_ff128-ep1000]]),1,0) -> 0 | Y64: =IF(K64=MIN(Tabelle4[[#This Row],[d32_el2_dl2_ff128-ep500]:[d64_el3_dl3_ff128-ep1000]]),1,0) -> 0 | Z64: =IF(L64=MIN(Tabelle4[[#This Row],[d32_el2_dl2_ff128-ep500]:[d64_el3_dl3_ff128-ep1000]]),1,0) -> 1 | AA64: =IF(M64=MIN(Tabelle4[[#This Row],[d32_el2_dl2_ff128-ep500]:[d64_el3_dl3_ff128-ep1000]]),1,0) -> 0
A65: 0 | B65: 10 | C65: Ich verstehe das nicht ganz. | E65: =D65+E58 -> 0 | G65: 64 | H65: {=INDEX($D$2:$D$701, (ROW()-ROW($G$2))*7 + (COLUMN()-COLUMN($G$2)) + 1)} -> 6 | I65: {=INDEX($D$2:$D$701, (ROW()-ROW($G$2))*7 + (COLUMN()-COLUMN($G$2)) + 1)} -> 3 | J65: {=INDEX($D$2:$D$701, (ROW()-ROW($G$2))*7 + (COLUMN()-COLUMN($G$2)) + 1)} -> 5 | K65: {=INDEX($D$2:$D$701, (ROW()-ROW($G$2))*7 + (COLUMN()-COLUMN($G$2)) + 1)} -> 5 | L65: {=INDEX($D$2:$D$701, (ROW()-ROW($G$2))*7 + (COLUMN()-COLUMN($G$2)) + 1)} -> 5 | M65: {=INDEX($D$2:$D$701, (ROW()-ROW($G$2))*7 + (COLUMN()-COLUMN($G$2)) + 1)} -> 3 | O65: =IF(H65=MAX(Tabelle4[[#This Row],[d32_el2_dl2_ff128-ep500]:[d64_el3_dl3_ff128-ep1000]]),1,0) -> 1 | P65: =IF(I65=MAX(Tabelle4[[#This Row],[d32_el2_dl2_ff128-ep500]:[d64_el3_dl3_ff128-ep1000]]),1,0) -> 0 | Q65: =IF(J65=MAX(Tabelle4[[#This Row],[d32_el2_dl2_ff128-ep500]:[d64_el3_dl3_ff128-ep1000]]),1,0) -> 0 | R65: =IF(K65=MAX(Tabelle4[[#This Row],[d32_el2_dl2_ff128-ep500]:[d64_el3_dl3_ff128-ep1000]]),1,0) -> 0 | S65: =IF(L65=MAX(Tabelle4[[#This Row],[d32_el2_dl2_ff128-ep500]:[d64_el3_dl3_ff128-ep1000]]),1,0) -> 0 | T65: =IF(M65=MAX(Tabelle4[[#This Row],[d32_el2_dl2_ff128-ep500]:[d64_el3_dl3_ff128-ep1000]]),1,0) -> 0 | V65: =IF(H65=MIN(Tabelle4[[#This Row],[d32_el2_dl2_ff128-ep500]:[d64_el3_dl3_ff128-ep1000]]),1,0) -> 0 | W65: =IF(I65=MIN(Tabelle4[[#This Row],[d32_el2_dl2_ff128-ep500]:[d64_el3_dl3_ff128-ep1000]]),1,0) -> 1 | X65: =IF(J65=MIN(Tabelle4[[#This Row],[d32_el2_dl2_ff128-ep500]:[d64_el3_dl3_ff128-ep1000]]),1,0) -> 0 | Y65: =IF(K65=MIN(Tabelle4[[#This Row],[d32_el2_dl2_ff128-ep500]:[d64_el3_dl3_ff128-ep1000]]),1,0) -> 0 | Z65: =IF(L65=MIN(Tabelle4[[#This Row],[d32_el2_dl2_ff128-ep500]:[d64_el3_dl3_ff128-ep1000]]),1,0) -> 0 | AA65: =IF(M65=MIN(Tabelle4[[#This Row],[d32_el2_dl2_ff128-ep500]:[d64_el3_dl3_ff128-ep1000]]),1,0) -> 1
A66: 1 | B66: d32_el2_dl2_ff128-ep500 | C66: ['verstehen', 'nicht'] | D66: 10 | E66: =D66+E59 -> 58 | G66: 65 | H66: {=INDEX($D$2:$D$701, (ROW()-ROW($G$2))*7 + (COLUMN()-COLUMN($G$2)) + 1)} -> 9 | I66: {=INDEX($D$2:$D$701, (ROW()-ROW($G$2))*7 + (COLUMN()-COLUMN($G$2)) + 1)} -> 6 | J66: {=INDEX($D$2:$D$701, (ROW()-ROW($G$2))*7 + (COLUMN()-COLUMN($G$2)) + 1)} -> 9 | K66: {=INDEX($D$2:$D$701, (ROW()-ROW($G$2))*7 + (COLUMN()-COLUMN($G$2)) + 1)} -> 6 | L66: {=INDEX($D$2:$D$701, (ROW()-ROW($G$2))*7 + (COLUMN()-COLUMN($G$2)) + 1)} -> 9 | M66: {=INDEX($D$2:$D$701, (ROW()-ROW($G$2))*7 + (COLUMN()-COLUMN($G$2)) + 1)} -> 9 | O66: =IF(H66=MAX(Tabelle4[[#This Row],[d32_el2_dl2_ff128-ep500]:[d64_el3_dl3_ff128-ep1000]]),1,0) -> 1 | P66: =IF(I66=MAX(Tabelle4[[#This Row],[d32_el2_dl2_ff128-ep500]:[d64_el3_dl3_ff128-ep1000]]),1,0) -> 0 | Q66: =IF(J66=MAX(Tabelle4[[#This Row],[d32_el2_dl2_ff128-ep500]:[d64_el3_dl3_ff128-ep1000]]),1,0) -> 1 | R66: =IF(K66=MAX(Tabelle4[[#This Row],[d32_el2_dl2_ff128-ep500]:[d64_el3_dl3_ff128-ep1000]]),1,0) -> 0 | S66: =IF(L66=MAX(Tabelle4[[#This Row],[d32_el2_dl2_ff128-ep500]:[d64_el3_dl3_ff128-ep1000]]),1,0) -> 1 | T66: =IF(M66=MAX(Tabelle4[[#This Row],[d32_el2_dl2_ff128-ep500]:[d64_el3_dl3_ff128-ep1000]]),1,0) -> 1 | V66: =IF(H66=MIN(Tabelle4[[#This Row],[d32_el2_dl2_ff128-ep500]:[d64_el3_dl3_ff128-ep1000]]),1,0) -> 0 | W66: =IF(I66=MIN(Tabelle4[[#This Row],[d32_el2_dl2_ff128-ep500]:[d64_el3_dl3_ff128-ep1000]]),1,0) -> 1 | X66: =IF(J66=MIN(Tabelle4[[#This Row],[d32_el2_dl2_ff128-ep500]:[d64_el3_dl3_ff128-ep1000]]),1,0) -> 0 | Y66: =IF(K66=MIN(Tabelle4[[#This Row],[d32_el2_dl2_ff128-ep500]:[d64_el3_dl3_ff128-ep1000]]),1,0) -> 1 | Z66: =IF(L66=MIN(Tabelle4[[#This Row],[d32_el2_dl2_ff128-ep500]:[d64_el3_dl3_ff128-ep1000]]),1,0) -> 0 | AA66: =IF(M66=MIN(Tabelle4[[#This Row],[d32_el2_dl2_ff128-ep500]:[d64_el3_dl3_ff128-ep1000]]),1,0) -> 0
A67: 2 | B67: d64_el1_dl1_ff64-ep1000 | C67: ['verstehen', 'nicht'] | D67: 10 | E67: =D67+E60 -> 49 | G67: 66 | H67: {=INDEX($D$2:$D$701, (ROW()-ROW($G$2))*7 + (COLUMN()-COLUMN($G$2)) + 1)} -> 10 | I67: {=INDEX($D$2:$D$701, (ROW()-ROW($G$2))*7 + (COLUMN()-COLUMN($G$2)) + 1)} -> 10 | J67: {=INDEX($D$2:$D$701, (ROW()-ROW($G$2))*7 + (COLUMN()-COLUMN($G$2)) + 1)} -> 9 | K67: {=INDEX($D$2:$D$701, (ROW()-ROW($G$2))*7 + (COLUMN()-COLUMN($G$2)) + 1)} -> 9 | L67: {=INDEX($D$2:$D$701, (ROW()-ROW($G$2))*7 + (COLUMN()-COLUMN($G$2)) + 1)} -> 10 | M67: {=INDEX($D$2:$D$701, (ROW()-ROW($G$2))*7 + (COLUMN()-COLUMN($G$2)) + 1)} -> 9 | O67: =IF(H67=MAX(Tabelle4[[#This Row],[d32_el2_dl2_ff128-ep500]:[d64_el3_dl3_ff128-ep1000]]),1,0) -> 1 | P67: =IF(I67=MAX(Tabelle4[[#This Row],[d32_el2_dl2_ff128-ep500]:[d64_el3_dl3_ff128-ep1000]]),1,0) -> 1 | Q67: =IF(J67=MAX(Tabelle4[[#This Row],[d32_el2_dl2_ff128-ep500]:[d64_el3_dl3_ff128-ep1000]]),1,0) -> 0 | R67: =IF(K67=MAX(Tabelle4[[#This Row],[d32_el2_dl2_ff128-ep500]:[d64_el3_dl3_ff128-ep1000]]),1,0) -> 0 | S67: =IF(L67=MAX(Tabelle4[[#This Row],[d32_el2_dl2_ff128-ep500]:[d64_el3_dl3_ff128-ep1000]]),1,0) -> 1 | T67: =IF(M67=MAX(Tabelle4[[#This Row],[d32_el2_dl2_ff128-ep500]:[d64_el3_dl3_ff128-ep1000]]),1,0) -> 0 | V67: =IF(H67=MIN(Tabelle4[[#This Row],[d32_el2_dl2_ff128-ep500]:[d64_el3_dl3_ff128-ep1000]]),1,0) -> 0 | W67: =IF(I67=MIN(Tabelle4[[#This Row],[d32_el2_dl2_ff128-ep500]:[d64_el3_dl3_ff128-ep1000]]),1,0) -> 0 | X67: =IF(J67=MIN(Tabelle4[[#This Row],[d32_el2_dl2_ff128-ep500]:[d64_el3_dl3_ff128-ep1000]]),1,0) -> 1 | Y67: =IF(K67=MIN(Tabelle4[[#This Row],[d32_el2_dl2_ff128-ep500]:[d64_el3_dl3_ff128-ep1000]]),1,0) -> 1 | Z67: =IF(L67=MIN(Tabelle4[[#This Row],[d32_el2_dl2_ff128-ep500]:[d64_el3_dl3_ff128-ep1000]]),1,0) -> 0 | AA67: =IF(M67=MIN(Tabelle4[[#This Row],[d32_el2_dl2_ff128-ep500]:[d64_el3_dl3_ff128-ep1000]]),1,0) -> 1
A68: 3 | B68: d64_el2_dl2_ff64-ep500 | C68: ['ich', 'verstehen', 'nicht'] | D68: 10 | E68: =D68+E61 -> 50 | G68: 67 | H68: {=INDEX($D$2:$D$701, (ROW()-ROW($G$2))*7 + (COLUMN()-COLUMN($G$2)) + 1)} -> 2 | I68: {=INDEX($D$2:$D$701, (ROW()-ROW($G$2))*7 + (COLUMN()-COLUMN($G$2)) + 1)} -> 3 | J68: {=INDEX($D$2:$D$701, (ROW()-ROW($G$2))*7 + (COLUMN()-COLUMN($G$2)) + 1)} -> 0 | K68: {=INDEX($D$2:$D$701, (ROW()-ROW($G$2))*7 + (COLUMN()-COLUMN($G$2)) + 1)} -> 0 | L68: {=INDEX($D$2:$D$701, (ROW()-ROW($G$2))*7 + (COLUMN()-COLUMN($G$2)) + 1)} -> 0 | M68: {=INDEX($D$2:$D$701, (ROW()-ROW($G$2))*7 + (COLUMN()-COLUMN($G$2)) + 1)} -> 0 | O68: =IF(H68=MAX(Tabelle4[[#This Row],[d32_el2_dl2_ff128-ep500]:[d64_el3_dl3_ff128-ep1000]]),1,0) -> 0 | P68: =IF(I68=MAX(Tabelle4[[#This Row],[d32_el2_dl2_ff128-ep500]:[d64_el3_dl3_ff128-ep1000]]),1,0) -> 1 | Q68: =IF(J68=MAX(Tabelle4[[#This Row],[d32_el2_dl2_ff128-ep500]:[d64_el3_dl3_ff128-ep1000]]),1,0) -> 0 | R68: =IF(K68=MAX(Tabelle4[[#This Row],[d32_el2_dl2_ff128-ep500]:[d64_el3_dl3_ff128-ep1000]]),1,0) -> 0 | S68: =IF(L68=MAX(Tabelle4[[#This Row],[d32_el2_dl2_ff128-ep500]:[d64_el3_dl3_ff128-ep1000]]),1,0) -> 0 | T68: =IF(M68=MAX(Tabelle4[[#This Row],[d32_el2_dl2_ff128-ep500]:[d64_el3_dl3_ff128-ep1000]]),1,0) -> 0 | V68: =IF(H68=MIN(Tabelle4[[#This Row],[d32_el2_dl2_ff128-ep500]:[d64_el3_dl3_ff128-ep1000]]),1,0) -> 0 | W68: =IF(I68=MIN(Tabelle4[[#This Row],[d32_el2_dl2_ff128-ep500]:[d64_el3_dl3_ff128-ep1000]]),1,0) -> 0 | X68: =IF(J68=MIN(Tabelle4[[#This Row],[d32_el2_dl2_ff128-ep500]:[d64_el3_dl3_ff128-ep1000]]),1,0) -> 1 | Y68: =IF(K68=MIN(Tabelle4[[#This Row],[d32_el2_dl2_ff128-ep500]:[d64_el3_dl3_ff128-ep1000]]),1,0) -> 1 | Z68: =IF(L68=MIN(Tabelle4[[#This Row],[d32_el2_dl2_ff128-ep500]:[d64_el3_dl3_ff128-ep1000]]),1,0) -> 1 | AA68: =IF(M68=MIN(Tabelle4[[#This Row],[d32_el2_dl2_ff128-ep500]:[d64_el3_dl3_ff128-ep1000]]),1,0) -> 1
A69: 4 | B69: d64_el2_dl2_ff64-ep1000 | C69: ['ich', 'verstehen', 'nicht'] | D69: 10 | E69: =D69+E62 -> 51 | G69: 68 | H69: {=INDEX($D$2:$D$701, (ROW()-ROW($G$2))*7 + (COLUMN()-COLUMN($G$2)) + 1)} -> 9 | I69: {=INDEX($D$2:$D$701, (ROW()-ROW($G$2))*7 + (COLUMN()-COLUMN($G$2)) + 1)} -> 10 | J69: {=INDEX($D$2:$D$701, (ROW()-ROW($G$2))*7 + (COLUMN()-COLUMN($G$2)) + 1)} -> 10 | K69: {=INDEX($D$2:$D$701, (ROW()-ROW($G$2))*7 + (COLUMN()-COLUMN($G$2)) + 1)} -> 10 | L69: {=INDEX($D$2:$D$701, (ROW()-ROW($G$2))*7 + (COLUMN()-COLUMN($G$2)) + 1)} -> 10 | M69: {=INDEX($D$2:$D$701, (ROW()-ROW($G$2))*7 + (COLUMN()-COLUMN($G$2)) + 1)} -> 10 | O69: =IF(H69=MAX(Tabelle4[[#This Row],[d32_el2_dl2_ff128-ep500]:[d64_el3_dl3_ff128-ep1000]]),1,0) -> 0 | P69: =IF(I69=MAX(Tabelle4[[#This Row],[d32_el2_dl2_ff128-ep500]:[d64_el3_dl3_ff128-ep1000]]),1,0) -> 1 | Q69: =IF(J69=MAX(Tabelle4[[#This Row],[d32_el2_dl2_ff128-ep500]:[d64_el3_dl3_ff128-ep1000]]),1,0) -> 1 | R69: =IF(K69=MAX(Tabelle4[[#This Row],[d32_el2_dl2_ff128-ep500]:[d64_el3_dl3_ff128-ep1000]]),1,0) -> 1 | S69: =IF(L69=MAX(Tabelle4[[#This Row],[d32_el2_dl2_ff128-ep500]:[d64_el3_dl3_ff128-ep1000]]),1,0) -> 1 | T69: =IF(M69=MAX(Tabelle4[[#This Row],[d32_el2_dl2_ff128-ep500]:[d64_el3_dl3_ff128-ep1000]]),1,0) -> 1 | V69: =IF(H69=MIN(Tabelle4[[#This Row],[d32_el2_dl2_ff128-ep500]:[d64_el3_dl3_ff128-ep1000]]),1,0) -> 1 | W69: =IF(I69=MIN(Tabelle4[[#This Row],[d32_el2_dl2_ff128-ep500]:[d64_el3_dl3_ff128-ep1000]]),1,0) -> 0 | X69: =IF(J69=MIN(Tabelle4[[#This Row],[d32_el2_dl2_ff128-ep500]:[d64_el3_dl3_ff128-ep1000]]),1,0) -> 0 | Y69: =IF(K69=MIN(Tabelle4[[#This Row],[d32_el2_dl2_ff128-ep500]:[d64_el3_dl3_ff128-ep1000]]),1,0) -> 0 | Z69: =IF(L69=MIN(Tabelle4[[#This Row],[d32_el2_dl2_ff128-ep500]:[d64_el3_dl3_ff128-ep1000]]),1,0) -> 0 | AA69: =IF(M69=MIN(Tabelle4[[#This Row],[d32_el2_dl2_ff128-ep500]:[d64_el3_dl3_ff128-ep1000]]),1,0) -> 0
A70: 5 | B70: d64_el2_dl2_ff128-ep1000 | C70: ['verstehen', 'nicht'] | D70: 10 | E70: =D70+E63 -> 57 | G70: 69 | H70: {=INDEX($D$2:$D$701, (ROW()-ROW($G$2))*7 + (COLUMN()-COLUMN($G$2)) + 1)} -> 8 | I70: {=INDEX($D$2:$D$701, (ROW()-ROW($G$2))*7 + (COLUMN()-COLUMN($G$2)) + 1)} -> 10 | J70: {=INDEX($D$2:$D$701, (ROW()-ROW($G$2))*7 + (COLUMN()-COLUMN($G$2)) + 1)} -> 8 | K70: {=INDEX($D$2:$D$701, (ROW()-ROW($G$2))*7 + (COLUMN()-COLUMN($G$2)) + 1)} -> 8 | L70: {=INDEX($D$2:$D$701, (ROW()-ROW($G$2))*7 + (COLUMN()-COLUMN($G$2)) + 1)} -> 4 | M70: {=INDEX($D$2:$D$701, (ROW()-ROW($G$2))*7 + (COLUMN()-COLUMN($G$2)) + 1)} -> 10 | O70: =IF(H70=MAX(Tabelle4[[#This Row],[d32_el2_dl2_ff128-ep500]:[d64_el3_dl3_ff128-ep1000]]),1,0) -> 0 | P70: =IF(I70=MAX(Tabelle4[[#This Row],[d32_el2_dl2_ff128-ep500]:[d64_el3_dl3_ff128-ep1000]]),1,0) -> 1 | Q70: =IF(J70=MAX(Tabelle4[[#This Row],[d32_el2_dl2_ff128-ep500]:[d64_el3_dl3_ff128-ep1000]]),1,0) -> 0 | R70: =IF(K70=MAX(Tabelle4[[#This Row],[d32_el2_dl2_ff128-ep500]:[d64_el3_dl3_ff128-ep1000]]),1,0) -> 0 | S70: =IF(L70=MAX(Tabelle4[[#This Row],[d32_el2_dl2_ff128-ep500]:[d64_el3_dl3_ff128-ep1000]]),1,0) -> 0 | T70: =IF(M70=MAX(Tabelle4[[#This Row],[d32_el2_dl2_ff128-ep500]:[d64_el3_dl3_ff128-ep1000]]),1,0) -> 1 | V70: =IF(H70=MIN(Tabelle4[[#This Row],[d32_el2_dl2_ff128-ep500]:[d64_el3_dl3_ff128-ep1000]]),1,0) -> 0 | W70: =IF(I70=MIN(Tabelle4[[#This Row],[d32_el2_dl2_ff128-ep500]:[d64_el3_dl3_ff128-ep1000]]),1,0) -> 0 | X70: =IF(J70=MIN(Tabelle4[[#This Row],[d32_el2_dl2_ff128-ep500]:[d64_el3_dl3_ff128-ep1000]]),1,0) -> 0 | Y70: =IF(K70=MIN(Tabelle4[[#This Row],[d32_el2_dl2_ff128-ep500]:[d64_el3_dl3_ff128-ep1000]]),1,0) -> 0 | Z70: =IF(L70=MIN(Tabelle4[[#This Row],[d32_el2_dl2_ff128-ep500]:[d64_el3_dl3_ff128-ep1000]]),1,0) -> 1 | AA70: =IF(M70=MIN(Tabelle4[[#This Row],[d32_el2_dl2_ff128-ep500]:[d64_el3_dl3_ff128-ep1000]]),1,0) -> 0
A71: 6 | B71: d64_el3_dl3_ff128-ep1000 | C71: ['ich', 'verstehen', 'nicht'] | D71: 10 | E71: =D71+E64 -> 61 | G71: 70 | H71: {=INDEX($D$2:$D$701, (ROW()-ROW($G$2))*7 + (COLUMN()-COLUMN($G$2)) + 1)} -> 5 | I71: {=INDEX($D$2:$D$701, (ROW()-ROW($G$2))*7 + (COLUMN()-COLUMN($G$2)) + 1)} -> 5 | J71: {=INDEX($D$2:$D$701, (ROW()-ROW($G$2))*7 + (COLUMN()-COLUMN($G$2)) + 1)} -> 6 | K71: {=INDEX($D$2:$D$701, (ROW()-ROW($G$2))*7 + (COLUMN()-COLUMN($G$2)) + 1)} -> 7 | L71: {=INDEX($D$2:$D$701, (ROW()-ROW($G$2))*7 + (COLUMN()-COLUMN($G$2)) + 1)} -> 7 | M71: {=INDEX($D$2:$D$701, (ROW()-ROW($G$2))*7 + (COLUMN()-COLUMN($G$2)) + 1)} -> 4 | O71: =IF(H71=MAX(Tabelle4[[#This Row],[d32_el2_dl2_ff128-ep500]:[d64_el3_dl3_ff128-ep1000]]),1,0) -> 0 | P71: =IF(I71=MAX(Tabelle4[[#This Row],[d32_el2_dl2_ff128-ep500]:[d64_el3_dl3_ff128-ep1000]]),1,0) -> 0 | Q71: =IF(J71=MAX(Tabelle4[[#This Row],[d32_el2_dl2_ff128-ep500]:[d64_el3_dl3_ff128-ep1000]]),1,0) -> 0 | R71: =IF(K71=MAX(Tabelle4[[#This Row],[d32_el2_dl2_ff128-ep500]:[d64_el3_dl3_ff128-ep1000]]),1,0) -> 1 | S71: =IF(L71=MAX(Tabelle4[[#This Row],[d32_el2_dl2_ff128-ep500]:[d64_el3_dl3_ff128-ep1000]]),1,0) -> 1 | T71: =IF(M71=MAX(Tabelle4[[#This Row],[d32_el2_dl2_ff128-ep500]:[d64_el3_dl3_ff128-ep1000]]),1,0) -> 0 | V71: =IF(H71=MIN(Tabelle4[[#This Row],[d32_el2_dl2_ff128-ep500]:[d64_el3_dl3_ff128-ep1000]]),1,0) -> 0 | W71: =IF(I71=MIN(Tabelle4[[#This Row],[d32_el2_dl2_ff128-ep500]:[d64_el3_dl3_ff128-ep1000]]),1,0) -> 0 | X71: =IF(J71=MIN(Tabelle4[[#This Row],[d32_el2_dl2_ff128-ep500]:[d64_el3_dl3_ff128-ep1000]]),1,0) -> 0 | Y71: =IF(K71=MIN(Tabelle4[[#This Row],[d32_el2_dl2_ff128-ep500]:[d64_el3_dl3_ff128-ep1000]]),1,0) -> 0 | Z71: =IF(L71=MIN(Tabelle4[[#This Row],[d32_el2_dl2_ff128-ep500]:[d64_el3_dl3_ff128-ep1000]]),1,0) -> 0 | AA71: =IF(M71=MIN(Tabelle4[[#This Row],[d32_el2_dl2_ff128-ep500]:[d64_el3_dl3_ff128-ep1000]]),1,0) -> 1
A72: 0 | B72: 11 | C72: Kannst du mir die TÃ¼r aufmachen? | E72: =D72+E65 -> 0 | G72: 71 | H72: {=INDEX($D$2:$D$701, (ROW()-ROW($G$2))*7 + (COLUMN()-COLUMN($G$2)) + 1)} -> 8 | I72: {=INDEX($D$2:$D$701, (ROW()-ROW($G$2))*7 + (COLUMN()-COLUMN($G$2)) + 1)} -> 8 | J72: {=INDEX($D$2:$D$701, (ROW()-ROW($G$2))*7 + (COLUMN()-COLUMN($G$2)) + 1)} -> 8 | K72: {=INDEX($D$2:$D$701, (ROW()-ROW($G$2))*7 + (COLUMN()-COLUMN($G$2)) + 1)} -> 8 | L72: {=INDEX($D$2:$D$701, (ROW()-ROW($G$2))*7 + (COLUMN()-COLUMN($G$2)) + 1)} -> 8 | M72: {=INDEX($D$2:$D$701, (ROW()-ROW($G$2))*7 + (COLUMN()-COLUMN($G$2)) + 1)} -> 8 | O72: =IF(H72=MAX(Tabelle4[[#This Row],[d32_el2_dl2_ff128-ep500]:[d64_el3_dl3_ff128-ep1000]]),1,0) -> 1 | P72: =IF(I72=MAX(Tabelle4[[#This Row],[d32_el2_dl2_ff128-ep500]:[d64_el3_dl3_ff128-ep1000]]),1,0) -> 1 | Q72: =IF(J72=MAX(Tabelle4[[#This Row],[d32_el2_dl2_ff128-ep500]:[d64_el3_dl3_ff128-ep1000]]),1,0) -> 1 | R72: =IF(K72=MAX(Tabelle4[[#This Row],[d32_el2_dl2_ff128-ep500]:[d64_el3_dl3_ff128-ep1000]]),1,0) -> 1 | S72: =IF(L72=MAX(Tabelle4[[#This Row],[d32_el2_dl2_ff128-ep500]:[d64_el3_dl3_ff128-ep1000]]),1,0) -> 1 | T72: =IF(M72=MAX(Tabelle4[[#This Row],[d32_el2_dl2_ff128-ep500]:[d64_el3_dl3_ff128-ep1000]]),1,0) -> 1 | V72: =IF(H72=MIN(Tabelle4[[#This Row],[d32_el2_dl2_ff128-ep500]:[d64_el3_dl3_ff128-ep1000]]),1,0) -> 1 | W72: =IF(I72=MIN(Tabelle4[[#This Row],[d32_el2_dl2_ff128-ep500]:[d64_el3_dl3_ff128-ep1000]]),1,0) -> 1 | X72: =IF(J72=MIN(Tabelle4[[#This Row],[d32_el2_dl2_ff128-ep500]:[d64_el3_dl3_ff128-ep1000]]),1,0) -> 1 | Y72: =IF(K72=MIN(Tabelle4[[#This Row],[d32_el2_dl2_ff128-ep500]:[d64_el3_dl3_ff128-ep1000]]),1,0) -> 1 | Z72: =IF(L72=MIN(Tabelle4[[#This Row],[d32_el2_dl2_ff128-ep500]:[d64_el3_dl3_ff128-ep1000]]),1,0) -> 1 | AA72: =IF(M72=MIN(Tabelle4[[#This Row],[d32_el2_dl2_ff128-ep500]:[d64_el3_dl3_ff128-ep1000]]),1,0) -> 1
A73: 1 | B73: d32_el2_dl2_ff128-ep500 | C73: ['du', 'frage', 'du'] | D73: 6 | E73: =D73+E66 -> 64 | G73: 72 | H73: {=INDEX($D$2:$D$701, (ROW()-ROW($G$2))*7 + (COLUMN()-COLUMN($G$2)) + 1)} -> 8 | I73: {=INDEX($D$2:$D$701, (ROW()-ROW($G$2))*7 + (COLUMN()-COLUMN($G$2)) + 1)} -> 4 | J73: {=INDEX($D$2:$D$701, (ROW()-ROW($G$2))*7 + (COLUMN()-COLUMN($G$2)) + 1)} -> 6 | K73: {=INDEX($D$2:$D$701, (ROW()-ROW($G$2))*7 + (COLUMN()-COLUMN($G$2)) + 1)} -> 8 | L73: {=INDEX($D$2:$D$701, (ROW()-ROW($G$2))*7 + (COLUMN()-COLUMN($G$2)) + 1)} -> 8 | M73: {=INDEX($D$2:$D$701, (ROW()-ROW($G$2))*7 + (COLUMN()-COLUMN($G$2)) + 1)} -> 9 | O73: =IF(H73=MAX(Tabelle4[[#This Row],[d32_el2_dl2_ff128-ep500]:[d64_el3_dl3_ff128-ep1000]]),1,0) -> 0 | P73: =IF(I73=MAX(Tabelle4[[#This Row],[d32_el2_dl2_ff128-ep500]:[d64_el3_dl3_ff128-ep1000]]),1,0) -> 0 | Q73: =IF(J73=MAX(Tabelle4[[#This Row],[d32_el2_dl2_ff128-ep500]:[d64_el3_dl3_ff128-ep1000]]),1,0) -> 0 | R73: =IF(K73=MAX(Tabelle4[[#This Row],[d32_el2_dl2_ff128-ep500]:[d64_el3_dl3_ff128-ep1000]]),1,0) -> 0 | S73: =IF(L73=MAX(Tabelle4[[#This Row],[d32_el2_dl2_ff128-ep500]:[d64_el3_dl3_ff128-ep1000]]),1,0) -> 0 | T73: =IF(M73=MAX(Tabelle4[[#This Row],[d32_el2_dl2_ff128-ep500]:[d64_el3_dl3_ff128-ep1000]]),1,0) -> 1 | V73: =IF(H73=MIN(Tabelle4[[#This Row],[d32_el2_dl2_ff128-ep500]:[d64_el3_dl3_ff128-ep1000]]),1,0) -> 0 | W73: =IF(I73=MIN(Tabelle4[[#This Row],[d32_el2_dl2_ff128-ep500]:[d64_el3_dl3_ff128-ep1000]]),1,0) -> 1 | X73: =IF(J73=MIN(Tabelle4[[#This Row],[d32_el2_dl2_ff128-ep500]:[d64_el3_dl3_ff128-ep1000]]),1,0) -> 0 | Y73: =IF(K73=MIN(Tabelle4[[#This Row],[d32_el2_dl2_ff128-ep500]:[d64_el3_dl3_ff128-ep1000]]),1,0) -> 0 | Z73: =IF(L73=MIN(Tabelle4[[#This Row],[d32_el2_dl2_ff128-ep500]:[d64_el3_dl3_ff128-ep1000]]),1,0) -> 0 | AA73: =IF(M73=MIN(Tabelle4[[#This Row],[d32_el2_dl2_ff128-ep500]:[d64_el3_dl3_ff128-ep1000]]),1,0) -> 0
A74: 2 | B74: d64_el1_dl1_ff64-ep1000 | C74: ['du', 'machen', 'du'] | D74: 6 | E74: =D74+E67 -> 55 | G74: 73 | H74: {=INDEX($D$2:$D$701, (ROW()-ROW($G$2))*7 + (COLUMN()-COLUMN($G$2)) + 1)} -> 0 | I74: {=INDEX($D$2:$D$701, (ROW()-ROW($G$2))*7 + (COLUMN()-COLUMN($G$2)) + 1)} -> 6 | J74: {=INDEX($D$2:$D$701, (ROW()-ROW($G$2))*7 + (COLUMN()-COLUMN($G$2)) + 1)} -> 0 | K74: {=INDEX($D$2:$D$701, (ROW()-ROW($G$2))*7 + (COLUMN()-COLUMN($G$2)) + 1)} -> 0 | L74: {=INDEX($D$2:$D$701, (ROW()-ROW($G$2))*7 + (COLUMN()-COLUMN($G$2)) + 1)} -> 2 | M74: {=INDEX($D$2:$D$701, (ROW()-ROW($G$2))*7 + (COLUMN()-COLUMN($G$2)) + 1)} -> 0 | O74: =IF(H74=MAX(Tabelle4[[#This Row],[d32_el2_dl2_ff128-ep500]:[d64_el3_dl3_ff128-ep1000]]),1,0) -> 0 | P74: =IF(I74=MAX(Tabelle4[[#This Row],[d32_el2_dl2_ff128-ep500]:[d64_el3_dl3_ff128-ep1000]]),1,0) -> 1 | Q74: =IF(J74=MAX(Tabelle4[[#This Row],[d32_el2_dl2_ff128-ep500]:[d64_el3_dl3_ff128-ep1000]]),1,0) -> 0 | R74: =IF(K74=MAX(Tabelle4[[#This Row],[d32_el2_dl2_ff128-ep500]:[d64_el3_dl3_ff128-ep1000]]),1,0) -> 0 | S74: =IF(L74=MAX(Tabelle4[[#This Row],[d32_el2_dl2_ff128-ep500]:[d64_el3_dl3_ff128-ep1000]]),1,0) -> 0 | T74: =IF(M74=MAX(Tabelle4[[#This Row],[d32_el2_dl2_ff128-ep500]:[d64_el3_dl3_ff128-ep1000]]),1,0) -> 0 | V74: =IF(H74=MIN(Tabelle4[[#This Row],[d32_el2_dl2_ff128-ep500]:[d64_el3_dl3_ff128-ep1000]]),1,0) -> 1 | W74: =IF(I74=MIN(Tabelle4[[#This Row],[d32_el2_dl2_ff128-ep500]:[d64_el3_dl3_ff128-ep1000]]),1,0) -> 0 | X74: =IF(J74=MIN(Tabelle4[[#This Row],[d32_el2_dl2_ff128-ep500]:[d64_el3_dl3_ff128-ep1000]]),1,0) -> 1 | Y74: =IF(K74=MIN(Tabelle4[[#This Row],[d32_el2_dl2_ff128-ep500]:[d64_el3_dl3_ff128-ep1000]]),1,0) -> 1 | Z74: =IF(L74=MIN(Tabelle4[[#This Row],[d32_el2_dl2_ff128-ep500]:[d64_el3_dl3_ff128-ep1000]]),1,0) -> 0 | AA74: =IF(M74=MIN(Tabelle4[[#This Row],[d32_el2_dl2_ff128-ep500]:[d64_el3_dl3_ff128-ep1000]]),1,0) -> 1
A75: 3 | B75: d64_el2_dl2_ff64-ep500 | C75: ['du', 'kann', 'du', 'probe', 'du'] | D75: 6 | E75: =D75+E68 -> 56 | G75: 74 | H75: {=INDEX($D$2:$D$701, (ROW()-ROW($G$2))*7 + (COLUMN()-COLUMN($G$2)) + 1)} -> 4 | I75: {=INDEX($D$2:$D$701, (ROW()-ROW($G$2))*7 + (COLUMN()-COLUMN($G$2)) + 1)} -> 1 | J75: {=INDEX($D$2:$D$701, (ROW()-ROW($G$2))*7 + (COLUMN()-COLUMN($G$2)) + 1)} -> 1 | K75: {=INDEX($D$2:$D$701, (ROW()-ROW($G$2))*7 + (COLUMN()-COLUMN($G$2)) + 1)} -> 1 | L75: {=INDEX($D$2:$D$701, (ROW()-ROW($G$2))*7 + (COLUMN()-COLUMN($G$2)) + 1)} -> 3 | M75: {=INDEX($D$2:$D$701, (ROW()-ROW($G$2))*7 + (COLUMN()-COLUMN($G$2)) + 1)} -> 1 | O75: =IF(H75=MAX(Tabelle4[[#This Row],[d32_el2_dl2_ff128-ep500]:[d64_el3_dl3_ff128-ep1000]]),1,0) -> 1 | P75: =IF(I75=MAX(Tabelle4[[#This Row],[d32_el2_dl2_ff128-ep500]:[d64_el3_dl3_ff128-ep1000]]),1,0) -> 0 | Q75: =IF(J75=MAX(Tabelle4[[#This Row],[d32_el2_dl2_ff128-ep500]:[d64_el3_dl3_ff128-ep1000]]),1,0) -> 0 | R75: =IF(K75=MAX(Tabelle4[[#This Row],[d32_el2_dl2_ff128-ep500]:[d64_el3_dl3_ff128-ep1000]]),1,0) -> 0 | S75: =IF(L75=MAX(Tabelle4[[#This Row],[d32_el2_dl2_ff128-ep500]:[d64_el3_dl3_ff128-ep1000]]),1,0) -> 0 | T75: =IF(M75=MAX(Tabelle4[[#This Row],[d32_el2_dl2_ff128-ep500]:[d64_el3_dl3_ff128-ep1000]]),1,0) -> 0 | V75: =IF(H75=MIN(Tabelle4[[#This Row],[d32_el2_dl2_ff128-ep500]:[d64_el3_dl3_ff128-ep1000]]),1,0) -> 0 | W75: =IF(I75=MIN(Tabelle4[[#This Row],[d32_el2_dl2_ff128-ep500]:[d64_el3_dl3_ff128-ep1000]]),1,0) -> 1 | X75: =IF(J75=MIN(Tabelle4[[#This Row],[d32_el2_dl2_ff128-ep500]:[d64_el3_dl3_ff128-ep1000]]),1,0) -> 1 | Y75: =IF(K75=MIN(Tabelle4[[#This Row],[d32_el2_dl2_ff128-ep500]:[d64_el3_dl3_ff128-ep1000]]),1,0) -> 1 | Z75: =IF(L75=MIN(Tabelle4[[#This Row],[d32_el2_dl2_ff128-ep500]:[d64_el3_dl3_ff128-ep1000]]),1,0) -> 0 | AA75: =IF(M75=MIN(Tabelle4[[#This Row],[d32_el2_dl2_ff128-ep500]:[d64_el3_dl3_ff128-ep1000]]),1,0) -> 1
A76: 4 | B76: d64_el2_dl2_ff64-ep1000 | C76: ['kann', 'probe', 'du'] | D76: 6 | E76: =D76+E69 -> 57 | G76: 75 | H76: {=INDEX($D$2:$D$701, (ROW()-ROW($G$2))*7 + (COLUMN()-COLUMN($G$2)) + 1)} -> 1 | I76: {=INDEX($D$2:$D$701, (ROW()-ROW($G$2))*7 + (COLUMN()-COLUMN($G$2)) + 1)} -> 4 | J76: {=INDEX($D$2:$D$701, (ROW()-ROW($G$2))*7 + (COLUMN()-COLUMN($G$2)) + 1)} -> 3 | K76: {=INDEX($D$2:$D$701, (ROW()-ROW($G$2))*7 + (COLUMN()-COLUMN($G$2)) + 1)} -> 3 | L76: {=INDEX($D$2:$D$701, (ROW()-ROW($G$2))*7 + (COLUMN()-COLUMN($G$2)) + 1)} -> 0 | M76: {=INDEX($D$2:$D$701, (ROW()-ROW($G$2))*7 + (COLUMN()-COLUMN($G$2)) + 1)} -> 0 | O76: =IF(H76=MAX(Tabelle4[[#This Row],[d32_el2_dl2_ff128-ep500]:[d64_el3_dl3_ff128-ep1000]]),1,0) -> 0 | P76: =IF(I76=MAX(Tabelle4[[#This Row],[d32_el2_dl2_ff128-ep500]:[d64_el3_dl3_ff128-ep1000]]),1,0) -> 1 | Q76: =IF(J76=MAX(Tabelle4[[#This Row],[d32_el2_dl2_ff128-ep500]:[d64_el3_dl3_ff128-ep1000]]),1,0) -> 0 | R76: =IF(K76=MAX(Tabelle4[[#This Row],[d32_el2_dl2_ff128-ep500]:[d64_el3_dl3_ff128-ep1000]]),1,0) -> 0 | S76: =IF(L76=MAX(Tabelle4[[#This Row],[d32_el2_dl2_ff128-ep500]:[d64_el3_dl3_ff128-ep1000]]),1,0) -> 0 | T76: =IF(M76=MAX(Tabelle4[[#This Row],[d32_el2_dl2_ff128-ep500]:[d64_el3_dl3_ff128-ep1000]]),1,0) -> 0 | V76: =IF(H76=MIN(Tabelle4[[#This Row],[d32_el2_dl2_ff128-ep500]:[d64_el3_dl3_ff128-ep1000]]),1,0) -> 0 | W76: =IF(I76=MIN(Tabelle4[[#This Row],[d32_el2_dl2_ff128-ep500]:[d64_el3_dl3_ff128-ep1000]]),1,0) -> 0 | X76: =IF(J76=MIN(Tabelle4[[#This Row],[d32_el2_dl2_ff128-ep500]:[d64_el3_dl3_ff128-ep1000]]),1,0) -> 0 | Y76: =IF(K76=MIN(Tabelle4[[#This Row],[d32_el2_dl2_ff128-ep500]:[d64_el3_dl3_ff128-ep1000]]),1,0) -> 0 | Z76: =IF(L76=MIN(Tabelle4[[#This Row],[d32_el2_dl2_ff128-ep500]:[d64_el3_dl3_ff128-ep1000]]),1,0) -> 1 | AA76: =IF(M76=MIN(Tabelle4[[#This Row],[d32_el2_dl2_ff128-ep500]:[d64_el3_dl3_ff128-ep1000]]),1,0) -> 1
A77: 5 | B77: d64_el2_dl2_ff128-ep1000 | C77: ['du', 'kann', 'du', 'kann', 'du'] | D77: 6 | E77: =D77+E70 -> 63 | G77: 76 | H77: {=INDEX($D$2:$D$701, (ROW()-ROW($G$2))*7 + (COLUMN()-COLUMN($G$2)) + 1)} -> 9 | I77: {=INDEX($D$2:$D$701, (ROW()-ROW($G$2))*7 + (COLUMN()-COLUMN($G$2)) + 1)} -> 7 | J77: {=INDEX($D$2:$D$701, (ROW()-ROW($G$2))*7 + (COLUMN()-COLUMN($G$2)) + 1)} -> 6 | K77: {=INDEX($D$2:$D$701, (ROW()-ROW($G$2))*7 + (COLUMN()-COLUMN($G$2)) + 1)} -> 6 | L77: {=INDEX($D$2:$D$701, (ROW()-ROW($G$2))*7 + (COLUMN()-COLUMN($G$2)) + 1)} -> 7 | M77: {=INDEX($D$2:$D$701, (ROW()-ROW($G$2))*7 + (COLUMN()-COLUMN($G$2)) + 1)} -> 8 | O77: =IF(H77=MAX(Tabelle4[[#This Row],[d32_el2_dl2_ff128-ep500]:[d64_el3_dl3_ff128-ep1000]]),1,0) -> 1 | P77: =IF(I77=MAX(Tabelle4[[#This Row],[d32_el2_dl2_ff128-ep500]:[d64_el3_dl3_ff128-ep1000]]),1,0) -> 0 | Q77: =IF(J77=MAX(Tabelle4[[#This Row],[d32_el2_dl2_ff128-ep500]:[d64_el3_dl3_ff128-ep1000]]),1,0) -> 0 | R77: =IF(K77=MAX(Tabelle4[[#This Row],[d32_el2_dl2_ff128-ep500]:[d64_el3_dl3_ff128-ep1000]]),1,0) -> 0 | S77: =IF(L77=MAX(Tabelle4[[#This Row],[d32_el2_dl2_ff128-ep500]:[d64_el3_dl3_ff128-ep1000]]),1,0) -> 0 | T77: =IF(M77=MAX(Tabelle4[[#This Row],[d32_el2_dl2_ff128-ep500]:[d64_el3_dl3_ff128-ep1000]]),1,0) -> 0 | V77: =IF(H77=MIN(Tabelle4[[#This Row],[d32_el2_dl2_ff128-ep500]:[d64_el3_dl3_ff128-ep1000]]),1,0) -> 0 | W77: =IF(I77=MIN(Tabelle4[[#This Row],[d32_el2_dl2_ff128-ep500]:[d64_el3_dl3_ff128-ep1000]]),1,0) -> 0 | X77: =IF(J77=MIN(Tabelle4[[#This Row],[d32_el2_dl2_ff128-ep500]:[d64_el3_dl3_ff128-ep1000]]),1,0) -> 1 | Y77: =IF(K77=MIN(Tabelle4[[#This Row],[d32_el2_dl2_ff128-ep500]:[d64_el3_dl3_ff128-ep1000]]),1,0) -> 1 | Z77: =IF(L77=MIN(Tabelle4[[#This Row],[d32_el2_dl2_ff128-ep500]:[d64_el3_dl3_ff128-ep1000]]),1,0) -> 0 | AA77: =IF(M77=MIN(Tabelle4[[#This Row],[d32_el2_dl2_ff128-ep500]:[d64_el3_dl3_ff128-ep1000]]),1,0) -> 0
A78: 6 | B78: d64_el3_dl3_ff128-ep1000 | C78: ['kann', 'du', 'selbst', 'ansprechen', 'abmachen'] | D78: 4 | E78: =D78+E71 -> 65 | G78: 77 | H78: {=INDEX($D$2:$D$701, (ROW()-ROW($G$2))*7 + (COLUMN()-COLUMN($G$2)) + 1)} -> 8 | I78: {=INDEX($D$2:$D$701, (ROW()-ROW($G$2))*7 + (COLUMN()-COLUMN($G$2)) + 1)} -> 10 | J78: {=INDEX($D$2:$D$701, (ROW()-ROW($G$2))*7 + (COLUMN()-COLUMN($G$2)) + 1)} -> 8 | K78: {=INDEX($D$2:$D$701, (ROW()-ROW($G$2))*7 + (COLUMN()-COLUMN($G$2)) + 1)} -> 8 | L78: {=INDEX($D$2:$D$701, (ROW()-ROW($G$2))*7 + (COLUMN()-COLUMN($G$2)) + 1)} -> 8 | M78: {=INDEX($D$2:$D$701, (ROW()-ROW($G$2))*7 + (COLUMN()-COLUMN($G$2)) + 1)} -> 8 | O78: =IF(H78=MAX(Tabelle4[[#This Row],[d32_el2_dl2_ff128-ep500]:[d64_el3_dl3_ff128-ep1000]]),1,0) -> 0 | P78: =IF(I78=MAX(Tabelle4[[#This Row],[d32_el2_dl2_ff128-ep500]:[d64_el3_dl3_ff128-ep1000]]),1,0) -> 1 | Q78: =IF(J78=MAX(Tabelle4[[#This Row],[d32_el2_dl2_ff128-ep500]:[d64_el3_dl3_ff128-ep1000]]),1,0) -> 0 | R78: =IF(K78=MAX(Tabelle4[[#This Row],[d32_el2_dl2_ff128-ep500]:[d64_el3_dl3_ff128-ep1000]]),1,0) -> 0 | S78: =IF(L78=MAX(Tabelle4[[#This Row],[d32_el2_dl2_ff128-ep500]:[d64_el3_dl3_ff128-ep1000]]),1,0) -> 0 | T78: =IF(M78=MAX(Tabelle4[[#This Row],[d32_el2_dl2_ff128-ep500]:[d64_el3_dl3_ff128-ep1000]]),1,0) -> 0 | V78: =IF(H78=MIN(Tabelle4[[#This Row],[d32_el2_dl2_ff128-ep500]:[d64_el3_dl3_ff128-ep1000]]),1,0) -> 1 | W78: =IF(I78=MIN(Tabelle4[[#This Row],[d32_el2_dl2_ff128-ep500]:[d64_el3_dl3_ff128-ep1000]]),1,0) -> 0 | X78: =IF(J78=MIN(Tabelle4[[#This Row],[d32_el2_dl2_ff128-ep500]:[d64_el3_dl3_ff128-ep1000]]),1,0) -> 1 | Y78: =IF(K78=MIN(Tabelle4[[#This Row],[d32_el2_dl2_ff128-ep500]:[d64_el3_dl3_ff128-ep1000]]),1,0) -> 1 | Z78: =IF(L78=MIN(Tabelle4[[#This Row],[d32_el2_dl2_ff128-ep500]:[d64_el3_dl3_ff128-ep1000]]),1,0) -> 1 | AA78: =IF(M78=MIN(Tabelle4[[#This Row],[d32_el2_dl2_ff128-ep500]:[d64_el3_dl3_ff128-ep1000]]),1,0) -> 1
A79: 0 | B79: 12 | C79: Wo ist die nÃ¤chste Haltestelle? | E79: =D79+E72 -> 0 | G79: 78 | H79: {=INDEX($D$2:$D$701, (ROW()-ROW($G$2))*7 + (COLUMN()-COLUMN($G$2)) + 1)} -> 2 | I79: {=INDEX($D$2:$D$701, (ROW()-ROW($G$2))*7 + (COLUMN()-COLUMN($G$2)) + 1)} -> 1 | J79: {=INDEX($D$2:$D$701, (ROW()-ROW($G$2))*7 + (COLUMN()-COLUMN($G$2)) + 1)} -> 1 | K79: {=INDEX($D$2:$D$701, (ROW()-ROW($G$2))*7 + (COLUMN()-COLUMN($G$2)) + 1)} -> 1 | L79: {=INDEX($D$2:$D$701, (ROW()-ROW($G$2))*7 + (COLUMN()-COLUMN($G$2)) + 1)} -> 2 | M79: {=INDEX($D$2:$D$701, (ROW()-ROW($G$2))*7 + (COLUMN()-COLUMN($G$2)) + 1)} -> 0 | O79: =IF(H79=MAX(Tabelle4[[#This Row],[d32_el2_dl2_ff128-ep500]:[d64_el3_dl3_ff128-ep1000]]),1,0) -> 1 | P79: =IF(I79=MAX(Tabelle4[[#This Row],[d32_el2_dl2_ff128-ep500]:[d64_el3_dl3_ff128-ep1000]]),1,0) -> 0 | Q79: =IF(J79=MAX(Tabelle4[[#This Row],[d32_el2_dl2_ff128-ep500]:[d64_el3_dl3_ff128-ep1000]]),1,0) -> 0 | R79: =IF(K79=MAX(Tabelle4[[#This Row],[d32_el2_dl2_ff128-ep500]:[d64_el3_dl3_ff128-ep1000]]),1,0) -> 0 | S79: =IF(L79=MAX(Tabelle4[[#This Row],[d32_el2_dl2_ff128-ep500]:[d64_el3_dl3_ff128-ep1000]]),1,0) -> 1 | T79: =IF(M79=MAX(Tabelle4[[#This Row],[d32_el2_dl2_ff128-ep500]:[d64_el3_dl3_ff128-ep1000]]),1,0) -> 0 | V79: =IF(H79=MIN(Tabelle4[[#This Row],[d32_el2_dl2_ff128-ep500]:[d64_el3_dl3_ff128-ep1000]]),1,0) -> 0 | W79: =IF(I79=MIN(Tabelle4[[#This Row],[d32_el2_dl2_ff128-ep500]:[d64_el3_dl3_ff128-ep1000]]),1,0) -> 0 | X79: =IF(J79=MIN(Tabelle4[[#This Row],[d32_el2_dl2_ff128-ep500]:[d64_el3_dl3_ff128-ep1000]]),1,0) -> 0 | Y79: =IF(K79=MIN(Tabelle4[[#This Row],[d32_el2_dl2_ff128-ep500]:[d64_el3_dl3_ff128-ep1000]]),1,0) -> 0 | Z79: =IF(L79=MIN(Tabelle4[[#This Row],[d32_el2_dl2_ff128-ep500]:[d64_el3_dl3_ff128-ep1000]]),1,0) -> 0 | AA79: =IF(M79=MIN(Tabelle4[[#This Row],[d32_el2_dl2_ff128-ep500]:[d64_el3_dl3_ff128-ep1000]]),1,0) -> 1
A80: 1 | B80: d32_el2_dl2_ff128-ep500 | C80: ['index', 'index', 'index', 'prod', 'prod', 'prod', 'prod', 'prod'] | D80: 0 | E80: =D80+E73 -> 64 | G80: 79 | H80: {=INDEX($D$2:$D$701, (ROW()-ROW($G$2))*7 + (COLUMN()-COLUMN($G$2)) + 1)} -> 8 | I80: {=INDEX($D$2:$D$701, (ROW()-ROW($G$2))*7 + (COLUMN()-COLUMN($G$2)) + 1)} -> 9 | J80: {=INDEX($D$2:$D$701, (ROW()-ROW($G$2))*7 + (COLUMN()-COLUMN($G$2)) + 1)} -> 8 | K80: {=INDEX($D$2:$D$701, (ROW()-ROW($G$2))*7 + (COLUMN()-COLUMN($G$2)) + 1)} -> 8 | L80: {=INDEX($D$2:$D$701, (ROW()-ROW($G$2))*7 + (COLUMN()-COLUMN($G$2)) + 1)} -> 8 | M80: {=INDEX($D$2:$D$701, (ROW()-ROW($G$2))*7 + (COLUMN()-COLUMN($G$2)) + 1)} -> 9 | O80: =IF(H80=MAX(Tabelle4[[#This Row],[d32_el2_dl2_ff128-ep500]:[d64_el3_dl3_ff128-ep1000]]),1,0) -> 0 | P80: =IF(I80=MAX(Tabelle4[[#This Row],[d32_el2_dl2_ff128-ep500]:[d64_el3_dl3_ff128-ep1000]]),1,0) -> 1 | Q80: =IF(J80=MAX(Tabelle4[[#This Row],[d32_el2_dl2_ff128-ep500]:[d64_el3_dl3_ff128-ep1000]]),1,0) -> 0 | R80: =IF(K80=MAX(Tabelle4[[#This Row],[d32_el2_dl2_ff128-ep500]:[d64_el3_dl3_ff128-ep1000]]),1,0) -> 0 | S80: =IF(L80=MAX(Tabelle4[[#This Row],[d32_el2_dl2_ff128-ep500]:[d64_el3_dl3_ff128-ep1000]]),1,0) -> 0 | T80: =IF(M80=MAX(Tabelle4[[#This Row],[d32_el2_dl2_ff128-ep500]:[d64_el3_dl3_ff128-ep1000]]),1,0) -> 1 | V80: =IF(H80=MIN(Tabelle4[[#This Row],[d32_el2_dl2_ff128-ep500]:[d64_el3_dl3_ff128-ep1000]]),1,0) -> 1 | W80: =IF(I80=MIN(Tabelle4[[#This Row],[d32_el2_dl2_ff128-ep500]:[d64_el3_dl3_ff128-ep1000]]),1,0) -> 0 | X80: =IF(J80=MIN(Tabelle4[[#This Row],[d32_el2_dl2_ff128-ep500]:[d64_el3_dl3_ff128-ep1000]]),1,0) -> 1 | Y80: =IF(K80=MIN(Tabelle4[[#This Row],[d32_el2_dl2_ff128-ep500]:[d64_el3_dl3_ff128-ep1000]]),1,0) -> 1 | Z80: =IF(L80=MIN(Tabelle4[[#This Row],[d32_el2_dl2_ff128-ep500]:[d64_el3_dl3_ff128-ep1000]]),1,0) -> 1 | AA80: =IF(M80=MIN(Tabelle4[[#This Row],[d32_el2_dl2_ff128-ep500]:[d64_el3_dl3_ff128-ep1000]]),1,0) -> 0
A81: 2 | B81: d64_el1_dl1_ff64-ep1000 | C81: ['kennen', 'index', 'schild', 'prod', 'prod', 'prod'] | D81: 3 | E81: =D81+E74 -> 58 | G81: 80 | H81: {=INDEX($D$2:$D$701, (ROW()-ROW($G$2))*7 + (COLUMN()-COLUMN($G$2)) + 1)} -> 4 | I81: {=INDEX($D$2:$D$701, (ROW()-ROW($G$2))*7 + (COLUMN()-COLUMN($G$2)) + 1)} -> 8 | J81: {=INDEX($D$2:$D$701, (ROW()-ROW($G$2))*7 + (COLUMN()-COLUMN($G$2)) + 1)} -> 6 | K81: {=INDEX($D$2:$D$701, (ROW()-ROW($G$2))*7 + (COLUMN()-COLUMN($G$2)) + 1)} -> 6 | L81: {=INDEX($D$2:$D$701, (ROW()-ROW($G$2))*7 + (COLUMN()-COLUMN($G$2)) + 1)} -> 6 | M81: {=INDEX($D$2:$D$701, (ROW()-ROW($G$2))*7 + (COLUMN()-COLUMN($G$2)) + 1)} -> 8 | O81: =IF(H81=MAX(Tabelle4[[#This Row],[d32_el2_dl2_ff128-ep500]:[d64_el3_dl3_ff128-ep1000]]),1,0) -> 0 | P81: =IF(I81=MAX(Tabelle4[[#This Row],[d32_el2_dl2_ff128-ep500]:[d64_el3_dl3_ff128-ep1000]]),1,0) -> 1 | Q81: =IF(J81=MAX(Tabelle4[[#This Row],[d32_el2_dl2_ff128-ep500]:[d64_el3_dl3_ff128-ep1000]]),1,0) -> 0 | R81: =IF(K81=MAX(Tabelle4[[#This Row],[d32_el2_dl2_ff128-ep500]:[d64_el3_dl3_ff128-ep1000]]),1,0) -> 0 | S81: =IF(L81=MAX(Tabelle4[[#This Row],[d32_el2_dl2_ff128-ep500]:[d64_el3_dl3_ff128-ep1000]]),1,0) -> 0 | T81: =IF(M81=MAX(Tabelle4[[#This Row],[d32_el2_dl2_ff128-ep500]:[d64_el3_dl3_ff128-ep1000]]),1,0) -> 1 | V81: =IF(H81=MIN(Tabelle4[[#This Row],[d32_el2_dl2_ff128-ep500]:[d64_el3_dl3_ff128-ep1000]]),1,0) -> 1 | W81: =IF(I81=MIN(Tabelle4[[#This Row],[d32_el2_dl2_ff128-ep500]:[d64_el3_dl3_ff128-ep1000]]),1,0) -> 0 | X81: =IF(J81=MIN(Tabelle4[[#This Row],[d32_el2_dl2_ff128-ep500]:[d64_el3_dl3_ff128-ep1000]]),1,0) -> 0 | Y81: =IF(K81=MIN(Tabelle4[[#This Row],[d32_el2_dl2_ff128-ep500]:[d64_el3_dl3_ff128-ep1000]]),1,0) -> 0 | Z81: =IF(L81=MIN(Tabelle4[[#This Row],[d32_el2_dl2_ff128-ep500]:[d64_el3_dl3_ff128-ep1000]]),1,0) -> 0 | AA81: =IF(M81=MIN(Tabelle4[[#This Row],[d32_el2_dl2_ff128-ep500]:[d64_el3_dl3_ff128-ep1000]]),1,0) -> 0
A82: 3 | B82: d64_el2_dl2_ff64-ep500 | C82: ['index', 'technik', 'prod', 'prod', 'prod', 'prod', 'prod', 'prod', 'prod'] | D82: 0 | E82: =D82+E75 -> 56 | G82: 81 | H82: {=INDEX($D$2:$D$701, (ROW()-ROW($G$2))*7 + (COLUMN()-COLUMN($G$2)) + 1)} -> 3 | I82: {=INDEX($D$2:$D$701, (ROW()-ROW($G$2))*7 + (COLUMN()-COLUMN($G$2)) + 1)} -> 0 | J82: {=INDEX($D$2:$D$701, (ROW()-ROW($G$2))*7 + (COLUMN()-COLUMN($G$2)) + 1)} -> 2 | K82: {=INDEX($D$2:$D$701, (ROW()-ROW($G$2))*7 + (COLUMN()-COLUMN($G$2)) + 1)} -> 2 | L82: {=INDEX($D$2:$D$701, (ROW()-ROW($G$2))*7 + (COLUMN()-COLUMN($G$2)) + 1)} -> 1 | M82: {=INDEX($D$2:$D$701, (ROW()-ROW($G$2))*7 + (COLUMN()-COLUMN($G$2)) + 1)} -> 2 | O82: =IF(H82=MAX(Tabelle4[[#This Row],[d32_el2_dl2_ff128-ep500]:[d64_el3_dl3_ff128-ep1000]]),1,0) -> 1 | P82: =IF(I82=MAX(Tabelle4[[#This Row],[d32_el2_dl2_ff128-ep500]:[d64_el3_dl3_ff128-ep1000]]),1,0) -> 0 | Q82: =IF(J82=MAX(Tabelle4[[#This Row],[d32_el2_dl2_ff128-ep500]:[d64_el3_dl3_ff128-ep1000]]),1,0) -> 0 | R82: =IF(K82=MAX(Tabelle4[[#This Row],[d32_el2_dl2_ff128-ep500]:[d64_el3_dl3_ff128-ep1000]]),1,0) -> 0 | S82: =IF(L82=MAX(Tabelle4[[#This Row],[d32_el2_dl2_ff128-ep500]:[d64_el3_dl3_ff128-ep1000]]),1,0) -> 0 | T82: =IF(M82=MAX(Tabelle4[[#This Row],[d32_el2_dl2_ff128-ep500]:[d64_el3_dl3_ff128-ep1000]]),1,0) -> 0 | V82: =IF(H82=MIN(Tabelle4[[#This Row],[d32_el2_dl2_ff128-ep500]:[d64_el3_dl3_ff128-ep1000]]),1,0) -> 0 | W82: =IF(I82=MIN(Tabelle4[[#This Row],[d32_el2_dl2_ff128-ep500]:[d64_el3_dl3_ff128-ep1000]]),1,0) -> 1 | X82: =IF(J82=MIN(Tabelle4[[#This Row],[d32_el2_dl2_ff128-ep500]:[d64_el3_dl3_ff128-ep1000]]),1,0) -> 0 | Y82: =IF(K82=MIN(Tabelle4[[#This Row],[d32_el2_dl2_ff128-ep500]:[d64_el3_dl3_ff128-ep1000]]),1,0) -> 0 | Z82: =IF(L82=MIN(Tabelle4[[#This Row],[d32_el2_dl2_ff128-ep500]:[d64_el3_dl3_ff128-ep1000]]),1,0) -> 0 | AA82: =IF(M82=MIN(Tabelle4[[#This Row],[d32_el2_dl2_ff128-ep500]:[d64_el3_dl3_ff128-ep1000]]),1,0) -> 0
A83: 4 | B83: d64_el2_dl2_ff64-ep1000 | C83: ['index', 'technik', 'prod', 'prod', 'prod', 'prod', 'prod', 'prod', 'prod'] | D83: 0 | E83: =D83+E76 -> 57 | G83: 82 | H83: {=INDEX($D$2:$D$701, (ROW()-ROW($G$2))*7 + (COLUMN()-COLUMN($G$2)) + 1)} -> 4 | I83: {=INDEX($D$2:$D$701, (ROW()-ROW($G$2))*7 + (COLUMN()-COLUMN($G$2)) + 1)} -> 7 | J83: {=INDEX($D$2:$D$701, (ROW()-ROW($G$2))*7 + (COLUMN()-COLUMN($G$2)) + 1)} -> 10 | K83: {=INDEX($D$2:$D$701, (ROW()-ROW($G$2))*7 + (COLUMN()-COLUMN($G$2)) + 1)} -> 4 | L83: {=INDEX($D$2:$D$701, (ROW()-ROW($G$2))*7 + (COLUMN()-COLUMN($G$2)) + 1)} -> 4 | M83: {=INDEX($D$2:$D$701, (ROW()-ROW($G$2))*7 + (COLUMN()-COLUMN($G$2)) + 1)} -> 5 | O83: =IF(H83=MAX(Tabelle4[[#This Row],[d32_el2_dl2_ff128-ep500]:[d64_el3_dl3_ff128-ep1000]]),1,0) -> 0 | P83: =IF(I83=MAX(Tabelle4[[#This Row],[d32_el2_dl2_ff128-ep500]:[d64_el3_dl3_ff128-ep1000]]),1,0) -> 0 | Q83: =IF(J83=MAX(Tabelle4[[#This Row],[d32_el2_dl2_ff128-ep500]:[d64_el3_dl3_ff128-ep1000]]),1,0) -> 1 | R83: =IF(K83=MAX(Tabelle4[[#This Row],[d32_el2_dl2_ff128-ep500]:[d64_el3_dl3_ff128-ep1000]]),1,0) -> 0 | S83: =IF(L83=MAX(Tabelle4[[#This Row],[d32_el2_dl2_ff128-ep500]:[d64_el3_dl3_ff128-ep1000]]),1,0) -> 0 | T83: =IF(M83=MAX(Tabelle4[[#This Row],[d32_el2_dl2_ff128-ep500]:[d64_el3_dl3_ff128-ep1000]]),1,0) -> 0 | V83: =IF(H83=MIN(Tabelle4[[#This Row],[d32_el2_dl2_ff128-ep500]:[d64_el3_dl3_ff128-ep1000]]),1,0) -> 1 | W83: =IF(I83=MIN(Tabelle4[[#This Row],[d32_el2_dl2_ff128-ep500]:[d64_el3_dl3_ff128-ep1000]]),1,0) -> 0 | X83: =IF(J83=MIN(Tabelle4[[#This Row],[d32_el2_dl2_ff128-ep500]:[d64_el3_dl3_ff128-ep1000]]),1,0) -> 0 | Y83: =IF(K83=MIN(Tabelle4[[#This Row],[d32_el2_dl2_ff128-ep500]:[d64_el3_dl3_ff128-ep1000]]),1,0) -> 1 | Z83: =IF(L83=MIN(Tabelle4[[#This Row],[d32_el2_dl2_ff128-ep500]:[d64_el3_dl3_ff128-ep1000]]),1,0) -> 1 | AA83: =IF(M83=MIN(Tabelle4[[#This Row],[d32_el2_dl2_ff128-ep500]:[d64_el3_dl3_ff128-ep1000]]),1,0) -> 0
A84: 5 | B84: d64_el2_dl2_ff128-ep1000 | C84: ['prod', 'prod', 'prod', 'prod', 'prod', 'prod', 'prod', 'prod'] | D84: 0 | E84: =D84+E77 -> 63 | G84: 83 | H84: {=INDEX($D$2:$D$701, (ROW()-ROW($G$2))*7 + (COLUMN()-COLUMN($G$2)) + 1)} -> 5 | I84: {=INDEX($D$2:$D$701, (ROW()-ROW($G$2))*7 + (COLUMN()-COLUMN($G$2)) + 1)} -> 4 | J84: {=INDEX($D$2:$D$701, (ROW()-ROW($G$2))*7 + (COLUMN()-COLUMN($G$2)) + 1)} -> 7 | K84: {=INDEX($D$2:$D$701, (ROW()-ROW($G$2))*7 + (COLUMN()-COLUMN($G$2)) + 1)} -> 7 | L84: {=INDEX($D$2:$D$701, (ROW()-ROW($G$2))*7 + (COLUMN()-COLUMN($G$2)) + 1)} -> 8 | M84: {=INDEX($D$2:$D$701, (ROW()-ROW($G$2))*7 + (COLUMN()-COLUMN($G$2)) + 1)} -> 7 | O84: =IF(H84=MAX(Tabelle4[[#This Row],[d32_el2_dl2_ff128-ep500]:[d64_el3_dl3_ff128-ep1000]]),1,0) -> 0 | P84: =IF(I84=MAX(Tabelle4[[#This Row],[d32_el2_dl2_ff128-ep500]:[d64_el3_dl3_ff128-ep1000]]),1,0) -> 0 | Q84: =IF(J84=MAX(Tabelle4[[#This Row],[d32_el2_dl2_ff128-ep500]:[d64_el3_dl3_ff128-ep1000]]),1,0) -> 0 | R84: =IF(K84=MAX(Tabelle4[[#This Row],[d32_el2_dl2_ff128-ep500]:[d64_el3_dl3_ff128-ep1000]]),1,0) -> 0 | S84: =IF(L84=MAX(Tabelle4[[#This Row],[d32_el2_dl2_ff128-ep500]:[d64_el3_dl3_ff128-ep1000]]),1,0) -> 1 | T84: =IF(M84=MAX(Tabelle4[[#This Row],[d32_el2_dl2_ff128-ep500]:[d64_el3_dl3_ff128-ep1000]]),1,0) -> 0 | V84: =IF(H84=MIN(Tabelle4[[#This Row],[d32_el2_dl2_ff128-ep500]:[d64_el3_dl3_ff128-ep1000]]),1,0) -> 0 | W84: =IF(I84=MIN(Tabelle4[[#This Row],[d32_el2_dl2_ff128-ep500]:[d64_el3_dl3_ff128-ep1000]]),1,0) -> 1 | X84: =IF(J84=MIN(Tabelle4[[#This Row],[d32_el2_dl2_ff128-ep500]:[d64_el3_dl3_ff128-ep1000]]),1,0) -> 0 | Y84: =IF(K84=MIN(Tabelle4[[#This Row],[d32_el2_dl2_ff128-ep500]:[d64_el3_dl3_ff128-ep1000]]),1,0) -> 0 | Z84: =IF(L84=MIN(Tabelle4[[#This Row],[d32_el2_dl2_ff128-ep500]:[d64_el3_dl3_ff128-ep1000]]),1,0) -> 0 | AA84: =IF(M84=MIN(Tabelle4[[#This Row],[d32_el2_dl2_ff128-ep500]:[d64_el3_dl3_ff128-ep1000]]),1,0) -> 0
A85: 6 | B85: d64_el3_dl3_ff128-ep1000 | C85: ['wie', 'prod', 'prod', 'prod', 'prod'] | D85: 0 | E85: =D85+E78 -> 65 | G85: 84 | H85: {=INDEX($D$2:$D$701, (ROW()-ROW($G$2))*7 + (COLUMN()-COLUMN($G$2)) + 1)} -> 3 | I85: {=INDEX($D$2:$D$701, (ROW()-ROW($G$2))*7 + (COLUMN()-COLUMN($G$2)) + 1)} -> 0 | J85: {=INDEX($D$2:$D$701, (ROW()-ROW($G$2))*7 + (COLUMN()-COLUMN($G$2)) + 1)} -> 2 | K85: {=INDEX($D$2:$D$701, (ROW()-ROW($G$2))*7 + (COLUMN()-COLUMN($G$2)) + 1)} -> 2 | L85: {=INDEX($D$2:$D$701, (ROW()-ROW($G$2))*7 + (COLUMN()-COLUMN($G$2)) + 1)} -> 0 | M85: {=INDEX($D$2:$D$701, (ROW()-ROW($G$2))*7 + (COLUMN()-COLUMN($G$2)) + 1)} -> 1 | O85: =IF(H85=MAX(Tabelle4[[#This Row],[d32_el2_dl2_ff128-ep500]:[d64_el3_dl3_ff128-ep1000]]),1,0) -> 1 | P85: =IF(I85=MAX(Tabelle4[[#This Row],[d32_el2_dl2_ff128-ep500]:[d64_el3_dl3_ff128-ep1000]]),1,0) -> 0 | Q85: =IF(J85=MAX(Tabelle4[[#This Row],[d32_el2_dl2_ff128-ep500]:[d64_el3_dl3_ff128-ep1000]]),1,0) -> 0 | R85: =IF(K85=MAX(Tabelle4[[#This Row],[d32_el2_dl2_ff128-ep500]:[d64_el3_dl3_ff128-ep1000]]),1,0) -> 0 | S85: =IF(L85=MAX(Tabelle4[[#This Row],[d32_el2_dl2_ff128-ep500]:[d64_el3_dl3_ff128-ep1000]]),1,0) -> 0 | T85: =IF(M85=MAX(Tabelle4[[#This Row],[d32_el2_dl2_ff128-ep500]:[d64_el3_dl3_ff128-ep1000]]),1,0) -> 0 | V85: =IF(H85=MIN(Tabelle4[[#This Row],[d32_el2_dl2_ff128-ep500]:[d64_el3_dl3_ff128-ep1000]]),1,0) -> 0 | W85: =IF(I85=MIN(Tabelle4[[#This Row],[d32_el2_dl2_ff128-ep500]:[d64_el3_dl3_ff128-ep1000]]),1,0) -> 1 | X85: =IF(J85=MIN(Tabelle4[[#This Row],[d32_el2_dl2_ff128-ep500]:[d64_el3_dl3_ff128-ep1000]]),1,0) -> 0 | Y85: =IF(K85=MIN(Tabelle4[[#This Row],[d32_el2_dl2_ff128-ep500]:[d64_el3_dl3_ff128-ep1000]]),1,0) -> 0 | Z85: =IF(L85=MIN(Tabelle4[[#This Row],[d32_el2_dl2_ff128-ep500]:[d64_el3_dl3_ff128-ep1000]]),1,0) -> 1 | AA85: =IF(M85=MIN(Tabelle4[[#This Row],[d32_el2_dl2_ff128-ep500]:[d64_el3_dl3_ff128-ep1000]]),1,0) -> 0
A86: 0 | B86: 13 | C86: Darf ich mich hier hinsetzen? | E86: =D86+E79 -> 0 | G86: 85 | H86: {=INDEX($D$2:$D$701, (ROW()-ROW($G$2))*7 + (COLUMN()-COLUMN($G$2)) + 1)} -> 8 | I86: {=INDEX($D$2:$D$701, (ROW()-ROW($G$2))*7 + (COLUMN()-COLUMN($G$2)) + 1)} -> 10 | J86: {=INDEX($D$2:$D$701, (ROW()-ROW($G$2))*7 + (COLUMN()-COLUMN($G$2)) + 1)} -> 8 | K86: {=INDEX($D$2:$D$701, (ROW()-ROW($G$2))*7 + (COLUMN()-COLUMN($G$2)) + 1)} -> 10 | L86: {=INDEX($D$2:$D$701, (ROW()-ROW($G$2))*7 + (COLUMN()-COLUMN($G$2)) + 1)} -> 8 | M86: {=INDEX($D$2:$D$701, (ROW()-ROW($G$2))*7 + (COLUMN()-COLUMN($G$2)) + 1)} -> 8 | O86: =IF(H86=MAX(Tabelle4[[#This Row],[d32_el2_dl2_ff128-ep500]:[d64_el3_dl3_ff128-ep1000]]),1,0) -> 0 | P86: =IF(I86=MAX(Tabelle4[[#This Row],[d32_el2_dl2_ff128-ep500]:[d64_el3_dl3_ff128-ep1000]]),1,0) -> 1 | Q86: =IF(J86=MAX(Tabelle4[[#This Row],[d32_el2_dl2_ff128-ep500]:[d64_el3_dl3_ff128-ep1000]]),1,0) -> 0 | R86: =IF(K86=MAX(Tabelle4[[#This Row],[d32_el2_dl2_ff128-ep500]:[d64_el3_dl3_ff128-ep1000]]),1,0) -> 1 | S86: =IF(L86=MAX(Tabelle4[[#This Row],[d32_el2_dl2_ff128-ep500]:[d64_el3_dl3_ff128-ep1000]]),1,0) -> 0 | T86: =IF(M86=MAX(Tabelle4[[#This Row],[d32_el2_dl2_ff128-ep500]:[d64_el3_dl3_ff128-ep1000]]),1,0) -> 0 | V86: =IF(H86=MIN(Tabelle4[[#This Row],[d32_el2_dl2_ff128-ep500]:[d64_el3_dl3_ff128-ep1000]]),1,0) -> 1 | W86: =IF(I86=MIN(Tabelle4[[#This Row],[d32_el2_dl2_ff128-ep500]:[d64_el3_dl3_ff128-ep1000]]),1,0) -> 0 | X86: =IF(J86=MIN(Tabelle4[[#This Row],[d32_el2_dl2_ff128-ep500]:[d64_el3_dl3_ff128-ep1000]]),1,0) -> 1 | Y86: =IF(K86=MIN(Tabelle4[[#This Row],[d32_el2_dl2_ff128-ep500]:[d64_el3_dl3_ff128-ep1000]]),1,0) -> 0 | Z86: =IF(L86=MIN(Tabelle4[[#This Row],[d32_el2_dl2_ff128-ep500]:[d64_el3_dl3_ff128-ep1000]]),1,0) -> 1 | AA86: =IF(M86=MIN(Tabelle4[[#This Row],[d32_el2_dl2_ff128-ep500]:[d64_el3_dl3_ff128-ep1000]]),1,0) -> 1
A87: 1 | B87: d32_el2_dl2_ff128-ep500 | C87: ['ich', 'sitzen'] | D87: 10 | E87: =D87+E80 -> 74 | G87: 86 | H87: {=INDEX($D$2:$D$701, (ROW()-ROW($G$2))*7 + (COLUMN()-COLUMN($G$2)) + 1)} -> 8 | I87: {=INDEX($D$2:$D$701, (ROW()-ROW($G$2))*7 + (COLUMN()-COLUMN($G$2)) + 1)} -> 4 | J87: {=INDEX($D$2:$D$701, (ROW()-ROW($G$2))*7 + (COLUMN()-COLUMN($G$2)) + 1)} -> 10 | K87: {=INDEX($D$2:$D$701, (ROW()-ROW($G$2))*7 + (COLUMN()-COLUMN($G$2)) + 1)} -> 10 | L87: {=INDEX($D$2:$D$701, (ROW()-ROW($G$2))*7 + (COLUMN()-COLUMN($G$2)) + 1)} -> 0 | M87: {=INDEX($D$2:$D$701, (ROW()-ROW($G$2))*7 + (COLUMN()-COLUMN($G$2)) + 1)} -> 6 | O87: =IF(H87=MAX(Tabelle4[[#This Row],[d32_el2_dl2_ff128-ep500]:[d64_el3_dl3_ff128-ep1000]]),1,0) -> 0 | P87: =IF(I87=MAX(Tabelle4[[#This Row],[d32_el2_dl2_ff128-ep500]:[d64_el3_dl3_ff128-ep1000]]),1,0) -> 0 | Q87: =IF(J87=MAX(Tabelle4[[#This Row],[d32_el2_dl2_ff128-ep500]:[d64_el3_dl3_ff128-ep1000]]),1,0) -> 1 | R87: =IF(K87=MAX(Tabelle4[[#This Row],[d32_el2_dl2_ff128-ep500]:[d64_el3_dl3_ff128-ep1000]]),1,0) -> 1 | S87: =IF(L87=MAX(Tabelle4[[#This Row],[d32_el2_dl2_ff128-ep500]:[d64_el3_dl3_ff128-ep1000]]),1,0) -> 0 | T87: =IF(M87=MAX(Tabelle4[[#This Row],[d32_el2_dl2_ff128-ep500]:[d64_el3_dl3_ff128-ep1000]]),1,0) -> 0 | V87: =IF(H87=MIN(Tabelle4[[#This Row],[d32_el2_dl2_ff128-ep500]:[d64_el3_dl3_ff128-ep1000]]),1,0) -> 0 | W87: =IF(I87=MIN(Tabelle4[[#This Row],[d32_el2_dl2_ff128-ep500]:[d64_el3_dl3_ff128-ep1000]]),1,0) -> 0 | X87: =IF(J87=MIN(Tabelle4[[#This Row],[d32_el2_dl2_ff128-ep500]:[d64_el3_dl3_ff128-ep1000]]),1,0) -> 0 | Y87: =IF(K87=MIN(Tabelle4[[#This Row],[d32_el2_dl2_ff128-ep500]:[d64_el3_dl3_ff128-ep1000]]),1,0) -> 0 | Z87: =IF(L87=MIN(Tabelle4[[#This Row],[d32_el2_dl2_ff128-ep500]:[d64_el3_dl3_ff128-ep1000]]),1,0) -> 1 | AA87: =IF(M87=MIN(Tabelle4[[#This Row],[d32_el2_dl2_ff128-ep500]:[d64_el3_dl3_ff128-ep1000]]),1,0) -> 0
A88: 2 | B88: d64_el1_dl1_ff64-ep1000 | C88: ['ich', 'nahe', 'sitzen'] | D88: 10 | E88: =D88+E81 -> 68 | G88: 87 | H88: {=INDEX($D$2:$D$701, (ROW()-ROW($G$2))*7 + (COLUMN()-COLUMN($G$2)) + 1)} -> 9 | I88: {=INDEX($D$2:$D$701, (ROW()-ROW($G$2))*7 + (COLUMN()-COLUMN($G$2)) + 1)} -> 9 | J88: {=INDEX($D$2:$D$701, (ROW()-ROW($G$2))*7 + (COLUMN()-COLUMN($G$2)) + 1)} -> 9 | K88: {=INDEX($D$2:$D$701, (ROW()-ROW($G$2))*7 + (COLUMN()-COLUMN($G$2)) + 1)} -> 9 | L88: {=INDEX($D$2:$D$701, (ROW()-ROW($G$2))*7 + (COLUMN()-COLUMN($G$2)) + 1)} -> 8 | M88: {=INDEX($D$2:$D$701, (ROW()-ROW($G$2))*7 + (COLUMN()-COLUMN($G$2)) + 1)} -> 10 | O88: =IF(H88=MAX(Tabelle4[[#This Row],[d32_el2_dl2_ff128-ep500]:[d64_el3_dl3_ff128-ep1000]]),1,0) -> 0 | P88: =IF(I88=MAX(Tabelle4[[#This Row],[d32_el2_dl2_ff128-ep500]:[d64_el3_dl3_ff128-ep1000]]),1,0) -> 0 | Q88: =IF(J88=MAX(Tabelle4[[#This Row],[d32_el2_dl2_ff128-ep500]:[d64_el3_dl3_ff128-ep1000]]),1,0) -> 0 | R88: =IF(K88=MAX(Tabelle4[[#This Row],[d32_el2_dl2_ff128-ep500]:[d64_el3_dl3_ff128-ep1000]]),1,0) -> 0 | S88: =IF(L88=MAX(Tabelle4[[#This Row],[d32_el2_dl2_ff128-ep500]:[d64_el3_dl3_ff128-ep1000]]),1,0) -> 0 | T88: =IF(M88=MAX(Tabelle4[[#This Row],[d32_el2_dl2_ff128-ep500]:[d64_el3_dl3_ff128-ep1000]]),1,0) -> 1 | V88: =IF(H88=MIN(Tabelle4[[#This Row],[d32_el2_dl2_ff128-ep500]:[d64_el3_dl3_ff128-ep1000]]),1,0) -> 0 | W88: =IF(I88=MIN(Tabelle4[[#This Row],[d32_el2_dl2_ff128-ep500]:[d64_el3_dl3_ff128-ep1000]]),1,0) -> 0 | X88: =IF(J88=MIN(Tabelle4[[#This Row],[d32_el2_dl2_ff128-ep500]:[d64_el3_dl3_ff128-ep1000]]),1,0) -> 0 | Y88: =IF(K88=MIN(Tabelle4[[#This Row],[d32_el2_dl2_ff128-ep500]:[d64_el3_dl3_ff128-ep1000]]),1,0) -> 0 | Z88: =IF(L88=MIN(Tabelle4[[#This Row],[d32_el2_dl2_ff128-ep500]:[d64_el3_dl3_ff128-ep1000]]),1,0) -> 1 | AA88: =IF(M88=MIN(Tabelle4[[#This Row],[d32_el2_dl2_ff128-ep500]:[d64_el3_dl3_ff128-ep1000]]),1,0) -> 0
A89: 3 | B89: d64_el2_dl2_ff64-ep500 | C89: ['ich', 'muss', 'ich', 'sitzen'] | D89: 9 | E89: =D89+E82 -> 65 | G89: 88 | H89: {=INDEX($D$2:$D$701, (ROW()-ROW($G$2))*7 + (COLUMN()-COLUMN($G$2)) + 1)} -> 6 | I89: {=INDEX($D$2:$D$701, (ROW()-ROW($G$2))*7 + (COLUMN()-COLUMN($G$2)) + 1)} -> 10 | J89: {=INDEX($D$2:$D$701, (ROW()-ROW($G$2))*7 + (COLUMN()-COLUMN($G$2)) + 1)} -> 4 | K89: {=INDEX($D$2:$D$701, (ROW()-ROW($G$2))*7 + (COLUMN()-COLUMN($G$2)) + 1)} -> 5 | L89: {=INDEX($D$2:$D$701, (ROW()-ROW($G$2))*7 + (COLUMN()-COLUMN($G$2)) + 1)} -> 10 | M89: {=INDEX($D$2:$D$701, (ROW()-ROW($G$2))*7 + (COLUMN()-COLUMN($G$2)) + 1)} -> 10 | O89: =IF(H89=MAX(Tabelle4[[#This Row],[d32_el2_dl2_ff128-ep500]:[d64_el3_dl3_ff128-ep1000]]),1,0) -> 0 | P89: =IF(I89=MAX(Tabelle4[[#This Row],[d32_el2_dl2_ff128-ep500]:[d64_el3_dl3_ff128-ep1000]]),1,0) -> 1 | Q89: =IF(J89=MAX(Tabelle4[[#This Row],[d32_el2_dl2_ff128-ep500]:[d64_el3_dl3_ff128-ep1000]]),1,0) -> 0 | R89: =IF(K89=MAX(Tabelle4[[#This Row],[d32_el2_dl2_ff128-ep500]:[d64_el3_dl3_ff128-ep1000]]),1,0) -> 0 | S89: =IF(L89=MAX(Tabelle4[[#This Row],[d32_el2_dl2_ff128-ep500]:[d64_el3_dl3_ff128-ep1000]]),1,0) -> 1 | T89: =IF(M89=MAX(Tabelle4[[#This Row],[d32_el2_dl2_ff128-ep500]:[d64_el3_dl3_ff128-ep1000]]),1,0) -> 1 | V89: =IF(H89=MIN(Tabelle4[[#This Row],[d32_el2_dl2_ff128-ep500]:[d64_el3_dl3_ff128-ep1000]]),1,0) -> 0 | W89: =IF(I89=MIN(Tabelle4[[#This Row],[d32_el2_dl2_ff128-ep500]:[d64_el3_dl3_ff128-ep1000]]),1,0) -> 0 | X89: =IF(J89=MIN(Tabelle4[[#This Row],[d32_el2_dl2_ff128-ep500]:[d64_el3_dl3_ff128-ep1000]]),1,0) -> 1 | Y89: =IF(K89=MIN(Tabelle4[[#This Row],[d32_el2_dl2_ff128-ep500]:[d64_el3_dl3_ff128-ep1000]]),1,0) -> 0 | Z89: =IF(L89=MIN(Tabelle4[[#This Row],[d32_el2_dl2_ff128-ep500]:[d64_el3_dl3_ff128-ep1000]]),1,0) -> 0 | AA89: =IF(M89=MIN(Tabelle4[[#This Row],[d32_el2_dl2_ff128-ep500]:[d64_el3_dl3_ff128-ep1000]]),1,0) -> 0
A90: 4 | B90: d64_el2_dl2_ff64-ep1000 | C90: ['muss', 'ich', 'folgen'] | D90: 3 | E90: =D90+E83 -> 60 | G90: 89 | H90: {=INDEX($D$2:$D$701, (ROW()-ROW($G$2))*7 + (COLUMN()-COLUMN($G$2)) + 1)} -> 10 | I90: {=INDEX($D$2:$D$701, (ROW()-ROW($G$2))*7 + (COLUMN()-COLUMN($G$2)) + 1)} -> 10 | J90: {=INDEX($D$2:$D$701, (ROW()-ROW($G$2))*7 + (COLUMN()-COLUMN($G$2)) + 1)} -> 10 | K90: {=INDEX($D$2:$D$701, (ROW()-ROW($G$2))*7 + (COLUMN()-COLUMN($G$2)) + 1)} -> 10 | L90: {=INDEX($D$2:$D$701, (ROW()-ROW($G$2))*7 + (COLUMN()-COLUMN($G$2)) + 1)} -> 10 | M90: {=INDEX($D$2:$D$701, (ROW()-ROW($G$2))*7 + (COLUMN()-COLUMN($G$2)) + 1)} -> 10 | O90: =IF(H90=MAX(Tabelle4[[#This Row],[d32_el2_dl2_ff128-ep500]:[d64_el3_dl3_ff128-ep1000]]),1,0) -> 1 | P90: =IF(I90=MAX(Tabelle4[[#This Row],[d32_el2_dl2_ff128-ep500]:[d64_el3_dl3_ff128-ep1000]]),1,0) -> 1 | Q90: =IF(J90=MAX(Tabelle4[[#This Row],[d32_el2_dl2_ff128-ep500]:[d64_el3_dl3_ff128-ep1000]]),1,0) -> 1 | R90: =IF(K90=MAX(Tabelle4[[#This Row],[d32_el2_dl2_ff128-ep500]:[d64_el3_dl3_ff128-ep1000]]),1,0) -> 1 | S90: =IF(L90=MAX(Tabelle4[[#This Row],[d32_el2_dl2_ff128-ep500]:[d64_el3_dl3_ff128-ep1000]]),1,0) -> 1 | T90: =IF(M90=MAX(Tabelle4[[#This Row],[d32_el2_dl2_ff128-ep500]:[d64_el3_dl3_ff128-ep1000]]),1,0) -> 1 | V90: =IF(H90=MIN(Tabelle4[[#This Row],[d32_el2_dl2_ff128-ep500]:[d64_el3_dl3_ff128-ep1000]]),1,0) -> 1 | W90: =IF(I90=MIN(Tabelle4[[#This Row],[d32_el2_dl2_ff128-ep500]:[d64_el3_dl3_ff128-ep1000]]),1,0) -> 1 | X90: =IF(J90=MIN(Tabelle4[[#This Row],[d32_el2_dl2_ff128-ep500]:[d64_el3_dl3_ff128-ep1000]]),1,0) -> 1 | Y90: =IF(K90=MIN(Tabelle4[[#This Row],[d32_el2_dl2_ff128-ep500]:[d64_el3_dl3_ff128-ep1000]]),1,0) -> 1 | Z90: =IF(L90=MIN(Tabelle4[[#This Row],[d32_el2_dl2_ff128-ep500]:[d64_el3_dl3_ff128-ep1000]]),1,0) -> 1 | AA90: =IF(M90=MIN(Tabelle4[[#This Row],[d32_el2_dl2_ff128-ep500]:[d64_el3_dl3_ff128-ep1000]]),1,0) -> 1
A91: 5 | B91: d64_el2_dl2_ff128-ep1000 | C91: ['sitzen', 'ich', 'sitzen', 'dorthin gehen', 'sitzen'] | D91: 9 | E91: =D91+E84 -> 72 | G91: 90 | H91: {=INDEX($D$2:$D$701, (ROW()-ROW($G$2))*7 + (COLUMN()-COLUMN($G$2)) + 1)} -> 4 | I91: {=INDEX($D$2:$D$701, (ROW()-ROW($G$2))*7 + (COLUMN()-COLUMN($G$2)) + 1)} -> 9 | J91: {=INDEX($D$2:$D$701, (ROW()-ROW($G$2))*7 + (COLUMN()-COLUMN($G$2)) + 1)} -> 7 | K91: {=INDEX($D$2:$D$701, (ROW()-ROW($G$2))*7 + (COLUMN()-COLUMN($G$2)) + 1)} -> 7 | L91: {=INDEX($D$2:$D$701, (ROW()-ROW($G$2))*7 + (COLUMN()-COLUMN($G$2)) + 1)} -> 6 | M91: {=INDEX($D$2:$D$701, (ROW()-ROW($G$2))*7 + (COLUMN()-COLUMN($G$2)) + 1)} -> 2 | O91: =IF(H91=MAX(Tabelle4[[#This Row],[d32_el2_dl2_ff128-ep500]:[d64_el3_dl3_ff128-ep1000]]),1,0) -> 0 | P91: =IF(I91=MAX(Tabelle4[[#This Row],[d32_el2_dl2_ff128-ep500]:[d64_el3_dl3_ff128-ep1000]]),1,0) -> 1 | Q91: =IF(J91=MAX(Tabelle4[[#This Row],[d32_el2_dl2_ff128-ep500]:[d64_el3_dl3_ff128-ep1000]]),1,0) -> 0 | R91: =IF(K91=MAX(Tabelle4[[#This Row],[d32_el2_dl2_ff128-ep500]:[d64_el3_dl3_ff128-ep1000]]),1,0) -> 0 | S91: =IF(L91=MAX(Tabelle4[[#This Row],[d32_el2_dl2_ff128-ep500]:[d64_el3_dl3_ff128-ep1000]]),1,0) -> 0 | T91: =IF(M91=MAX(Tabelle4[[#This Row],[d32_el2_dl2_ff128-ep500]:[d64_el3_dl3_ff128-ep1000]]),1,0) -> 0 | V91: =IF(H91=MIN(Tabelle4[[#This Row],[d32_el2_dl2_ff128-ep500]:[d64_el3_dl3_ff128-ep1000]]),1,0) -> 0 | W91: =IF(I91=MIN(Tabelle4[[#This Row],[d32_el2_dl2_ff128-ep500]:[d64_el3_dl3_ff128-ep1000]]),1,0) -> 0 | X91: =IF(J91=MIN(Tabelle4[[#This Row],[d32_el2_dl2_ff128-ep500]:[d64_el3_dl3_ff128-ep1000]]),1,0) -> 0 | Y91: =IF(K91=MIN(Tabelle4[[#This Row],[d32_el2_dl2_ff128-ep500]:[d64_el3_dl3_ff128-ep1000]]),1,0) -> 0 | Z91: =IF(L91=MIN(Tabelle4[[#This Row],[d32_el2_dl2_ff128-ep500]:[d64_el3_dl3_ff128-ep1000]]),1,0) -> 0 | AA91: =IF(M91=MIN(Tabelle4[[#This Row],[d32_el2_dl2_ff128-ep500]:[d64_el3_dl3_ff128-ep1000]]),1,0) -> 1
A92: 6 | B92: d64_el3_dl3_ff128-ep1000 | C92: ['ich', 'hier', 'sitzen', 'sitzen', 'sitzen'] | D92: 9 | E92: =D92+E85 -> 74 | G92: 91 | H92: {=INDEX($D$2:$D$701, (ROW()-ROW($G$2))*7 + (COLUMN()-COLUMN($G$2)) + 1)} -> 9 | I92: {=INDEX($D$2:$D$701, (ROW()-ROW($G$2))*7 + (COLUMN()-COLUMN($G$2)) + 1)} -> 9 | J92: {=INDEX($D$2:$D$701, (ROW()-ROW($G$2))*7 + (COLUMN()-COLUMN($G$2)) + 1)} -> 10 | K92: {=INDEX($D$2:$D$701, (ROW()-ROW($G$2))*7 + (COLUMN()-COLUMN($G$2)) + 1)} -> 10 | L92: {=INDEX($D$2:$D$701, (ROW()-ROW($G$2))*7 + (COLUMN()-COLUMN($G$2)) + 1)} -> 7 | M92: {=INDEX($D$2:$D$701, (ROW()-ROW($G$2))*7 + (COLUMN()-COLUMN($G$2)) + 1)} -> 1 | O92: =IF(H92=MAX(Tabelle4[[#This Row],[d32_el2_dl2_ff128-ep500]:[d64_el3_dl3_ff128-ep1000]]),1,0) -> 0 | P92: =IF(I92=MAX(Tabelle4[[#This Row],[d32_el2_dl2_ff128-ep500]:[d64_el3_dl3_ff128-ep1000]]),1,0) -> 0 | Q92: =IF(J92=MAX(Tabelle4[[#This Row],[d32_el2_dl2_ff128-ep500]:[d64_el3_dl3_ff128-ep1000]]),1,0) -> 1 | R92: =IF(K92=MAX(Tabelle4[[#This Row],[d32_el2_dl2_ff128-ep500]:[d64_el3_dl3_ff128-ep1000]]),1,0) -> 1 | S92: =IF(L92=MAX(Tabelle4[[#This Row],[d32_el2_dl2_ff128-ep500]:[d64_el3_dl3_ff128-ep1000]]),1,0) -> 0 | T92: =IF(M92=MAX(Tabelle4[[#This Row],[d32_el2_dl2_ff128-ep500]:[d64_el3_dl3_ff128-ep1000]]),1,0) -> 0 | V92: =IF(H92=MIN(Tabelle4[[#This Row],[d32_el2_dl2_ff128-ep500]:[d64_el3_dl3_ff128-ep1000]]),1,0) -> 0 | W92: =IF(I92=MIN(Tabelle4[[#This Row],[d32_el2_dl2_ff128-ep500]:[d64_el3_dl3_ff128-ep1000]]),1,0) -> 0 | X92: =IF(J92=MIN(Tabelle4[[#This Row],[d32_el2_dl2_ff128-ep500]:[d64_el3_dl3_ff128-ep1000]]),1,0) -> 0 | Y92: =IF(K92=MIN(Tabelle4[[#This Row],[d32_el2_dl2_ff128-ep500]:[d64_el3_dl3_ff128-ep1000]]),1,0) -> 0 | Z92: =IF(L92=MIN(Tabelle4[[#This Row],[d32_el2_dl2_ff128-ep500]:[d64_el3_dl3_ff128-ep1000]]),1,0) -> 0 | AA92: =IF(M92=MIN(Tabelle4[[#This Row],[d32_el2_dl2_ff128-ep500]:[d64_el3_dl3_ff128-ep1000]]),1,0) -> 1
A93: 0 | B93: 14 | C93: Ich hÃ¤tte gerne einen Kaffee. | E93: =D93+E86 -> 0 | G93: 92 | H93: {=INDEX($D$2:$D$701, (ROW()-ROW($G$2))*7 + (COLUMN()-COLUMN($G$2)) + 1)} -> 9 | I93: {=INDEX($D$2:$D$701, (ROW()-ROW($G$2))*7 + (COLUMN()-COLUMN($G$2)) + 1)} -> 9 | J93: {=INDEX($D$2:$D$701, (ROW()-ROW($G$2))*7 + (COLUMN()-COLUMN($G$2)) + 1)} -> 10 | K93: {=INDEX($D$2:$D$701, (ROW()-ROW($G$2))*7 + (COLUMN()-COLUMN($G$2)) + 1)} -> 10 | L93: {=INDEX($D$2:$D$701, (ROW()-ROW($G$2))*7 + (COLUMN()-COLUMN($G$2)) + 1)} -> 3 | M93: {=INDEX($D$2:$D$701, (ROW()-ROW($G$2))*7 + (COLUMN()-COLUMN($G$2)) + 1)} -> 8 | O93: =IF(H93=MAX(Tabelle4[[#This Row],[d32_el2_dl2_ff128-ep500]:[d64_el3_dl3_ff128-ep1000]]),1,0) -> 0 | P93: =IF(I93=MAX(Tabelle4[[#This Row],[d32_el2_dl2_ff128-ep500]:[d64_el3_dl3_ff128-ep1000]]),1,0) -> 0 | Q93: =IF(J93=MAX(Tabelle4[[#This Row],[d32_el2_dl2_ff128-ep500]:[d64_el3_dl3_ff128-ep1000]]),1,0) -> 1 | R93: =IF(K93=MAX(Tabelle4[[#This Row],[d32_el2_dl2_ff128-ep500]:[d64_el3_dl3_ff128-ep1000]]),1,0) -> 1 | S93: =IF(L93=MAX(Tabelle4[[#This Row],[d32_el2_dl2_ff128-ep500]:[d64_el3_dl3_ff128-ep1000]]),1,0) -> 0 | T93: =IF(M93=MAX(Tabelle4[[#This Row],[d32_el2_dl2_ff128-ep500]:[d64_el3_dl3_ff128-ep1000]]),1,0) -> 0 | V93: =IF(H93=MIN(Tabelle4[[#This Row],[d32_el2_dl2_ff128-ep500]:[d64_el3_dl3_ff128-ep1000]]),1,0) -> 0 | W93: =IF(I93=MIN(Tabelle4[[#This Row],[d32_el2_dl2_ff128-ep500]:[d64_el3_dl3_ff128-ep1000]]),1,0) -> 0 | X93: =IF(J93=MIN(Tabelle4[[#This Row],[d32_el2_dl2_ff128-ep500]:[d64_el3_dl3_ff128-ep1000]]),1,0) -> 0 | Y93: =IF(K93=MIN(Tabelle4[[#This Row],[d32_el2_dl2_ff128-ep500]:[d64_el3_dl3_ff128-ep1000]]),1,0) -> 0 | Z93: =IF(L93=MIN(Tabelle4[[#This Row],[d32_el2_dl2_ff128-ep500]:[d64_el3_dl3_ff128-ep1000]]),1,0) -> 1 | AA93: =IF(M93=MIN(Tabelle4[[#This Row],[d32_el2_dl2_ff128-ep500]:[d64_el3_dl3_ff128-ep1000]]),1,0) -> 0
A94: 1 | B94: d32_el2_dl2_ff128-ep500 | C94: ['ich', 'kaufen', 'ich', 'kaffee'] | D94: 8 | E94: =D94+E87 -> 82 | G94: 93 | H94: {=INDEX($D$2:$D$701, (ROW()-ROW($G$2))*7 + (COLUMN()-COLUMN($G$2)) + 1)} -> 7 | I94: {=INDEX($D$2:$D$701, (ROW()-ROW($G$2))*7 + (COLUMN()-COLUMN($G$2)) + 1)} -> 7 | J94: {=INDEX($D$2:$D$701, (ROW()-ROW($G$2))*7 + (COLUMN()-COLUMN($G$2)) + 1)} -> 7 | K94: {=INDEX($D$2:$D$701, (ROW()-ROW($G$2))*7 + (COLUMN()-COLUMN($G$2)) + 1)} -> 8 | L94: {=INDEX($D$2:$D$701, (ROW()-ROW($G$2))*7 + (COLUMN()-COLUMN($G$2)) + 1)} -> 5 | M94: {=INDEX($D$2:$D$701, (ROW()-ROW($G$2))*7 + (COLUMN()-COLUMN($G$2)) + 1)} -> 10 | O94: =IF(H94=MAX(Tabelle4[[#This Row],[d32_el2_dl2_ff128-ep500]:[d64_el3_dl3_ff128-ep1000]]),1,0) -> 0 | P94: =IF(I94=MAX(Tabelle4[[#This Row],[d32_el2_dl2_ff128-ep500]:[d64_el3_dl3_ff128-ep1000]]),1,0) -> 0 | Q94: =IF(J94=MAX(Tabelle4[[#This Row],[d32_el2_dl2_ff128-ep500]:[d64_el3_dl3_ff128-ep1000]]),1,0) -> 0 | R94: =IF(K94=MAX(Tabelle4[[#This Row],[d32_el2_dl2_ff128-ep500]:[d64_el3_dl3_ff128-ep1000]]),1,0) -> 0 | S94: =IF(L94=MAX(Tabelle4[[#This Row],[d32_el2_dl2_ff128-ep500]:[d64_el3_dl3_ff128-ep1000]]),1,0) -> 0 | T94: =IF(M94=MAX(Tabelle4[[#This Row],[d32_el2_dl2_ff128-ep500]:[d64_el3_dl3_ff128-ep1000]]),1,0) -> 1 | V94: =IF(H94=MIN(Tabelle4[[#This Row],[d32_el2_dl2_ff128-ep500]:[d64_el3_dl3_ff128-ep1000]]),1,0) -> 0 | W94: =IF(I94=MIN(Tabelle4[[#This Row],[d32_el2_dl2_ff128-ep500]:[d64_el3_dl3_ff128-ep1000]]),1,0) -> 0 | X94: =IF(J94=MIN(Tabelle4[[#This Row],[d32_el2_dl2_ff128-ep500]:[d64_el3_dl3_ff128-ep1000]]),1,0) -> 0 | Y94: =IF(K94=MIN(Tabelle4[[#This Row],[d32_el2_dl2_ff128-ep500]:[d64_el3_dl3_ff128-ep1000]]),1,0) -> 0 | Z94: =IF(L94=MIN(Tabelle4[[#This Row],[d32_el2_dl2_ff128-ep500]:[d64_el3_dl3_ff128-ep1000]]),1,0) -> 1 | AA94: =IF(M94=MIN(Tabelle4[[#This Row],[d32_el2_dl2_ff128-ep500]:[d64_el3_dl3_ff128-ep1000]]),1,0) -> 0
A95: 2 | B95: d64_el1_dl1_ff64-ep1000 | C95: ['ich', 'gern', 'ich', 'kaffee'] | D95: 10 | E95: =D95+E88 -> 78 | G95: 94 | H95: {=INDEX($D$2:$D$701, (ROW()-ROW($G$2))*7 + (COLUMN()-COLUMN($G$2)) + 1)} -> 2 | I95: {=INDEX($D$2:$D$701, (ROW()-ROW($G$2))*7 + (COLUMN()-COLUMN($G$2)) + 1)} -> 7 | J95: {=INDEX($D$2:$D$701, (ROW()-ROW($G$2))*7 + (COLUMN()-COLUMN($G$2)) + 1)} -> 6 | K95: {=INDEX($D$2:$D$701, (ROW()-ROW($G$2))*7 + (COLUMN()-COLUMN($G$2)) + 1)} -> 6 | L95: {=INDEX($D$2:$D$701, (ROW()-ROW($G$2))*7 + (COLUMN()-COLUMN($G$2)) + 1)} -> 5 | M95: {=INDEX($D$2:$D$701, (ROW()-ROW($G$2))*7 + (COLUMN()-COLUMN($G$2)) + 1)} -> 5 | O95: =IF(H95=MAX(Tabelle4[[#This Row],[d32_el2_dl2_ff128-ep500]:[d64_el3_dl3_ff128-ep1000]]),1,0) -> 0 | P95: =IF(I95=MAX(Tabelle4[[#This Row],[d32_el2_dl2_ff128-ep500]:[d64_el3_dl3_ff128-ep1000]]),1,0) -> 1 | Q95: =IF(J95=MAX(Tabelle4[[#This Row],[d32_el2_dl2_ff128-ep500]:[d64_el3_dl3_ff128-ep1000]]),1,0) -> 0 | R95: =IF(K95=MAX(Tabelle4[[#This Row],[d32_el2_dl2_ff128-ep500]:[d64_el3_dl3_ff128-ep1000]]),1,0) -> 0 | S95: =IF(L95=MAX(Tabelle4[[#This Row],[d32_el2_dl2_ff128-ep500]:[d64_el3_dl3_ff128-ep1000]]),1,0) -> 0 | T95: =IF(M95=MAX(Tabelle4[[#This Row],[d32_el2_dl2_ff128-ep500]:[d64_el3_dl3_ff128-ep1000]]),1,0) -> 0 | V95: =IF(H95=MIN(Tabelle4[[#This Row],[d32_el2_dl2_ff128-ep500]:[d64_el3_dl3_ff128-ep1000]]),1,0) -> 1 | W95: =IF(I95=MIN(Tabelle4[[#This Row],[d32_el2_dl2_ff128-ep500]:[d64_el3_dl3_ff128-ep1000]]),1,0) -> 0 | X95: =IF(J95=MIN(Tabelle4[[#This Row],[d32_el2_dl2_ff128-ep500]:[d64_el3_dl3_ff128-ep1000]]),1,0) -> 0 | Y95: =IF(K95=MIN(Tabelle4[[#This Row],[d32_el2_dl2_ff128-ep500]:[d64_el3_dl3_ff128-ep1000]]),1,0) -> 0 | Z95: =IF(L95=MIN(Tabelle4[[#This Row],[d32_el2_dl2_ff128-ep500]:[d64_el3_dl3_ff128-ep1000]]),1,0) -> 0 | AA95: =IF(M95=MIN(Tabelle4[[#This Row],[d32_el2_dl2_ff128-ep500]:[d64_el3_dl3_ff128-ep1000]]),1,0) -> 0
A96: 3 | B96: d64_el2_dl2_ff64-ep500 | C96: ['ich', 'etwas lieben', 'bild', 'bekommen'] | D96: 5 | E96: =D96+E89 -> 70 | G96: 95 | H96: {=INDEX($D$2:$D$701, (ROW()-ROW($G$2))*7 + (COLUMN()-COLUMN($G$2)) + 1)} -> 7 | I96: {=INDEX($D$2:$D$701, (ROW()-ROW($G$2))*7 + (COLUMN()-COLUMN($G$2)) + 1)} -> 6 | J96: {=INDEX($D$2:$D$701, (ROW()-ROW($G$2))*7 + (COLUMN()-COLUMN($G$2)) + 1)} -> 5 | K96: {=INDEX($D$2:$D$701, (ROW()-ROW($G$2))*7 + (COLUMN()-COLUMN($G$2)) + 1)} -> 7 | L96: {=INDEX($D$2:$D$701, (ROW()-ROW($G$2))*7 + (COLUMN()-COLUMN($G$2)) + 1)} -> 4 | M96: {=INDEX($D$2:$D$701, (ROW()-ROW($G$2))*7 + (COLUMN()-COLUMN($G$2)) + 1)} -> 6 | O96: =IF(H96=MAX(Tabelle4[[#This Row],[d32_el2_dl2_ff128-ep500]:[d64_el3_dl3_ff128-ep1000]]),1,0) -> 1 | P96: =IF(I96=MAX(Tabelle4[[#This Row],[d32_el2_dl2_ff128-ep500]:[d64_el3_dl3_ff128-ep1000]]),1,0) -> 0 | Q96: =IF(J96=MAX(Tabelle4[[#This Row],[d32_el2_dl2_ff128-ep500]:[d64_el3_dl3_ff128-ep1000]]),1,0) -> 0 | R96: =IF(K96=MAX(Tabelle4[[#This Row],[d32_el2_dl2_ff128-ep500]:[d64_el3_dl3_ff128-ep1000]]),1,0) -> 1 | S96: =IF(L96=MAX(Tabelle4[[#This Row],[d32_el2_dl2_ff128-ep500]:[d64_el3_dl3_ff128-ep1000]]),1,0) -> 0 | T96: =IF(M96=MAX(Tabelle4[[#This Row],[d32_el2_dl2_ff128-ep500]:[d64_el3_dl3_ff128-ep1000]]),1,0) -> 0 | V96: =IF(H96=MIN(Tabelle4[[#This Row],[d32_el2_dl2_ff128-ep500]:[d64_el3_dl3_ff128-ep1000]]),1,0) -> 0 | W96: =IF(I96=MIN(Tabelle4[[#This Row],[d32_el2_dl2_ff128-ep500]:[d64_el3_dl3_ff128-ep1000]]),1,0) -> 0 | X96: =IF(J96=MIN(Tabelle4[[#This Row],[d32_el2_dl2_ff128-ep500]:[d64_el3_dl3_ff128-ep1000]]),1,0) -> 0 | Y96: =IF(K96=MIN(Tabelle4[[#This Row],[d32_el2_dl2_ff128-ep500]:[d64_el3_dl3_ff128-ep1000]]),1,0) -> 0 | Z96: =IF(L96=MIN(Tabelle4[[#This Row],[d32_el2_dl2_ff128-ep500]:[d64_el3_dl3_ff128-ep1000]]),1,0) -> 1 | AA96: =IF(M96=MIN(Tabelle4[[#This Row],[d32_el2_dl2_ff128-ep500]:[d64_el3_dl3_ff128-ep1000]]),1,0) -> 0
A97: 4 | B97: d64_el2_dl2_ff64-ep1000 | C97: ['ich', 'selbst', 'auch', 'kaffee', 'schmal dünn'] | D97: 6 | E97: =D97+E90 -> 66 | G97: 96 | H97: {=INDEX($D$2:$D$701, (ROW()-ROW($G$2))*7 + (COLUMN()-COLUMN($G$2)) + 1)} -> 7 | I97: {=INDEX($D$2:$D$701, (ROW()-ROW($G$2))*7 + (COLUMN()-COLUMN($G$2)) + 1)} -> 9 | J97: {=INDEX($D$2:$D$701, (ROW()-ROW($G$2))*7 + (COLUMN()-COLUMN($G$2)) + 1)} -> 9 | K97: {=INDEX($D$2:$D$701, (ROW()-ROW($G$2))*7 + (COLUMN()-COLUMN($G$2)) + 1)} -> 9 | L97: {=INDEX($D$2:$D$701, (ROW()-ROW($G$2))*7 + (COLUMN()-COLUMN($G$2)) + 1)} -> 9 | M97: {=INDEX($D$2:$D$701, (ROW()-ROW($G$2))*7 + (COLUMN()-COLUMN($G$2)) + 1)} -> 9 | O97: =IF(H97=MAX(Tabelle4[[#This Row],[d32_el2_dl2_ff128-ep500]:[d64_el3_dl3_ff128-ep1000]]),1,0) -> 0 | P97: =IF(I97=MAX(Tabelle4[[#This Row],[d32_el2_dl2_ff128-ep500]:[d64_el3_dl3_ff128-ep1000]]),1,0) -> 1 | Q97: =IF(J97=MAX(Tabelle4[[#This Row],[d32_el2_dl2_ff128-ep500]:[d64_el3_dl3_ff128-ep1000]]),1,0) -> 1 | R97: =IF(K97=MAX(Tabelle4[[#This Row],[d32_el2_dl2_ff128-ep500]:[d64_el3_dl3_ff128-ep1000]]),1,0) -> 1 | S97: =IF(L97=MAX(Tabelle4[[#This Row],[d32_el2_dl2_ff128-ep500]:[d64_el3_dl3_ff128-ep1000]]),1,0) -> 1 | T97: =IF(M97=MAX(Tabelle4[[#This Row],[d32_el2_dl2_ff128-ep500]:[d64_el3_dl3_ff128-ep1000]]),1,0) -> 1 | V97: =IF(H97=MIN(Tabelle4[[#This Row],[d32_el2_dl2_ff128-ep500]:[d64_el3_dl3_ff128-ep1000]]),1,0) -> 1 | W97: =IF(I97=MIN(Tabelle4[[#This Row],[d32_el2_dl2_ff128-ep500]:[d64_el3_dl3_ff128-ep1000]]),1,0) -> 0 | X97: =IF(J97=MIN(Tabelle4[[#This Row],[d32_el2_dl2_ff128-ep500]:[d64_el3_dl3_ff128-ep1000]]),1,0) -> 0 | Y97: =IF(K97=MIN(Tabelle4[[#This Row],[d32_el2_dl2_ff128-ep500]:[d64_el3_dl3_ff128-ep1000]]),1,0) -> 0 | Z97: =IF(L97=MIN(Tabelle4[[#This Row],[d32_el2_dl2_ff128-ep500]:[d64_el3_dl3_ff128-ep1000]]),1,0) -> 0 | AA97: =IF(M97=MIN(Tabelle4[[#This Row],[d32_el2_dl2_ff128-ep500]:[d64_el3_dl3_ff128-ep1000]]),1,0) -> 0
A98: 5 | B98: d64_el2_dl2_ff128-ep1000 | C98: ['ich', 'aufpassen', 'prod', 'ich', 'geben festhalten'] | D98: 0 | E98: =D98+E91 -> 72 | G98: 97 | H98: {=INDEX($D$2:$D$701, (ROW()-ROW($G$2))*7 + (COLUMN()-COLUMN($G$2)) + 1)} -> 0 | I98: {=INDEX($D$2:$D$701, (ROW()-ROW($G$2))*7 + (COLUMN()-COLUMN($G$2)) + 1)} -> 0 | J98: {=INDEX($D$2:$D$701, (ROW()-ROW($G$2))*7 + (COLUMN()-COLUMN($G$2)) + 1)} -> 4 | K98: {=INDEX($D$2:$D$701, (ROW()-ROW($G$2))*7 + (COLUMN()-COLUMN($G$2)) + 1)} -> 4 | L98: {=INDEX($D$2:$D$701, (ROW()-ROW($G$2))*7 + (COLUMN()-COLUMN($G$2)) + 1)} -> 0 | M98: {=INDEX($D$2:$D$701, (ROW()-ROW($G$2))*7 + (COLUMN()-COLUMN($G$2)) + 1)} -> 3 | O98: =IF(H98=MAX(Tabelle4[[#This Row],[d32_el2_dl2_ff128-ep500]:[d64_el3_dl3_ff128-ep1000]]),1,0) -> 0 | P98: =IF(I98=MAX(Tabelle4[[#This Row],[d32_el2_dl2_ff128-ep500]:[d64_el3_dl3_ff128-ep1000]]),1,0) -> 0 | Q98: =IF(J98=MAX(Tabelle4[[#This Row],[d32_el2_dl2_ff128-ep500]:[d64_el3_dl3_ff128-ep1000]]),1,0) -> 1 | R98: =IF(K98=MAX(Tabelle4[[#This Row],[d32_el2_dl2_ff128-ep500]:[d64_el3_dl3_ff128-ep1000]]),1,0) -> 1 | S98: =IF(L98=MAX(Tabelle4[[#This Row],[d32_el2_dl2_ff128-ep500]:[d64_el3_dl3_ff128-ep1000]]),1,0) -> 0 | T98: =IF(M98=MAX(Tabelle4[[#This Row],[d32_el2_dl2_ff128-ep500]:[d64_el3_dl3_ff128-ep1000]]),1,0) -> 0 | V98: =IF(H98=MIN(Tabelle4[[#This Row],[d32_el2_dl2_ff128-ep500]:[d64_el3_dl3_ff128-ep1000]]),1,0) -> 1 | W98: =IF(I98=MIN(Tabelle4[[#This Row],[d32_el2_dl2_ff128-ep500]:[d64_el3_dl3_ff128-ep1000]]),1,0) -> 1 | X98: =IF(J98=MIN(Tabelle4[[#This Row],[d32_el2_dl2_ff128-ep500]:[d64_el3_dl3_ff128-ep1000]]),1,0) -> 0 | Y98: =IF(K98=MIN(Tabelle4[[#This Row],[d32_el2_dl2_ff128-ep500]:[d64_el3_dl3_ff128-ep1000]]),1,0) -> 0 | Z98: =IF(L98=MIN(Tabelle4[[#This Row],[d32_el2_dl2_ff128-ep500]:[d64_el3_dl3_ff128-ep1000]]),1,0) -> 1 | AA98: =IF(M98=MIN(Tabelle4[[#This Row],[d32_el2_dl2_ff128-ep500]:[d64_el3_dl3_ff128-ep1000]]),1,0) -> 0
A99: 6 | B99: d64_el3_dl3_ff128-ep1000 | C99: ['ich', 'mögen', 'mit', 'prod', 'hineinstecken'] | D99: 2 | E99: =D99+E92 -> 76 | G99: 98 | H99: {=INDEX($D$2:$D$701, (ROW()-ROW($G$2))*7 + (COLUMN()-COLUMN($G$2)) + 1)} -> 5 | I99: {=INDEX($D$2:$D$701, (ROW()-ROW($G$2))*7 + (COLUMN()-COLUMN($G$2)) + 1)} -> 5 | J99: {=INDEX($D$2:$D$701, (ROW()-ROW($G$2))*7 + (COLUMN()-COLUMN($G$2)) + 1)} -> 5 | K99: {=INDEX($D$2:$D$701, (ROW()-ROW($G$2))*7 + (COLUMN()-COLUMN($G$2)) + 1)} -> 5 | L99: {=INDEX($D$2:$D$701, (ROW()-ROW($G$2))*7 + (COLUMN()-COLUMN($G$2)) + 1)} -> 5 | M99: {=INDEX($D$2:$D$701, (ROW()-ROW($G$2))*7 + (COLUMN()-COLUMN($G$2)) + 1)} -> 4 | O99: =IF(H99=MAX(Tabelle4[[#This Row],[d32_el2_dl2_ff128-ep500]:[d64_el3_dl3_ff128-ep1000]]),1,0) -> 1 | P99: =IF(I99=MAX(Tabelle4[[#This Row],[d32_el2_dl2_ff128-ep500]:[d64_el3_dl3_ff128-ep1000]]),1,0) -> 1 | Q99: =IF(J99=MAX(Tabelle4[[#This Row],[d32_el2_dl2_ff128-ep500]:[d64_el3_dl3_ff128-ep1000]]),1,0) -> 1 | R99: =IF(K99=MAX(Tabelle4[[#This Row],[d32_el2_dl2_ff128-ep500]:[d64_el3_dl3_ff128-ep1000]]),1,0) -> 1 | S99: =IF(L99=MAX(Tabelle4[[#This Row],[d32_el2_dl2_ff128-ep500]:[d64_el3_dl3_ff128-ep1000]]),1,0) -> 1 | T99: =IF(M99=MAX(Tabelle4[[#This Row],[d32_el2_dl2_ff128-ep500]:[d64_el3_dl3_ff128-ep1000]]),1,0) -> 0 | V99: =IF(H99=MIN(Tabelle4[[#This Row],[d32_el2_dl2_ff128-ep500]:[d64_el3_dl3_ff128-ep1000]]),1,0) -> 0 | W99: =IF(I99=MIN(Tabelle4[[#This Row],[d32_el2_dl2_ff128-ep500]:[d64_el3_dl3_ff128-ep1000]]),1,0) -> 0 | X99: =IF(J99=MIN(Tabelle4[[#This Row],[d32_el2_dl2_ff128-ep500]:[d64_el3_dl3_ff128-ep1000]]),1,0) -> 0 | Y99: =IF(K99=MIN(Tabelle4[[#This Row],[d32_el2_dl2_ff128-ep500]:[d64_el3_dl3_ff128-ep1000]]),1,0) -> 0 | Z99: =IF(L99=MIN(Tabelle4[[#This Row],[d32_el2_dl2_ff128-ep500]:[d64_el3_dl3_ff128-ep1000]]),1,0) -> 0 | AA99: =IF(M99=MIN(Tabelle4[[#This Row],[d32_el2_dl2_ff128-ep500]:[d64_el3_dl3_ff128-ep1000]]),1,0) -> 1
A100: 0 | B100: 15 | C100: Hast du Lust, etwas zu unternehmen? | E100: =D100+E93 -> 0 | G100: 99 | H100: {=INDEX($D$2:$D$701, (ROW()-ROW($G$2))*7 + (COLUMN()-COLUMN($G$2)) + 1)} -> 7 | I100: {=INDEX($D$2:$D$701, (ROW()-ROW($G$2))*7 + (COLUMN()-COLUMN($G$2)) + 1)} -> 5 | J100: {=INDEX($D$2:$D$701, (ROW()-ROW($G$2))*7 + (COLUMN()-COLUMN($G$2)) + 1)} -> 0 | K100: {=INDEX($D$2:$D$701, (ROW()-ROW($G$2))*7 + (COLUMN()-COLUMN($G$2)) + 1)} -> 0 | L100: {=INDEX($D$2:$D$701, (ROW()-ROW($G$2))*7 + (COLUMN()-COLUMN($G$2)) + 1)} -> 3 | M100: {=INDEX($D$2:$D$701, (ROW()-ROW($G$2))*7 + (COLUMN()-COLUMN($G$2)) + 1)} -> 3 | O100: =IF(H100=MAX(Tabelle4[[#This Row],[d32_el2_dl2_ff128-ep500]:[d64_el3_dl3_ff128-ep1000]]),1,0) -> 1 | P100: =IF(I100=MAX(Tabelle4[[#This Row],[d32_el2_dl2_ff128-ep500]:[d64_el3_dl3_ff128-ep1000]]),1,0) -> 0 | Q100: =IF(J100=MAX(Tabelle4[[#This Row],[d32_el2_dl2_ff128-ep500]:[d64_el3_dl3_ff128-ep1000]]),1,0) -> 0 | R100: =IF(K100=MAX(Tabelle4[[#This Row],[d32_el2_dl2_ff128-ep500]:[d64_el3_dl3_ff128-ep1000]]),1,0) -> 0 | S100: =IF(L100=MAX(Tabelle4[[#This Row],[d32_el2_dl2_ff128-ep500]:[d64_el3_dl3_ff128-ep1000]]),1,0) -> 0 | T100: =IF(M100=MAX(Tabelle4[[#This Row],[d32_el2_dl2_ff128-ep500]:[d64_el3_dl3_ff128-ep1000]]),1,0) -> 0 | V100: =IF(H100=MIN(Tabelle4[[#This Row],[d32_el2_dl2_ff128-ep500]:[d64_el3_dl3_ff128-ep1000]]),1,0) -> 0 | W100: =IF(I100=MIN(Tabelle4[[#This Row],[d32_el2_dl2_ff128-ep500]:[d64_el3_dl3_ff128-ep1000]]),1,0) -> 0 | X100: =IF(J100=MIN(Tabelle4[[#This Row],[d32_el2_dl2_ff128-ep500]:[d64_el3_dl3_ff128-ep1000]]),1,0) -> 1 | Y100: =IF(K100=MIN(Tabelle4[[#This Row],[d32_el2_dl2_ff128-ep500]:[d64_el3_dl3_ff128-ep1000]]),1,0) -> 1 | Z100: =IF(L100=MIN(Tabelle4[[#This Row],[d32_el2_dl2_ff128-ep500]:[d64_el3_dl3_ff128-ep1000]]),1,0) -> 0 | AA100: =IF(M100=MIN(Tabelle4[[#This Row],[d32_el2_dl2_ff128-ep500]:[d64_el3_dl3_ff128-ep1000]]),1,0) -> 0
...

Sheet Weniger Epochen
B1: Satz / Modell | C1: Inhalt | D1: Punkte [0-10] | E1: Punkte kumuliert | G1: Satz | H1: ep1000 | I1: ep750 | J1: ep500 | K1: ep200 | L1: ep100 | M1: ep50 | N1: ep25 | P1: 1000 | Q1: 750 | R1: 500 | S1: 200 | T1: 100 | U1: 50 | V1: 25 | X1: 1000 | Y1: 750 | Z1: 500 | AA1: 200 | AB1: 100 | AC1: 50 | AD1: 25
A2: 0 | B2: 1 | C2: Guten Morgen! | G2: 1 | H2: {=INDEX($D$2:$D$701, (ROW()-ROW($G$2))*8 + (COLUMN()-COLUMN($G$2)) + 1)} -> 1 | I2: {=INDEX($D$2:$D$701, (ROW()-ROW($G$2))*8 + (COLUMN()-COLUMN($G$2)) + 1)} -> 0 | J2: {=INDEX($D$2:$D$701, (ROW()-ROW($G$2))*8 + (COLUMN()-COLUMN($G$2)) + 1)} -> 0 | K2: {=INDEX($D$2:$D$701, (ROW()-ROW($G$2))*8 + (COLUMN()-COLUMN($G$2)) + 1)} -> 5 | L2: {=INDEX($D$2:$D$701, (ROW()-ROW($G$2))*8 + (COLUMN()-COLUMN($G$2)) + 1)} -> 5 | M2: {=INDEX($D$2:$D$701, (ROW()-ROW($G$2))*8 + (COLUMN()-COLUMN($G$2)) + 1)} -> 3 | N2: {=INDEX($D$2:$D$701, (ROW()-ROW($G$2))*8 + (COLUMN()-COLUMN($G$2)) + 1)} -> 5 | P2: =IF(H2=MAX(Tabelle6[[#This Row],[ep1000]:[ep25]]),1,0) -> 0 | Q2: =IF(I2=MAX(Tabelle6[[#This Row],[ep1000]:[ep25]]),1,0) -> 0 | R2: =IF(J2=MAX(Tabelle6[[#This Row],[ep1000]:[ep25]]),1,0) -> 0 | S2: =IF(K2=MAX(Tabelle6[[#This Row],[ep1000]:[ep25]]),1,0) -> 1 | T2: =IF(L2=MAX(Tabelle6[[#This Row],[ep1000]:[ep25]]),1,0) -> 1 | U2: =IF(M2=MAX(Tabelle6[[#This Row],[ep1000]:[ep25]]),1,0) -> 0 | V2: =IF(N2=MAX(Tabelle6[[#This Row],[ep1000]:[ep25]]),1,0) -> 1 | X2: =IF(H2=MIN(Tabelle6[[#This Row],[ep1000]:[ep25]]),1,0) -> 0 | Y2: =IF(I2=MIN(Tabelle6[[#This Row],[ep1000]:[ep25]]),1,0) -> 1 | Z2: =IF(J2=MIN(Tabelle6[[#This Row],[ep1000]:[ep25]]),1,0) -> 1 | AA2: =IF(K2=MIN(Tabelle6[[#This Row],[ep1000]:[ep25]]),1,0) -> 0 | AB2: =IF(L2=MIN(Tabelle6[[#This Row],[ep1000]:[ep25]]),1,0) -> 0 | AC2: =IF(M2=MIN(Tabelle6[[#This Row],[ep1000]:[ep25]]),1,0) -> 0 | AD2: =IF(N2=MIN(Tabelle6[[#This Row],[ep1000]:[ep25]]),1,0) -> 0
A3: 1 | B3: d64_el1_dl1_ff64-ep1000 | C3: ['morgen', 'sonne wandern', 'sonne wandern', 'sonne wandern', 'sonne wandern', 'sonne wandern', 'sonne wandern', 'sonne wandern', 'sonne wandern', 'sonne wandern', 'sonne wandern', 'sonne wandern', 'sonne wandern', 'sonne wandern', 'sonne wandern', 'sonne wandern', 'sonne wandern', 'sonne wandern', 'sonne wandern', 'sonne wandern'] | D3: =Auswertung!I2 -> 1 | E3: =D3 -> 1 | G3: 2 | H3: {=INDEX($D$2:$D$701, (ROW()-ROW($G$2))*8 + (COLUMN()-COLUMN($G$2)) + 1)} -> 7 | I3: {=INDEX($D$2:$D$701, (ROW()-ROW($G$2))*8 + (COLUMN()-COLUMN($G$2)) + 1)} -> 7 | J3: {=INDEX($D$2:$D$701, (ROW()-ROW($G$2))*8 + (COLUMN()-COLUMN($G$2)) + 1)} -> 7 | K3: {=INDEX($D$2:$D$701, (ROW()-ROW($G$2))*8 + (COLUMN()-COLUMN($G$2)) + 1)} -> 4 | L3: {=INDEX($D$2:$D$701, (ROW()-ROW($G$2))*8 + (COLUMN()-COLUMN($G$2)) + 1)} -> 4 | M3: {=INDEX($D$2:$D$701, (ROW()-ROW($G$2))*8 + (COLUMN()-COLUMN($G$2)) + 1)} -> 4 | N3: {=INDEX($D$2:$D$701, (ROW()-ROW($G$2))*8 + (COLUMN()-COLUMN($G$2)) + 1)} -> 2 | P3: =IF(H3=MAX(Tabelle6[[#This Row],[ep1000]:[ep25]]),1,0) -> 1 | Q3: =IF(I3=MAX(Tabelle6[[#This Row],[ep1000]:[ep25]]),1,0) -> 1 | R3: =IF(J3=MAX(Tabelle6[[#This Row],[ep1000]:[ep25]]),1,0) -> 1 | S3: =IF(K3=MAX(Tabelle6[[#This Row],[ep1000]:[ep25]]),1,0) -> 0 | T3: =IF(L3=MAX(Tabelle6[[#This Row],[ep1000]:[ep25]]),1,0) -> 0 | U3: =IF(M3=MAX(Tabelle6[[#This Row],[ep1000]:[ep25]]),1,0) -> 0 | V3: =IF(N3=MAX(Tabelle6[[#This Row],[ep1000]:[ep25]]),1,0) -> 0 | X3: =IF(H3=MIN(Tabelle6[[#This Row],[ep1000]:[ep25]]),1,0) -> 0 | Y3: =IF(I3=MIN(Tabelle6[[#This Row],[ep1000]:[ep25]]),1,0) -> 0 | Z3: =IF(J3=MIN(Tabelle6[[#This Row],[ep1000]:[ep25]]),1,0) -> 0 | AA3: =IF(K3=MIN(Tabelle6[[#This Row],[ep1000]:[ep25]]),1,0) -> 0 | AB3: =IF(L3=MIN(Tabelle6[[#This Row],[ep1000]:[ep25]]),1,0) -> 0 | AC3: =IF(M3=MIN(Tabelle6[[#This Row],[ep1000]:[ep25]]),1,0) -> 0 | AD3: =IF(N3=MIN(Tabelle6[[#This Row],[ep1000]:[ep25]]),1,0) -> 1
A4: 2 | B4: d64_el1_dl1_ff64-ep750 | C4: ['ich', 'verschwommen'] | D4: 0 | E4: =D4 -> 0 | G4: 3 | H4: {=INDEX($D$2:$D$701, (ROW()-ROW($G$2))*8 + (COLUMN()-COLUMN($G$2)) + 1)} -> 4 | I4: {=INDEX($D$2:$D$701, (ROW()-ROW($G$2))*8 + (COLUMN()-COLUMN($G$2)) + 1)} -> 7 | J4: {=INDEX($D$2:$D$701, (ROW()-ROW($G$2))*8 + (COLUMN()-COLUMN($G$2)) + 1)} -> 7 | K4: {=INDEX($D$2:$D$701, (ROW()-ROW($G$2))*8 + (COLUMN()-COLUMN($G$2)) + 1)} -> 3 | L4: {=INDEX($D$2:$D$701, (ROW()-ROW($G$2))*8 + (COLUMN()-COLUMN($G$2)) + 1)} -> 3 | M4: {=INDEX($D$2:$D$701, (ROW()-ROW($G$2))*8 + (COLUMN()-COLUMN($G$2)) + 1)} -> 9 | N4: {=INDEX($D$2:$D$701, (ROW()-ROW($G$2))*8 + (COLUMN()-COLUMN($G$2)) + 1)} -> 10 | P4: =IF(H4=MAX(Tabelle6[[#This Row],[ep1000]:[ep25]]),1,0) -> 0 | Q4: =IF(I4=MAX(Tabelle6[[#This Row],[ep1000]:[ep25]]),1,0) -> 0 | R4: =IF(J4=MAX(Tabelle6[[#This Row],[ep1000]:[ep25]]),1,0) -> 0 | S4: =IF(K4=MAX(Tabelle6[[#This Row],[ep1000]:[ep25]]),1,0) -> 0 | T4: =IF(L4=MAX(Tabelle6[[#This Row],[ep1000]:[ep25]]),1,0) -> 0 | U4: =IF(M4=MAX(Tabelle6[[#This Row],[ep1000]:[ep25]]),1,0) -> 0 | V4: =IF(N4=MAX(Tabelle6[[#This Row],[ep1000]:[ep25]]),1,0) -> 1 | X4: =IF(H4=MIN(Tabelle6[[#This Row],[ep1000]:[ep25]]),1,0) -> 0 | Y4: =IF(I4=MIN(Tabelle6[[#This Row],[ep1000]:[ep25]]),1,0) -> 0 | Z4: =IF(J4=MIN(Tabelle6[[#This Row],[ep1000]:[ep25]]),1,0) -> 0 | AA4: =IF(K4=MIN(Tabelle6[[#This Row],[ep1000]:[ep25]]),1,0) -> 1 | AB4: =IF(L4=MIN(Tabelle6[[#This Row],[ep1000]:[ep25]]),1,0) -> 1 | AC4: =IF(M4=MIN(Tabelle6[[#This Row],[ep1000]:[ep25]]),1,0) -> 0 | AD4: =IF(N4=MIN(Tabelle6[[#This Row],[ep1000]:[ep25]]),1,0) -> 0
A5: 3 | B5: d64_el1_dl1_ff64-ep500 | C5: ['ich', 'kochen', 'ich', 'verschwommen'] | D5: 0 | E5: =D5 -> 0 | G5: 4 | H5: {=INDEX($D$2:$D$701, (ROW()-ROW($G$2))*8 + (COLUMN()-COLUMN($G$2)) + 1)} -> 6 | I5: {=INDEX($D$2:$D$701, (ROW()-ROW($G$2))*8 + (COLUMN()-COLUMN($G$2)) + 1)} -> 8 | J5: {=INDEX($D$2:$D$701, (ROW()-ROW($G$2))*8 + (COLUMN()-COLUMN($G$2)) + 1)} -> 8 | K5: {=INDEX($D$2:$D$701, (ROW()-ROW($G$2))*8 + (COLUMN()-COLUMN($G$2)) + 1)} -> 5 | L5: {=INDEX($D$2:$D$701, (ROW()-ROW($G$2))*8 + (COLUMN()-COLUMN($G$2)) + 1)} -> 5 | M5: {=INDEX($D$2:$D$701, (ROW()-ROW($G$2))*8 + (COLUMN()-COLUMN($G$2)) + 1)} -> 5 | N5: {=INDEX($D$2:$D$701, (ROW()-ROW($G$2))*8 + (COLUMN()-COLUMN($G$2)) + 1)} -> 8 | P5: =IF(H5=MAX(Tabelle6[[#This Row],[ep1000]:[ep25]]),1,0) -> 0 | Q5: =IF(I5=MAX(Tabelle6[[#This Row],[ep1000]:[ep25]]),1,0) -> 1 | R5: =IF(J5=MAX(Tabelle6[[#This Row],[ep1000]:[ep25]]),1,0) -> 1 | S5: =IF(K5=MAX(Tabelle6[[#This Row],[ep1000]:[ep25]]),1,0) -> 0 | T5: =IF(L5=MAX(Tabelle6[[#This Row],[ep1000]:[ep25]]),1,0) -> 0 | U5: =IF(M5=MAX(Tabelle6[[#This Row],[ep1000]:[ep25]]),1,0) -> 0 | V5: =IF(N5=MAX(Tabelle6[[#This Row],[ep1000]:[ep25]]),1,0) -> 1 | X5: =IF(H5=MIN(Tabelle6[[#This Row],[ep1000]:[ep25]]),1,0) -> 0 | Y5: =IF(I5=MIN(Tabelle6[[#This Row],[ep1000]:[ep25]]),1,0) -> 0 | Z5: =IF(J5=MIN(Tabelle6[[#This Row],[ep1000]:[ep25]]),1,0) -> 0 | AA5: =IF(K5=MIN(Tabelle6[[#This Row],[ep1000]:[ep25]]),1,0) -> 1 | AB5: =IF(L5=MIN(Tabelle6[[#This Row],[ep1000]:[ep25]]),1,0) -> 1 | AC5: =IF(M5=MIN(Tabelle6[[#This Row],[ep1000]:[ep25]]),1,0) -> 1 | AD5: =IF(N5=MIN(Tabelle6[[#This Row],[ep1000]:[ep25]]),1,0) -> 0
A6: 4 | B6: d64_el1_dl1_ff64-ep200 | C6: ['morgen', 'kochen'] | D6: 5 | E6: =D6 -> 5 | G6: 5 | H6: {=INDEX($D$2:$D$701, (ROW()-ROW($G$2))*8 + (COLUMN()-COLUMN($G$2)) + 1)} -> 8 | I6: {=INDEX($D$2:$D$701, (ROW()-ROW($G$2))*8 + (COLUMN()-COLUMN($G$2)) + 1)} -> 7 | J6: {=INDEX($D$2:$D$701, (ROW()-ROW($G$2))*8 + (COLUMN()-COLUMN($G$2)) + 1)} -> 6 | K6: {=INDEX($D$2:$D$701, (ROW()-ROW($G$2))*8 + (COLUMN()-COLUMN($G$2)) + 1)} -> 9 | L6: {=INDEX($D$2:$D$701, (ROW()-ROW($G$2))*8 + (COLUMN()-COLUMN($G$2)) + 1)} -> 2 | M6: {=INDEX($D$2:$D$701, (ROW()-ROW($G$2))*8 + (COLUMN()-COLUMN($G$2)) + 1)} -> 3 | N6: {=INDEX($D$2:$D$701, (ROW()-ROW($G$2))*8 + (COLUMN()-COLUMN($G$2)) + 1)} -> 3 | P6: =IF(H6=MAX(Tabelle6[[#This Row],[ep1000]:[ep25]]),1,0) -> 0 | Q6: =IF(I6=MAX(Tabelle6[[#This Row],[ep1000]:[ep25]]),1,0) -> 0 | R6: =IF(J6=MAX(Tabelle6[[#This Row],[ep1000]:[ep25]]),1,0) -> 0 | S6: =IF(K6=MAX(Tabelle6[[#This Row],[ep1000]:[ep25]]),1,0) -> 1 | T6: =IF(L6=MAX(Tabelle6[[#This Row],[ep1000]:[ep25]]),1,0) -> 0 | U6: =IF(M6=MAX(Tabelle6[[#This Row],[ep1000]:[ep25]]),1,0) -> 0 | V6: =IF(N6=MAX(Tabelle6[[#This Row],[ep1000]:[ep25]]),1,0) -> 0 | X6: =IF(H6=MIN(Tabelle6[[#This Row],[ep1000]:[ep25]]),1,0) -> 0 | Y6: =IF(I6=MIN(Tabelle6[[#This Row],[ep1000]:[ep25]]),1,0) -> 0 | Z6: =IF(J6=MIN(Tabelle6[[#This Row],[ep1000]:[ep25]]),1,0) -> 0 | AA6: =IF(K6=MIN(Tabelle6[[#This Row],[ep1000]:[ep25]]),1,0) -> 0 | AB6: =IF(L6=MIN(Tabelle6[[#This Row],[ep1000]:[ep25]]),1,0) -> 1 | AC6: =IF(M6=MIN(Tabelle6[[#This Row],[ep1000]:[ep25]]),1,0) -> 0 | AD6: =IF(N6=MIN(Tabelle6[[#This Row],[ep1000]:[ep25]]),1,0) -> 0
A7: 5 | B7: d64_el1_dl1_ff64-ep100 | C7: ['morgen', 'kochen'] | D7: 5 | E7: =D7 -> 5 | G7: 6 | H7: {=INDEX($D$2:$D$701, (ROW()-ROW($G$2))*8 + (COLUMN()-COLUMN($G$2)) + 1)} -> 2 | I7: {=INDEX($D$2:$D$701, (ROW()-ROW($G$2))*8 + (COLUMN()-COLUMN($G$2)) + 1)} -> 6 | J7: {=INDEX($D$2:$D$701, (ROW()-ROW($G$2))*8 + (COLUMN()-COLUMN($G$2)) + 1)} -> 6 | K7: {=INDEX($D$2:$D$701, (ROW()-ROW($G$2))*8 + (COLUMN()-COLUMN($G$2)) + 1)} -> 6 | L7: {=INDEX($D$2:$D$701, (ROW()-ROW($G$2))*8 + (COLUMN()-COLUMN($G$2)) + 1)} -> 4 | M7: {=INDEX($D$2:$D$701, (ROW()-ROW($G$2))*8 + (COLUMN()-COLUMN($G$2)) + 1)} -> 6 | N7: {=INDEX($D$2:$D$701, (ROW()-ROW($G$2))*8 + (COLUMN()-COLUMN($G$2)) + 1)} -> 2 | P7: =IF(H7=MAX(Tabelle6[[#This Row],[ep1000]:[ep25]]),1,0) -> 0 | Q7: =IF(I7=MAX(Tabelle6[[#This Row],[ep1000]:[ep25]]),1,0) -> 1 | R7: =IF(J7=MAX(Tabelle6[[#This Row],[ep1000]:[ep25]]),1,0) -> 1 | S7: =IF(K7=MAX(Tabelle6[[#This Row],[ep1000]:[ep25]]),1,0) -> 1 | T7: =IF(L7=MAX(Tabelle6[[#This Row],[ep1000]:[ep25]]),1,0) -> 0 | U7: =IF(M7=MAX(Tabelle6[[#This Row],[ep1000]:[ep25]]),1,0) -> 1 | V7: =IF(N7=MAX(Tabelle6[[#This Row],[ep1000]:[ep25]]),1,0) -> 0 | X7: =IF(H7=MIN(Tabelle6[[#This Row],[ep1000]:[ep25]]),1,0) -> 1 | Y7: =IF(I7=MIN(Tabelle6[[#This Row],[ep1000]:[ep25]]),1,0) -> 0 | Z7: =IF(J7=MIN(Tabelle6[[#This Row],[ep1000]:[ep25]]),1,0) -> 0 | AA7: =IF(K7=MIN(Tabelle6[[#This Row],[ep1000]:[ep25]]),1,0) -> 0 | AB7: =IF(L7=MIN(Tabelle6[[#This Row],[ep1000]:[ep25]]),1,0) -> 0 | AC7: =IF(M7=MIN(Tabelle6[[#This Row],[ep1000]:[ep25]]),1,0) -> 0 | AD7: =IF(N7=MIN(Tabelle6[[#This Row],[ep1000]:[ep25]]),1,0) -> 1
A8: 6 | B8: d64_el1_dl1_ff64-ep50 | C8: ['morgen', 'abend', 'abend', 'abend', 'abend', 'abend', 'abend', 'abend', 'abend', 'abend', 'abend', 'abend', 'abend', 'abend', 'abend', 'abend', 'abend', 'abend', 'abend', 'abend'] | D8: 3 | E8: =D8 -> 3 | G8: 7 | H8: {=INDEX($D$2:$D$701, (ROW()-ROW($G$2))*8 + (COLUMN()-COLUMN($G$2)) + 1)} -> 1 | I8: {=INDEX($D$2:$D$701, (ROW()-ROW($G$2))*8 + (COLUMN()-COLUMN($G$2)) + 1)} -> 0 | J8: {=INDEX($D$2:$D$701, (ROW()-ROW($G$2))*8 + (COLUMN()-COLUMN($G$2)) + 1)} -> 0 | K8: {=INDEX($D$2:$D$701, (ROW()-ROW($G$2))*8 + (COLUMN()-COLUMN($G$2)) + 1)} -> 0 | L8: {=INDEX($D$2:$D$701, (ROW()-ROW($G$2))*8 + (COLUMN()-COLUMN($G$2)) + 1)} -> 0 | M8: {=INDEX($D$2:$D$701, (ROW()-ROW($G$2))*8 + (COLUMN()-COLUMN($G$2)) + 1)} -> 0 | N8: {=INDEX($D$2:$D$701, (ROW()-ROW($G$2))*8 + (COLUMN()-COLUMN($G$2)) + 1)} -> 0 | P8: =IF(H8=MAX(Tabelle6[[#This Row],[ep1000]:[ep25]]),1,0) -> 1 | Q8: =IF(I8=MAX(Tabelle6[[#This Row],[ep1000]:[ep25]]),1,0) -> 0 | R8: =IF(J8=MAX(Tabelle6[[#This Row],[ep1000]:[ep25]]),1,0) -> 0 | S8: =IF(K8=MAX(Tabelle6[[#This Row],[ep1000]:[ep25]]),1,0) -> 0 | T8: =IF(L8=MAX(Tabelle6[[#This Row],[ep1000]:[ep25]]),1,0) -> 0 | U8: =IF(M8=MAX(Tabelle6[[#This Row],[ep1000]:[ep25]]),1,0) -> 0 | V8: =IF(N8=MAX(Tabelle6[[#This Row],[ep1000]:[ep25]]),1,0) -> 0 | X8: =IF(H8=MIN(Tabelle6[[#This Row],[ep1000]:[ep25]]),1,0) -> 0 | Y8: =IF(I8=MIN(Tabelle6[[#This Row],[ep1000]:[ep25]]),1,0) -> 1 | Z8: =IF(J8=MIN(Tabelle6[[#This Row],[ep1000]:[ep25]]),1,0) -> 1 | AA8: =IF(K8=MIN(Tabelle6[[#This Row],[ep1000]:[ep25]]),1,0) -> 1 | AB8: =IF(L8=MIN(Tabelle6[[#This Row],[ep1000]:[ep25]]),1,0) -> 1 | AC8: =IF(M8=MIN(Tabelle6[[#This Row],[ep1000]:[ep25]]),1,0) -> 1 | AD8: =IF(N8=MIN(Tabelle6[[#This Row],[ep1000]:[ep25]]),1,0) -> 1
